Workbook

Sheet READ_ME
B2: Smart VAs LLC — Monthly Financial Model
B4: Currency | C4: USD. All amounts in whole US dollars unless a line is labelled as a percentage, a ratio or a day count.
B5: Basis of accounting | C5: Accrual, per the seller general ledger and confirmed in the QOE engagement correspondence.
B6: Period covered | C6: June 2024 through June 2026 (25 consecutive months).
B7: Prepared for | C7: GP Partners — Quality of Earnings engagement.
B9: Scope
C11: The engagement email chain descopes the original request. The most recent instruction is to focus on the monthly financial statements only, with the trial balance rebuild, KPI set, labour-versus-revenue breakdown and the software/systems inventory deferred to a separate project. This workbook therefore contains the monthly income statement, balance sheet and statement of cash flows, together with the supporting schedules required by the finance memo, plus the month-over-month working capital schedule and the DSO section requested in the chain.
B13: Items deliberately excluded (deferred to the separate project)
C14: Annual trial balance rebuild; KPI/ratio set (gross profit margin against all labour, net profit margin, ROA, current ratio, cash ratio, D/E, D/A); the direct-labour-and-COGS-against-revenue tab; and the schedule defining the software, apps, programs and systems tied to the business.
B16: Source data
B18: Trial balance | C18: TB_20240531.pdf — Smart VAs LLC trial balance as of 31 May 2024. Transcribed in full; debits and credits both total 424,147.41, which agrees to the source document.
B19: General ledger | C19: 1_GeneralLedger_MoM_Combined.pdf — 925 pages, comprising 25 separate monthly ledger extracts concatenated into one file.
B20: Rows extracted | C20: 15,699 ledger lines. This figure was verified against an independent count of every record block in the PDF: 15,699 blocks, none missing a transaction date, none missing an amount.
B22: How the model is wired
B24: GL Data tab | C24: The only input tab. Column D holds the opening trial balance at 31 May 2024; columns E onward hold monthly ledger activity by account. All figures are debit-positive and credit-negative. Blue text marks a hardcoded input.
B25: Monthly Financials tab | C25: Every figure is a formula. Teal text marks a value pulled across from the GL Data tab; black marks a calculation within the tab. Nothing on this tab is typed in.
B26: Account mapping | C26: Each of the 76 accounts in the ledger and trial balance maps to exactly one statement line — no account is unmapped and none is counted twice. Statement lines pull their accounts by name, so adding an account to GL Data with an existing statement line flows through automatically.
B27: Recalculation | C27: Iterative calculation is enabled, as required by the marketing memo, because the modeled line of credit interest is circular (interest feeds net income, which feeds cash, which feeds the draw).
B29: Ledger sign conventions (fitted, not assumed)
C31: The ledger export reports each line as the change in that account's own natural balance rather than as an explicit debit or credit. Three accounts do not follow the convention their trial balance position implies, and the treatment below was established by testing which reading makes the ledger balance, not by assumption:
B32: Owner's Pay & Personal Expenses | C32: Behaves as credit-natural in the ledger. Confirmed by the 1 January 2025 and 1 January 2026 year-end entries, which close this account into Retained Earnings and only balance under this reading.
B33: Discounts and Refund | C33: Behave as credit-natural, i.e. reported as negative revenue rather than as debit-side contra-revenue.
B34: Result | C34: Under these conventions the ledger balances to (123.60) in total across all 25 months and all 15,699 lines. Eleven individual months balance to within one dollar.
B36: Accounts Receivable — derived figure
C38: This is the one number in the model that the ledger does not directly support, and it should be read as derived rather than reported.
C39: The ledger export omits the accounts receivable side of both customer invoices and customer payments. An invoice appears only as the revenue credit and the merchant fee debit; the matching payment appears only as the cash debit. The two net correctly when both fall in the same month — a customer billed 1,000 with a 29.30 merchant fee shows 970.70 of cash — but a receivable outstanding at a month end has no ledger line.
C40: The residual imbalance in each month is therefore booked to accounts receivable, on the GL Data tab, as a row labelled "A/R timing plug (derived)". It is a formula, not a hardcode, so it stays consistent if the underlying data changes.
B41: Size of the adjustment | C41: Small and self-correcting. Receivables open at 533 per the trial balance and close at 656 in June 2026, moving within a band of roughly plus or minus a few thousand dollars.
B42: Known exception | C42: November and December 2025 show a negative derived receivable of (6,579) and (2,769). This is a timing artefact of the missing ledger lines, not a customer credit balance. A ledger export that includes the A/R distribution lines would resolve it.
B44: Judgements and presentation choices
B46: Merchant fees | C46: Credit card fees are presented within operating expenses under "Fees and Charges" rather than as a cost of revenue. They run at roughly 2 to 3 per cent of revenue and are invoice-linked, so a reviewer may prefer them above the gross profit line. Reclassifying them would reduce gross margin and leave net income unchanged.
B47: Credit cards in cash flow | C47: Credit card balances are treated as operating rather than financing, on the basis that the cards are used to settle operating expenses rather than as a funding source.
B48: Intercompany balances | C48: The "Meet 5-star VAs" sub-accounts and "Intercompany - Meet 5-Star Pros" are carried as current assets (amounts due from affiliates), consistent with their position in the trial balance. These are related-party balances and warrant separate diligence.
B49: Income taxes | C49: No entity-level income tax expense is recorded in the ledger, consistent with a pass-through LLC. The tax schedule shows payroll tax and taxes and licences only.
B50: Depreciation | C50: Accumulated depreciation shows no movement across the 25 months. Fixed assets are carried at the trial balance amount throughout and no depreciation expense is recorded in the period.
B52: Line of credit mechanic
C54: The finance memo requires that a negative ending cash balance trigger a line of credit draw and the corresponding interest expense. The mechanic is built and live in the model.
B55: Status in this period | C55: It does not trigger. Cash is positive in every month, rising from 23,371 at June 2024 to 87,174 at June 2026. The modeled draw is therefore nil throughout and the interest expense it produces is nil.
B56: Assumptions | C56: Minimum cash balance and the annual interest rate are blue input cells in Schedule 5. They are modelling assumptions, not figures taken from the ledger.
B58: Checks built into the model
B60: Balance sheet | C60: Row "Check: Total Assets less Total Liabilities & Equity" returns nil in the opening column and in every one of the 25 months.
B61: Cash flow | C61: Row "Check: Ending Cash less Cash per Balance Sheet" returns nil in every month, so the cash flow statement reconciles to the balance sheet rather than being presented alongside it.
B62: Trial balance | C62: The opening column of the balance sheet is built from the 31 May 2024 trial balance, which self-balances at 424,147.41.

Sheet GL Data
A1: Smart VAs LLC
A2: General Ledger — Monthly Activity by Account (debit-positive / credit-negative)
A3: Currency: USD
A5: GL / TB Account | B5: Statement Line | C5: Class | D5: Opening TB 5/31/2024 | E5: Jun-24 | F5: Jul-24 | G5: Aug-24 | H5: Sep-24 | I5: Oct-24 | J5: Nov-24 | K5: Dec-24 | L5: Jan-25 | M5: Feb-25 | N5: Mar-25 | O5: Apr-25 | P5: May-25 | Q5: Jun-25 | R5: Jul-25 | S5: Aug-25 | T5: Sep-25 | U5: Oct-25 | V5: Nov-25 | W5: Dec-25 | X5: Jan-26 | Y5: Feb-26 | Z5: Mar-26 | AA5: Apr-26 | AB5: May-26 | AC5: Jun-26
A6: AMEX Credit Card | B6: AMEX Credit Card | C6: L | D6: -1252.3 | E6: -140.91 | F6: -576.74 | G6: -44.8 | H6: 316.99 | I6: 439.82 | J6: -562.91 | K6: -549.43 | L6: 576.2 | M6: 359.96 | N6: 193.95 | O6: 167.91 | P6: 50.42 | Q6: -1037.24 | R6: 853.4 | S6: 229.53 | T6: -2140.47 | U6: -1224.05 | V6: 2444.01 | W6: 410.33 | X6: -2494.02 | Y6: -1279.24 | Z6: 4556.23 | AA6: -374.82 | AB6: -9.45 | AC6: -44.7
A7: Accounts Receivable | B7: Accounts Receivable | C7: A | D7: 532.65 | E7: 0 | F7: 0 | G7: 0 | H7: 0 | I7: 0 | J7: 0 | K7: 0 | L7: 0 | M7: 0 | N7: 16.99 | O7: -16.99 | P7: 0 | Q7: 0 | R7: 0 | S7: 284.4 | T7: -284.4 | U7: 0 | V7: 0 | W7: 0 | X7: 0 | Y7: 0 | Z7: 0 | AA7: 0 | AB7: 0 | AC7: 0
A8: Accrued Retirement | B8: Accrued Retirement | C8: L | D8: -1289.88 | E8: 859.92 | F8: 45 | G8: 45 | H8: 0 | I8: 339.96 | J8: -339.96 | K8: -339.96 | L8: -339.96 | M8: -339.96 | N8: -339.96 | O8: -339.96 | P8: -339.96 | Q8: 2379.72 | R8: 0 | S8: 0 | T8: -339.96 | U8: 339.96 | V8: 0 | W8: 0 | X8: 0 | Y8: 0 | Z8: 0 | AA8: 0 | AB8: 0 | AC8: 0
A9: Accum Depreciation | B9: Accumulated Depreciation | C9: XA | D9: -12754.39 | E9: 0 | F9: 0 | G9: 0 | H9: 0 | I9: 0 | J9: 0 | K9: 0 | L9: 0 | M9: 0 | N9: 0 | O9: 0 | P9: 0 | Q9: 0 | R9: 0 | S9: 0 | T9: 0 | U9: 0 | V9: 0 | W9: 0 | X9: 0 | Y9: 0 | Z9: 0 | AA9: 0 | AB9: 0 | AC9: 0
A10: Advances subject to Liquidation | B10: Advances subject to Liquidation | C10: A | D10: 302.46 | E10: 44.55 | F10: 98.1 | G10: 26.14 | H10: -223.76 | I10: -16.16 | J10: 38.46 | K10: 333.97 | L10: -266.85 | M10: -176.12 | N10: -265.74 | O10: 245.61 | P10: -22.84 | Q10: 0 | R10: 0 | S10: -76.61 | T10: -41.21 | U10: 0 | V10: 0 | W10: 0 | X10: 0 | Y10: 0 | Z10: 0 | AA10: 0 | AB10: 0 | AC10: 0
A11: Advances to Contractors | B11: Advances to Contractors | C11: A | D11: 414.91 | E11: -223.5 | F11: 680.46 | G11: -89.25 | H11: 840.65 | I11: -515.86 | J11: 818.26 | K11: -442.03 | L11: -200.99 | M11: -177.67 | N11: 0.55 | O11: 115.28 | P11: 117.99 | Q11: -233.02 | R11: 194.68 | S11: 490.52 | T11: -405.44 | U11: -164.17 | V11: 201.48 | W11: 42.3 | X11: -65.6 | Y11: -725.36 | Z11: -296.43 | AA11: -189.39 | AB11: -82.72 | AC11: -105.65
A12: Amex Delta Credit Card | B12: Amex Delta Credit Card | C12: L | D12: -14166 | E12: -2433.24 | F12: 5490.63 | G12: 2062.26 | H12: 2036.7 | I12: -226.17 | J12: -58.21 | K12: -177.44 | L12: -2532.27 | M12: 102.24 | N12: -2014.36 | O12: 79.67 | P12: 10.31 | Q12: 2752.99 | R12: 290.81 | S12: 4062.32 | T12: 3088.99 | U12: 215.98 | V12: 168.65 | W12: -635.98 | X12: -2371.96 | Y12: 2940.77 | Z12: 98.78 | AA12: -62.08 | AB12: 143.75 | AC12: -929.51
A13: Charitable Contributions | B13: Charitable Contributions | C13: E | D13: 0 | E13: 0 | F13: 0 | G13: 0 | H13: 0 | I13: 0 | J13: 0 | K13: 0 | L13: 0 | M13: 0 | N13: 0 | O13: 0 | P13: 0 | Q13: 0 | R13: 0 | S13: 0 | T13: 0 | U13: 100 | V13: 0 | W13: 200 | X13: 100 | Y13: 100 | Z13: 100 | AA13: 100 | AB13: 100 | AC13: 100
A14: Chase Credit Card 4 (1892) | B14: Chase Credit Card 4 (1892) | C14: L | D14: -1889.3 | E14: 453.73 | F14: -75.17 | G14: -444.22 | H14: -487.91 | I14: -3093.67 | J14: 2133.37 | K14: -2431.52 | L14: -2362.43 | M14: -413.58 | N14: 31.53 | O14: 1733.81 | P14: -722.67 | Q14: 486.36 | R14: 1527.01 | S14: 4752.36 | T14: -649.46 | U14: -604.13 | V14: 1209.32 | W14: -963.81 | X14: 928.67 | Y14: -168.14 | Z14: 108.73 | AA14: -529.69 | AB14: 380.18 | AC14: -649.5
A15: Christmas Expenses Fund | B15: Christmas Expenses Fund | C15: L | D15: 0 | E15: 0 | F15: 0 | G15: -357.73 | H15: -450.57 | I15: -433.84 | J15: -427.7 | K15: 1669.84 | L15: 0 | M15: 0 | N15: 0 | O15: 0 | P15: 0 | Q15: 0 | R15: -807.41 | S15: 0 | T15: 0 | U15: 0 | V15: -684.16 | W15: 1491.57 | X15: 0 | Y15: 0 | Z15: 0 | AA15: 0 | AB15: 0 | AC15: 0
A16: Cost of Services:Contractors - Client Hours | B16: Contractors - Client Hours | C16: E | D16: 109119.97 | E16: 19394.04 | F16: 18266.33 | G16: 20915.87 | H16: 20818.06 | I16: 22253.11 | J16: 21849.94 | K16: 18495.84 | L16: 17320.71 | M16: 19492.66 | N16: 18326.41 | O16: 20629.36 | P16: 21453.48 | Q16: 21869.94 | R16: 21439.57 | S16: 25115.95 | T16: 24359.34 | U16: 24557.02 | V16: 23570.34 | W16: 21932.71 | X16: 21068.2 | Y16: 24105.05 | Z16: 21329.32 | AA16: 23432.68 | AB16: 22967.15 | AC16: 22258.75
A17: Cost of Services:Contractors - Idle Time | B17: Contractors - Idle Time | C17: E | D17: 6474.17 | E17: 1166.36 | F17: 817.49 | G17: 899.16 | H17: 668.06 | I17: 763.66 | J17: 1547.32 | K17: 1484.27 | L17: 985.85 | M17: 856.37 | N17: 1072.85 | O17: 617.86 | P17: 534.89 | Q17: 732.63 | R17: 1252.22 | S17: 1004.05 | T17: 1130.93 | U17: 974.1 | V17: 1300.18 | W17: 1260.22 | X17: 1062.81 | Y17: 1311.04 | Z17: 1443.68 | AA17: 1059.39 | AB17: 1295.65 | AC17: 701.82
... A81: Wise Fund | B81: Wise Fund | C81: A | D81: 9.83 | E81: -3.63 | F81: 0 | G81: -3.65 | H81: 0 | I81: 0 | J81: 0 | K81: 0 | L81: 0 | M81: 0 | N81: 0 | O81: 0 | P81: 0 | Q81: 0 | R81: 0 | S81: 0 | T81: 0 | U81: 0 | V81: 0 | W81: 0 | X81: 0 | Y81: 0 | Z81: 0 | AA81: 0 | AB81: 0 | AC81: 0
A82: A/R timing plug (derived — see READ_ME) | B82: Accounts Receivable | C82: A | D82: 0 | E82: =-SUM(E6:E81) -> -2.0374813e-12 | F82: =-SUM(F6:F81) -> -3.7471137e-12 | G82: =-SUM(G6:G81) -> 715.46 | H82: =-SUM(H6:H81) -> 901.14 | I82: =-SUM(I6:I81) -> 867.68 | J82: =-SUM(J6:J81) -> 855.4 | K82: =-SUM(K6:K81) -> -3216.08 | L82: =-SUM(L6:L81) -> 1030.42 | ... AC82: =-SUM(AC6:AC81) -> -3.6379788e-12
A84: Opening equity at 5/31/2024 (balancing, per TB) | D84: 35592.74

Sheet Monthly Financials
A1: Smart VAs LLC
A2: Monthly Financial Statements — Income Statement, Balance Sheet & Statement of Cash Flows
A3: Currency: USD (all amounts in whole US dollars)
A4: Period: June 2024 – June 2026 (25 months) | Basis: Accrual | Source: Seller general ledger & 5/31/2024 trial balance
A6: INCOME STATEMENT
B7: TB 5/31/24 | C7: Jun-24 | D7: Jul-24 | E7: Aug-24 | F7: Sep-24 | G7: Oct-24 | H7: Nov-24 | I7: Dec-24 | J7: Jan-25 | K7: Feb-25 | L7: Mar-25 | M7: Apr-25 | N7: May-25 | O7: Jun-25 | P7: Jul-25 | Q7: Aug-25 | R7: Sep-25 | S7: Oct-25 | T7: Nov-25 | U7: Dec-25 | V7: Jan-26 | W7: Feb-26 | X7: Mar-26 | Y7: Apr-26 | Z7: May-26 | AA7: Jun-26
A8: Revenue
A9: Service Revenue | C9: =-SUMIFS('GL Data'!$E:$E,'GL Data'!$B:$B,$A9) -> 68051.11 | D9: =-SUMIFS('GL Data'!$F:$F,'GL Data'!$B:$B,$A9) -> 81627.01 | E9: =-SUMIFS('GL Data'!$G:$G,'GL Data'!$B:$B,$A9) -> 72116.4 | F9: =-SUMIFS('GL Data'!$H:$H,'GL Data'!$B:$B,$A9) -> 71580.32 | G9: =-SUMIFS('GL Data'!$I:$I,'GL Data'!$B:$B,$A9) -> 75657.75 | H9: =-SUMIFS('GL Data'!$J:$J,'GL Data'!$B:$B,$A9) -> 71033.56 | I9: =-SUMIFS('GL Data'!$K:$K,'GL Data'!$B:$B,$A9) -> 70881.91 | J9: =-SUMIFS('GL Data'!$L:$L,'GL Data'!$B:$B,$A9) -> 66313.39 | K9: =-SUMIFS('GL Data'!$M:$M,'GL Data'!$B:$B,$A9) -> 61919.05 | L9: =-SUMIFS('GL Data'!$N:$N,'GL Data'!$B:$B,$A9) -> 69485.32 | M9: =-SUMIFS('GL Data'!$O:$O,'GL Data'!$B:$B,$A9) -> 77448.33 | N9: =-SUMIFS('GL Data'!$P:$P,'GL Data'!$B:$B,$A9) -> 83272.41 | O9: =-SUMIFS('GL Data'!$Q:$Q,'GL Data'!$B:$B,$A9) -> 55987.5 | P9: =-SUMIFS('GL Data'!$R:$R,'GL Data'!$B:$B,$A9) -> 97281.23 | Q9: =-SUMIFS('GL Data'!$S:$S,'GL Data'!$B:$B,$A9) -> 65230.76 | R9: =-SUMIFS('GL Data'!$T:$T,'GL Data'!$B:$B,$A9) -> 78706.91 | S9: =-SUMIFS('GL Data'!$U:$U,'GL Data'!$B:$B,$A9) -> 98271.75 | T9: =-SUMIFS('GL Data'!$V:$V,'GL Data'!$B:$B,$A9) -> 83283.37 | U9: =-SUMIFS('GL Data'!$W:$W,'GL Data'!$B:$B,$A9) -> 81117.9 | V9: =-SUMIFS('GL Data'!$X:$X,'GL Data'!$B:$B,$A9) -> 95842.24 | W9: =-SUMIFS('GL Data'!$Y:$Y,'GL Data'!$B:$B,$A9) -> 65696.46 | X9: =-SUMIFS('GL Data'!$Z:$Z,'GL Data'!$B:$B,$A9) -> 69807.44 | Y9: =-SUMIFS('GL Data'!$AA:$AA,'GL Data'!$B:$B,$A9) -> 96105.92 | Z9: =-SUMIFS('GL Data'!$AB:$AB,'GL Data'!$B:$B,$A9) -> 80095.39 | AA9: =-SUMIFS('GL Data'!$AC:$AC,'GL Data'!$B:$B,$A9) -> 64477.22
A10: Smart VA Academy Revenue | C10: =-SUMIFS('GL Data'!$E:$E,'GL Data'!$B:$B,$A10) -> 8.43 | D10: =-SUMIFS('GL Data'!$F:$F,'GL Data'!$B:$B,$A10) -> 8.46 | E10: =-SUMIFS('GL Data'!$G:$G,'GL Data'!$B:$B,$A10) -> 8.5 | F10: =-SUMIFS('GL Data'!$H:$H,'GL Data'!$B:$B,$A10) -> 0 | G10: =-SUMIFS('GL Data'!$I:$I,'GL Data'!$B:$B,$A10) -> 69.91 | H10: =-SUMIFS('GL Data'!$J:$J,'GL Data'!$B:$B,$A10) -> 21.02 | I10: =-SUMIFS('GL Data'!$K:$K,'GL Data'!$B:$B,$A10) -> 30.44 | J10: =-SUMIFS('GL Data'!$L:$L,'GL Data'!$B:$B,$A10) -> 22.03 | K10: =-SUMIFS('GL Data'!$M:$M,'GL Data'!$B:$B,$A10) -> 73.41 | L10: =-SUMIFS('GL Data'!$N:$N,'GL Data'!$B:$B,$A10) -> 0 | M10: =-SUMIFS('GL Data'!$O:$O,'GL Data'!$B:$B,$A10) -> 62.46 | N10: =-SUMIFS('GL Data'!$P:$P,'GL Data'!$B:$B,$A10) -> 53.48 | O10: =-SUMIFS('GL Data'!$Q:$Q,'GL Data'!$B:$B,$A10) -> 96.66 | P10: =-SUMIFS('GL Data'!$R:$R,'GL Data'!$B:$B,$A10) -> 39.98 | Q10: =-SUMIFS('GL Data'!$S:$S,'GL Data'!$B:$B,$A10) -> 88.42 | R10: =-SUMIFS('GL Data'!$T:$T,'GL Data'!$B:$B,$A10) -> 8.69 | S10: =-SUMIFS('GL Data'!$U:$U,'GL Data'!$B:$B,$A10) -> 121.29 | T10: =-SUMIFS('GL Data'!$V:$V,'GL Data'!$B:$B,$A10) -> 8.39 | U10: =-SUMIFS('GL Data'!$W:$W,'GL Data'!$B:$B,$A10) -> 8.46 | V10: =-SUMIFS('GL Data'!$X:$X,'GL Data'!$B:$B,$A10) -> 8.41 | W10: =-SUMIFS('GL Data'!$Y:$Y,'GL Data'!$B:$B,$A10) -> 0 | X10: =-SUMIFS('GL Data'!$Z:$Z,'GL Data'!$B:$B,$A10) -> 19.82 | Y10: =-SUMIFS('GL Data'!$AA:$AA,'GL Data'!$B:$B,$A10) -> 0 | Z10: =-SUMIFS('GL Data'!$AB:$AB,'GL Data'!$B:$B,$A10) -> 0 | AA10: =-SUMIFS('GL Data'!$AC:$AC,'GL Data'!$B:$B,$A10) -> 0
A11: Unapplied Cash Payments | C11: =-SUMIFS('GL Data'!$E:$E,'GL Data'!$B:$B,$A11) -> 0 | D11: =-SUMIFS('GL Data'!$F:$F,'GL Data'!$B:$B,$A11) -> 0 | E11: =-SUMIFS('GL Data'!$G:$G,'GL Data'!$B:$B,$A11) -> 0 | F11: =-SUMIFS('GL Data'!$H:$H,'GL Data'!$B:$B,$A11) -> 0 | G11: =-SUMIFS('GL Data'!$I:$I,'GL Data'!$B:$B,$A11) -> 0 | H11: =-SUMIFS('GL Data'!$J:$J,'GL Data'!$B:$B,$A11) -> 0 | I11: =-SUMIFS('GL Data'!$K:$K,'GL Data'!$B:$B,$A11) -> 0 | J11: =-SUMIFS('GL Data'!$L:$L,'GL Data'!$B:$B,$A11) -> 0 | K11: =-SUMIFS('GL Data'!$M:$M,'GL Data'!$B:$B,$A11) -> 0 | L11: =-SUMIFS('GL Data'!$N:$N,'GL Data'!$B:$B,$A11) -> 0 | M11: =-SUMIFS('GL Data'!$O:$O,'GL Data'!$B:$B,$A11) -> 0 | N11: =-SUMIFS('GL Data'!$P:$P,'GL Data'!$B:$B,$A11) -> 0 | O11: =-SUMIFS('GL Data'!$Q:$Q,'GL Data'!$B:$B,$A11) -> 0 | P11: =-SUMIFS('GL Data'!$R:$R,'GL Data'!$B:$B,$A11) -> 0 | Q11: =-SUMIFS('GL Data'!$S:$S,'GL Data'!$B:$B,$A11) -> -741.78 | R11: =-SUMIFS('GL Data'!$T:$T,'GL Data'!$B:$B,$A11) -> 741.78 | S11: =-SUMIFS('GL Data'!$U:$U,'GL Data'!$B:$B,$A11) -> 0 | T11: =-SUMIFS('GL Data'!$V:$V,'GL Data'!$B:$B,$A11) -> 0 | U11: =-SUMIFS('GL Data'!$W:$W,'GL Data'!$B:$B,$A11) -> 0 | V11: =-SUMIFS('GL Data'!$X:$X,'GL Data'!$B:$B,$A11) -> 0 | W11: =-SUMIFS('GL Data'!$Y:$Y,'GL Data'!$B:$B,$A11) -> 0 | X11: =-SUMIFS('GL Data'!$Z:$Z,'GL Data'!$B:$B,$A11) -> 0 | Y11: =-SUMIFS('GL Data'!$AA:$AA,'GL Data'!$B:$B,$A11) -> 0 | Z11: =-SUMIFS('GL Data'!$AB:$AB,'GL Data'!$B:$B,$A11) -> 0 | AA11: =-SUMIFS('GL Data'!$AC:$AC,'GL Data'!$B:$B,$A11) -> 0
A12: Other Miscellaneous Income | C12: =-SUMIFS('GL Data'!$E:$E,'GL Data'!$B:$B,$A12) -> 0 | D12: =-SUMIFS('GL Data'!$F:$F,'GL Data'!$B:$B,$A12) -> 0 | E12: =-SUMIFS('GL Data'!$G:$G,'GL Data'!$B:$B,$A12) -> 0 | F12: =-SUMIFS('GL Data'!$H:$H,'GL Data'!$B:$B,$A12) -> 0 | G12: =-SUMIFS('GL Data'!$I:$I,'GL Data'!$B:$B,$A12) -> 0 | H12: =-SUMIFS('GL Data'!$J:$J,'GL Data'!$B:$B,$A12) -> 0 | I12: =-SUMIFS('GL Data'!$K:$K,'GL Data'!$B:$B,$A12) -> 0 | J12: =-SUMIFS('GL Data'!$L:$L,'GL Data'!$B:$B,$A12) -> 0 | K12: =-SUMIFS('GL Data'!$M:$M,'GL Data'!$B:$B,$A12) -> 0 | L12: =-SUMIFS('GL Data'!$N:$N,'GL Data'!$B:$B,$A12) -> 0 | M12: =-SUMIFS('GL Data'!$O:$O,'GL Data'!$B:$B,$A12) -> 0 | N12: =-SUMIFS('GL Data'!$P:$P,'GL Data'!$B:$B,$A12) -> 135.82 | O12: =-SUMIFS('GL Data'!$Q:$Q,'GL Data'!$B:$B,$A12) -> 0 | P12: =-SUMIFS('GL Data'!$R:$R,'GL Data'!$B:$B,$A12) -> 0 | Q12: =-SUMIFS('GL Data'!$S:$S,'GL Data'!$B:$B,$A12) -> 0 | R12: =-SUMIFS('GL Data'!$T:$T,'GL Data'!$B:$B,$A12) -> 0 | S12: =-SUMIFS('GL Data'!$U:$U,'GL Data'!$B:$B,$A12) -> 0 | T12: =-SUMIFS('GL Data'!$V:$V,'GL Data'!$B:$B,$A12) -> 0 | U12: =-SUMIFS('GL Data'!$W:$W,'GL Data'!$B:$B,$A12) -> 0 | V12: =-SUMIFS('GL Data'!$X:$X,'GL Data'!$B:$B,$A12) -> 0 | W12: =-SUMIFS('GL Data'!$Y:$Y,'GL Data'!$B:$B,$A12) -> 0 | X12: =-SUMIFS('GL Data'!$Z:$Z,'GL Data'!$B:$B,$A12) -> 0 | Y12: =-SUMIFS('GL Data'!$AA:$AA,'GL Data'!$B:$B,$A12) -> 0 | Z12: =-SUMIFS('GL Data'!$AB:$AB,'GL Data'!$B:$B,$A12) -> 0 | AA12: =-SUMIFS('GL Data'!$AC:$AC,'GL Data'!$B:$B,$A12) -> 0
A13: Discounts | C13: =-SUMIFS('GL Data'!$E:$E,'GL Data'!$B:$B,$A13) -> -1260 | D13: =-SUMIFS('GL Data'!$F:$F,'GL Data'!$B:$B,$A13) -> -1578 | E13: =-SUMIFS('GL Data'!$G:$G,'GL Data'!$B:$B,$A13) -> -1800 | F13: =-SUMIFS('GL Data'!$H:$H,'GL Data'!$B:$B,$A13) -> -2160 | G13: =-SUMIFS('GL Data'!$I:$I,'GL Data'!$B:$B,$A13) -> -1125 | H13: =-SUMIFS('GL Data'!$J:$J,'GL Data'!$B:$B,$A13) -> -1500 | I13: =-SUMIFS('GL Data'!$K:$K,'GL Data'!$B:$B,$A13) -> -2610 | J13: =-SUMIFS('GL Data'!$L:$L,'GL Data'!$B:$B,$A13) -> -750 | K13: =-SUMIFS('GL Data'!$M:$M,'GL Data'!$B:$B,$A13) -> -1500 | L13: =-SUMIFS('GL Data'!$N:$N,'GL Data'!$B:$B,$A13) -> -1050 | M13: =-SUMIFS('GL Data'!$O:$O,'GL Data'!$B:$B,$A13) -> -1410 | N13: =-SUMIFS('GL Data'!$P:$P,'GL Data'!$B:$B,$A13) -> -2328 | O13: =-SUMIFS('GL Data'!$Q:$Q,'GL Data'!$B:$B,$A13) -> -600 | P13: =-SUMIFS('GL Data'!$R:$R,'GL Data'!$B:$B,$A13) -> -1638 | Q13: =-SUMIFS('GL Data'!$S:$S,'GL Data'!$B:$B,$A13) -> -1500 | R13: =-SUMIFS('GL Data'!$T:$T,'GL Data'!$B:$B,$A13) -> -1128 | S13: =-SUMIFS('GL Data'!$U:$U,'GL Data'!$B:$B,$A13) -> -3060.5 | T13: =-SUMIFS('GL Data'!$V:$V,'GL Data'!$B:$B,$A13) -> -2556 | U13: =-SUMIFS('GL Data'!$W:$W,'GL Data'!$B:$B,$A13) -> -1728 | V13: =-SUMIFS('GL Data'!$X:$X,'GL Data'!$B:$B,$A13) -> -3804 | W13: =-SUMIFS('GL Data'!$Y:$Y,'GL Data'!$B:$B,$A13) -> -2028 | X13: =-SUMIFS('GL Data'!$Z:$Z,'GL Data'!$B:$B,$A13) -> -828 | Y13: =-SUMIFS('GL Data'!$AA:$AA,'GL Data'!$B:$B,$A13) -> -1788 | Z13: =-SUMIFS('GL Data'!$AB:$AB,'GL Data'!$B:$B,$A13) -> -2378 | AA13: =-SUMIFS('GL Data'!$AC:$AC,'GL Data'!$B:$B,$A13) -> -350
A14: Refunds | C14: =-SUMIFS('GL Data'!$E:$E,'GL Data'!$B:$B,$A14) -> -1280 | D14: =-SUMIFS('GL Data'!$F:$F,'GL Data'!$B:$B,$A14) -> -1500 | E14: =-SUMIFS('GL Data'!$G:$G,'GL Data'!$B:$B,$A14) -> -880 | F14: =-SUMIFS('GL Data'!$H:$H,'GL Data'!$B:$B,$A14) -> 0 | G14: =-SUMIFS('GL Data'!$I:$I,'GL Data'!$B:$B,$A14) -> 0 | H14: =-SUMIFS('GL Data'!$J:$J,'GL Data'!$B:$B,$A14) -> 0 | I14: =-SUMIFS('GL Data'!$K:$K,'GL Data'!$B:$B,$A14) -> 0 | J14: =-SUMIFS('GL Data'!$L:$L,'GL Data'!$B:$B,$A14) -> 0 | K14: =-SUMIFS('GL Data'!$M:$M,'GL Data'!$B:$B,$A14) -> 0 | L14: =-SUMIFS('GL Data'!$N:$N,'GL Data'!$B:$B,$A14) -> 0 | M14: =-SUMIFS('GL Data'!$O:$O,'GL Data'!$B:$B,$A14) -> -1000 | N14: =-SUMIFS('GL Data'!$P:$P,'GL Data'!$B:$B,$A14) -> -50 | O14: =-SUMIFS('GL Data'!$Q:$Q,'GL Data'!$B:$B,$A14) -> -498 | P14: =-SUMIFS('GL Data'!$R:$R,'GL Data'!$B:$B,$A14) -> -780 | Q14: =-SUMIFS('GL Data'!$S:$S,'GL Data'!$B:$B,$A14) -> -500 | R14: =-SUMIFS('GL Data'!$T:$T,'GL Data'!$B:$B,$A14) -> -598.1 | S14: =-SUMIFS('GL Data'!$U:$U,'GL Data'!$B:$B,$A14) -> -500 | T14: =-SUMIFS('GL Data'!$V:$V,'GL Data'!$B:$B,$A14) -> 0 | U14: =-SUMIFS('GL Data'!$W:$W,'GL Data'!$B:$B,$A14) -> 0 | V14: =-SUMIFS('GL Data'!$X:$X,'GL Data'!$B:$B,$A14) -> -150 | W14: =-SUMIFS('GL Data'!$Y:$Y,'GL Data'!$B:$B,$A14) -> 0 | X14: =-SUMIFS('GL Data'!$Z:$Z,'GL Data'!$B:$B,$A14) -> -2136.2 | Y14: =-SUMIFS('GL Data'!$AA:$AA,'GL Data'!$B:$B,$A14) -> -5095.99 | Z14: =-SUMIFS('GL Data'!$AB:$AB,'GL Data'!$B:$B,$A14) -> -1000 | AA14: =-SUMIFS('GL Data'!$AC:$AC,'GL Data'!$B:$B,$A14) -> 0
A15: Net Revenue | C15: =SUM(C9:C14) -> 65519.54 | D15: =SUM(D9:D14) -> 78557.47 | E15: =SUM(E9:E14) -> 69444.9 | F15: =SUM(F9:F14) -> 69420.32 | G15: =SUM(G9:G14) -> 74602.66 | H15: =SUM(H9:H14) -> 69554.58 | I15: =SUM(I9:I14) -> 68302.35 | J15: =SUM(J9:J14) -> 65585.42 | ... AA15: =SUM(AA9:AA14) -> 64127.22
A17: Cost of Services
A18: Contractors - Client Hours | C18: =SUMIFS('GL Data'!$E:$E,'GL Data'!$B:$B,$A18) -> 19394.04 | D18: =SUMIFS('GL Data'!$F:$F,'GL Data'!$B:$B,$A18) -> 18266.33 | E18: =SUMIFS('GL Data'!$G:$G,'GL Data'!$B:$B,$A18) -> 20915.87 | F18: =SUMIFS('GL Data'!$H:$H,'GL Data'!$B:$B,$A18) -> 20818.06 | G18: =SUMIFS('GL Data'!$I:$I,'GL Data'!$B:$B,$A18) -> 22253.11 | H18: =SUMIFS('GL Data'!$J:$J,'GL Data'!$B:$B,$A18) -> 21849.94 | I18: =SUMIFS('GL Data'!$K:$K,'GL Data'!$B:$B,$A18) -> 18495.84 | J18: =SUMIFS('GL Data'!$L:$L,'GL Data'!$B:$B,$A18) -> 17320.71 | K18: =SUMIFS('GL Data'!$M:$M,'GL Data'!$B:$B,$A18) -> 19492.66 | L18: =SUMIFS('GL Data'!$N:$N,'GL Data'!$B:$B,$A18) -> 18326.41 | M18: =SUMIFS('GL Data'!$O:$O,'GL Data'!$B:$B,$A18) -> 20629.36 | N18: =SUMIFS('GL Data'!$P:$P,'GL Data'!$B:$B,$A18) -> 21453.48 | O18: =SUMIFS('GL Data'!$Q:$Q,'GL Data'!$B:$B,$A18) -> 21869.94 | P18: =SUMIFS('GL Data'!$R:$R,'GL Data'!$B:$B,$A18) -> 21439.57 | Q18: =SUMIFS('GL Data'!$S:$S,'GL Data'!$B:$B,$A18) -> 25115.95 | R18: =SUMIFS('GL Data'!$T:$T,'GL Data'!$B:$B,$A18) -> 24359.34 | S18: =SUMIFS('GL Data'!$U:$U,'GL Data'!$B:$B,$A18) -> 24557.02 | T18: =SUMIFS('GL Data'!$V:$V,'GL Data'!$B:$B,$A18) -> 23570.34 | U18: =SUMIFS('GL Data'!$W:$W,'GL Data'!$B:$B,$A18) -> 21932.71 | V18: =SUMIFS('GL Data'!$X:$X,'GL Data'!$B:$B,$A18) -> 21068.2 | W18: =SUMIFS('GL Data'!$Y:$Y,'GL Data'!$B:$B,$A18) -> 24105.05 | X18: =SUMIFS('GL Data'!$Z:$Z,'GL Data'!$B:$B,$A18) -> 21329.32 | Y18: =SUMIFS('GL Data'!$AA:$AA,'GL Data'!$B:$B,$A18) -> 23432.68 | Z18: =SUMIFS('GL Data'!$AB:$AB,'GL Data'!$B:$B,$A18) -> 22967.15 | AA18: =SUMIFS('GL Data'!$AC:$AC,'GL Data'!$B:$B,$A18) -> 22258.75
A19: Contractors - Idle Time | C19: =SUMIFS('GL Data'!$E:$E,'GL Data'!$B:$B,$A19) -> 1166.36 | D19: =SUMIFS('GL Data'!$F:$F,'GL Data'!$B:$B,$A19) -> 817.49 | E19: =SUMIFS('GL Data'!$G:$G,'GL Data'!$B:$B,$A19) -> 899.16 | F19: =SUMIFS('GL Data'!$H:$H,'GL Data'!$B:$B,$A19) -> 668.06 | G19: =SUMIFS('GL Data'!$I:$I,'GL Data'!$B:$B,$A19) -> 763.66 | H19: =SUMIFS('GL Data'!$J:$J,'GL Data'!$B:$B,$A19) -> 1547.32 | I19: =SUMIFS('GL Data'!$K:$K,'GL Data'!$B:$B,$A19) -> 1484.27 | J19: =SUMIFS('GL Data'!$L:$L,'GL Data'!$B:$B,$A19) -> 985.85 | K19: =SUMIFS('GL Data'!$M:$M,'GL Data'!$B:$B,$A19) -> 856.37 | L19: =SUMIFS('GL Data'!$N:$N,'GL Data'!$B:$B,$A19) -> 1072.85 | M19: =SUMIFS('GL Data'!$O:$O,'GL Data'!$B:$B,$A19) -> 617.86 | N19: =SUMIFS('GL Data'!$P:$P,'GL Data'!$B:$B,$A19) -> 534.89 | O19: =SUMIFS('GL Data'!$Q:$Q,'GL Data'!$B:$B,$A19) -> 732.63 | P19: =SUMIFS('GL Data'!$R:$R,'GL Data'!$B:$B,$A19) -> 1252.22 | Q19: =SUMIFS('GL Data'!$S:$S,'GL Data'!$B:$B,$A19) -> 1004.05 | R19: =SUMIFS('GL Data'!$T:$T,'GL Data'!$B:$B,$A19) -> 1130.93 | S19: =SUMIFS('GL Data'!$U:$U,'GL Data'!$B:$B,$A19) -> 974.1 | T19: =SUMIFS('GL Data'!$V:$V,'GL Data'!$B:$B,$A19) -> 1300.18 | U19: =SUMIFS('GL Data'!$W:$W,'GL Data'!$B:$B,$A19) -> 1260.22 | V19: =SUMIFS('GL Data'!$X:$X,'GL Data'!$B:$B,$A19) -> 1062.81 | W19: =SUMIFS('GL Data'!$Y:$Y,'GL Data'!$B:$B,$A19) -> 1311.04 | X19: =SUMIFS('GL Data'!$Z:$Z,'GL Data'!$B:$B,$A19) -> 1443.68 | Y19: =SUMIFS('GL Data'!$AA:$AA,'GL Data'!$B:$B,$A19) -> 1059.39 | Z19: =SUMIFS('GL Data'!$AB:$AB,'GL Data'!$B:$B,$A19) -> 1295.65 | AA19: =SUMIFS('GL Data'!$AC:$AC,'GL Data'!$B:$B,$A19) -> 701.82
A20: Contractors - Others | C20: =SUMIFS('GL Data'!$E:$E,'GL Data'!$B:$B,$A20) -> 7834.29 | D20: =SUMIFS('GL Data'!$F:$F,'GL Data'!$B:$B,$A20) -> 6064.7 | E20: =SUMIFS('GL Data'!$G:$G,'GL Data'!$B:$B,$A20) -> 4091.34 | F20: =SUMIFS('GL Data'!$H:$H,'GL Data'!$B:$B,$A20) -> 3818.86 | G20: =SUMIFS('GL Data'!$I:$I,'GL Data'!$B:$B,$A20) -> 3589.5 | H20: =SUMIFS('GL Data'!$J:$J,'GL Data'!$B:$B,$A20) -> 3313.24 | I20: =SUMIFS('GL Data'!$K:$K,'GL Data'!$B:$B,$A20) -> 3575.32 | J20: =SUMIFS('GL Data'!$L:$L,'GL Data'!$B:$B,$A20) -> 7481.92 | K20: =SUMIFS('GL Data'!$M:$M,'GL Data'!$B:$B,$A20) -> 3575.32 | L20: =SUMIFS('GL Data'!$N:$N,'GL Data'!$B:$B,$A20) -> 2981.41 | M20: =SUMIFS('GL Data'!$O:$O,'GL Data'!$B:$B,$A20) -> 3675.91 | N20: =SUMIFS('GL Data'!$P:$P,'GL Data'!$B:$B,$A20) -> 3134.72 | O20: =SUMIFS('GL Data'!$Q:$Q,'GL Data'!$B:$B,$A20) -> 2707.3 | P20: =SUMIFS('GL Data'!$R:$R,'GL Data'!$B:$B,$A20) -> 2899.91 | Q20: =SUMIFS('GL Data'!$S:$S,'GL Data'!$B:$B,$A20) -> 4162.38 | R20: =SUMIFS('GL Data'!$T:$T,'GL Data'!$B:$B,$A20) -> 3519.64 | S20: =SUMIFS('GL Data'!$U:$U,'GL Data'!$B:$B,$A20) -> 3252.98 | T20: =SUMIFS('GL Data'!$V:$V,'GL Data'!$B:$B,$A20) -> 3797.61 | U20: =SUMIFS('GL Data'!$W:$W,'GL Data'!$B:$B,$A20) -> 4713.44 | V20: =SUMIFS('GL Data'!$X:$X,'GL Data'!$B:$B,$A20) -> 6541.99 | W20: =SUMIFS('GL Data'!$Y:$Y,'GL Data'!$B:$B,$A20) -> 3330.03 | X20: =SUMIFS('GL Data'!$Z:$Z,'GL Data'!$B:$B,$A20) -> 3372.95 | Y20: =SUMIFS('GL Data'!$AA:$AA,'GL Data'!$B:$B,$A20) -> 4847.32 | Z20: =SUMIFS('GL Data'!$AB:$AB,'GL Data'!$B:$B,$A20) -> 3915.98 | AA20: =SUMIFS('GL Data'!$AC:$AC,'GL Data'!$B:$B,$A20) -> 3525.4
A21: VA Incentives | C21: =SUMIFS('GL Data'!$E:$E,'GL Data'!$B:$B,$A21) -> 247.85 | D21: =SUMIFS('GL Data'!$F:$F,'GL Data'!$B:$B,$A21) -> 354.06 | E21: =SUMIFS('GL Data'!$G:$G,'GL Data'!$B:$B,$A21) -> 309.98 | F21: =SUMIFS('GL Data'!$H:$H,'GL Data'!$B:$B,$A21) -> 50.56 | G21: =SUMIFS('GL Data'!$I:$I,'GL Data'!$B:$B,$A21) -> 409.59 | H21: =SUMIFS('GL Data'!$J:$J,'GL Data'!$B:$B,$A21) -> 126.1 | I21: =SUMIFS('GL Data'!$K:$K,'GL Data'!$B:$B,$A21) -> 278.28 | J21: =SUMIFS('GL Data'!$L:$L,'GL Data'!$B:$B,$A21) -> 257.2 | K21: =SUMIFS('GL Data'!$M:$M,'GL Data'!$B:$B,$A21) -> 252.19 | L21: =SUMIFS('GL Data'!$N:$N,'GL Data'!$B:$B,$A21) -> 111.07 | M21: =SUMIFS('GL Data'!$O:$O,'GL Data'!$B:$B,$A21) -> 476.68 | N21: =SUMIFS('GL Data'!$P:$P,'GL Data'!$B:$B,$A21) -> 85.67 | O21: =SUMIFS('GL Data'!$Q:$Q,'GL Data'!$B:$B,$A21) -> 206.89 | P21: =SUMIFS('GL Data'!$R:$R,'GL Data'!$B:$B,$A21) -> 714.82 | Q21: =SUMIFS('GL Data'!$S:$S,'GL Data'!$B:$B,$A21) -> 297.3 | R21: =SUMIFS('GL Data'!$T:$T,'GL Data'!$B:$B,$A21) -> 105.81 | S21: =SUMIFS('GL Data'!$U:$U,'GL Data'!$B:$B,$A21) -> 472.45 | T21: =SUMIFS('GL Data'!$V:$V,'GL Data'!$B:$B,$A21) -> 242.07 | U21: =SUMIFS('GL Data'!$W:$W,'GL Data'!$B:$B,$A21) -> 140.88 | V21: =SUMIFS('GL Data'!$X:$X,'GL Data'!$B:$B,$A21) -> 466.66 | W21: =SUMIFS('GL Data'!$Y:$Y,'GL Data'!$B:$B,$A21) -> 302.49 | X21: =SUMIFS('GL Data'!$Z:$Z,'GL Data'!$B:$B,$A21) -> 116.64 | Y21: =SUMIFS('GL Data'!$AA:$AA,'GL Data'!$B:$B,$A21) -> 711.88 | Z21: =SUMIFS('GL Data'!$AB:$AB,'GL Data'!$B:$B,$A21) -> 157.59 | AA21: =SUMIFS('GL Data'!$AC:$AC,'GL Data'!$B:$B,$A21) -> 236.81
A22: Total Cost of Services | C22: =SUM(C18:C21) -> 28642.54 | D22: =SUM(D18:D21) -> 25502.58 | E22: =SUM(E18:E21) -> 26216.35 | F22: =SUM(F18:F21) -> 25355.54 | G22: =SUM(G18:G21) -> 27015.86 | H22: =SUM(H18:H21) -> 26836.6 | I22: =SUM(I18:I21) -> 23833.71 | J22: =SUM(J18:J21) -> 26045.68 | ... AA22: =SUM(AA18:AA21) -> 26722.78
A23: Gross Profit | C23: =C15-C22 -> 36877 | D23: =D15-D22 -> 53054.89 | E23: =E15-E22 -> 43228.55 | F23: =F15-F22 -> 44064.78 | G23: =G15-G22 -> 47586.8 | H23: =H15-H22 -> 42717.98 | I23: =I15-I22 -> 44468.64 | J23: =J15-J22 -> 39539.74 | ... AA23: =AA15-AA22 -> 37404.44
A24: Gross Margin % | C24: =IFERROR(C23/C15,0) -> 0.56283973 | D24: =IFERROR(D23/D15,0) -> 0.67536404 | E24: =IFERROR(E23/E15,0) -> 0.62248704 | F24: =IFERROR(F23/F15,0) -> 0.63475334 | G24: =IFERROR(G23/G15,0) -> 0.63787002 | H24: =IFERROR(H23/H15,0) -> 0.61416488 | I24: =IFERROR(I23/I15,0) -> 0.65105578 | J24: =IFERROR(J23/J15,0) -> 0.60287393 | ... AA24: =IFERROR(AA23/AA15,0) -> 0.58328491
A26: Operating Expenses
A27: Marketing Expenses
A28: Advertising & Marketing | C28: =SUMIFS('GL Data'!$E:$E,'GL Data'!$B:$B,$A28) -> 827.45 | D28: =SUMIFS('GL Data'!$F:$F,'GL Data'!$B:$B,$A28) -> 825.18 | E28: =SUMIFS('GL Data'!$G:$G,'GL Data'!$B:$B,$A28) -> 1047.16 | F28: =SUMIFS('GL Data'!$H:$H,'GL Data'!$B:$B,$A28) -> 1019.82 | G28: =SUMIFS('GL Data'!$I:$I,'GL Data'!$B:$B,$A28) -> 771 | H28: =SUMIFS('GL Data'!$J:$J,'GL Data'!$B:$B,$A28) -> 949.58 | I28: =SUMIFS('GL Data'!$K:$K,'GL Data'!$B:$B,$A28) -> 1154.99 | J28: =SUMIFS('GL Data'!$L:$L,'GL Data'!$B:$B,$A28) -> 426.1 | K28: =SUMIFS('GL Data'!$M:$M,'GL Data'!$B:$B,$A28) -> 397.46 | L28: =SUMIFS('GL Data'!$N:$N,'GL Data'!$B:$B,$A28) -> 263.93 | M28: =SUMIFS('GL Data'!$O:$O,'GL Data'!$B:$B,$A28) -> 454.09 | N28: =SUMIFS('GL Data'!$P:$P,'GL Data'!$B:$B,$A28) -> 437.04 | O28: =SUMIFS('GL Data'!$Q:$Q,'GL Data'!$B:$B,$A28) -> 836.91 | P28: =SUMIFS('GL Data'!$R:$R,'GL Data'!$B:$B,$A28) -> 586.22 | Q28: =SUMIFS('GL Data'!$S:$S,'GL Data'!$B:$B,$A28) -> 359.35 | R28: =SUMIFS('GL Data'!$T:$T,'GL Data'!$B:$B,$A28) -> 488.99 | S28: =SUMIFS('GL Data'!$U:$U,'GL Data'!$B:$B,$A28) -> 466.09 | T28: =SUMIFS('GL Data'!$V:$V,'GL Data'!$B:$B,$A28) -> 608.78 | U28: =SUMIFS('GL Data'!$W:$W,'GL Data'!$B:$B,$A28) -> 552.84 | V28: =SUMIFS('GL Data'!$X:$X,'GL Data'!$B:$B,$A28) -> 412.8 | W28: =SUMIFS('GL Data'!$Y:$Y,'GL Data'!$B:$B,$A28) -> 357.41 | X28: =SUMIFS('GL Data'!$Z:$Z,'GL Data'!$B:$B,$A28) -> 615.57 | Y28: =SUMIFS('GL Data'!$AA:$AA,'GL Data'!$B:$B,$A28) -> 548.07 | Z28: =SUMIFS('GL Data'!$AB:$AB,'GL Data'!$B:$B,$A28) -> 583.71 | AA28: =SUMIFS('GL Data'!$AC:$AC,'GL Data'!$B:$B,$A28) -> 792.14
A29: Marketing Softwares | C29: =SUMIFS('GL Data'!$E:$E,'GL Data'!$B:$B,$A29) -> 662.09 | D29: =SUMIFS('GL Data'!$F:$F,'GL Data'!$B:$B,$A29) -> 236.68 | E29: =SUMIFS('GL Data'!$G:$G,'GL Data'!$B:$B,$A29) -> 279.23 | F29: =SUMIFS('GL Data'!$H:$H,'GL Data'!$B:$B,$A29) -> 340.67 | G29: =SUMIFS('GL Data'!$I:$I,'GL Data'!$B:$B,$A29) -> 277.06 | H29: =SUMIFS('GL Data'!$J:$J,'GL Data'!$B:$B,$A29) -> 212.56 | I29: =SUMIFS('GL Data'!$K:$K,'GL Data'!$B:$B,$A29) -> 332.05 | J29: =SUMIFS('GL Data'!$L:$L,'GL Data'!$B:$B,$A29) -> 291.49 | K29: =SUMIFS('GL Data'!$M:$M,'GL Data'!$B:$B,$A29) -> 341.1 | L29: =SUMIFS('GL Data'!$N:$N,'GL Data'!$B:$B,$A29) -> 250.37 | M29: =SUMIFS('GL Data'!$O:$O,'GL Data'!$B:$B,$A29) -> 245.75 | N29: =SUMIFS('GL Data'!$P:$P,'GL Data'!$B:$B,$A29) -> 380.92 | O29: =SUMIFS('GL Data'!$Q:$Q,'GL Data'!$B:$B,$A29) -> 645.24 | P29: =SUMIFS('GL Data'!$R:$R,'GL Data'!$B:$B,$A29) -> 315.52 | Q29: =SUMIFS('GL Data'!$S:$S,'GL Data'!$B:$B,$A29) -> 299.58 | R29: =SUMIFS('GL Data'!$T:$T,'GL Data'!$B:$B,$A29) -> 304.11 | S29: =SUMIFS('GL Data'!$U:$U,'GL Data'!$B:$B,$A29) -> 313.11 | T29: =SUMIFS('GL Data'!$V:$V,'GL Data'!$B:$B,$A29) -> 280.1 | U29: =SUMIFS('GL Data'!$W:$W,'GL Data'!$B:$B,$A29) -> 938.9 | V29: =SUMIFS('GL Data'!$X:$X,'GL Data'!$B:$B,$A29) -> -156 | W29: =SUMIFS('GL Data'!$Y:$Y,'GL Data'!$B:$B,$A29) -> 301.55 | X29: =SUMIFS('GL Data'!$Z:$Z,'GL Data'!$B:$B,$A29) -> 364.83 | Y29: =SUMIFS('GL Data'!$AA:$AA,'GL Data'!$B:$B,$A29) -> 301.55 | Z29: =SUMIFS('GL Data'!$AB:$AB,'GL Data'!$B:$B,$A29) -> 270.51 | AA29: =SUMIFS('GL Data'!$AC:$AC,'GL Data'!$B:$B,$A29) -> 647.3
A30: Marketing Subscriptions | C30: =SUMIFS('GL Data'!$E:$E,'GL Data'!$B:$B,$A30) -> 0 | D30: =SUMIFS('GL Data'!$F:$F,'GL Data'!$B:$B,$A30) -> 0 | E30: =SUMIFS('GL Data'!$G:$G,'GL Data'!$B:$B,$A30) -> 0 | F30: =SUMIFS('GL Data'!$H:$H,'GL Data'!$B:$B,$A30) -> 0 | G30: =SUMIFS('GL Data'!$I:$I,'GL Data'!$B:$B,$A30) -> 0 | H30: =SUMIFS('GL Data'!$J:$J,'GL Data'!$B:$B,$A30) -> 0 | I30: =SUMIFS('GL Data'!$K:$K,'GL Data'!$B:$B,$A30) -> 0 | J30: =SUMIFS('GL Data'!$L:$L,'GL Data'!$B:$B,$A30) -> 0 | K30: =SUMIFS('GL Data'!$M:$M,'GL Data'!$B:$B,$A30) -> 0 | L30: =SUMIFS('GL Data'!$N:$N,'GL Data'!$B:$B,$A30) -> 0 | M30: =SUMIFS('GL Data'!$O:$O,'GL Data'!$B:$B,$A30) -> 0 | N30: =SUMIFS('GL Data'!$P:$P,'GL Data'!$B:$B,$A30) -> 0 | O30: =SUMIFS('GL Data'!$Q:$Q,'GL Data'!$B:$B,$A30) -> 0 | P30: =SUMIFS('GL Data'!$R:$R,'GL Data'!$B:$B,$A30) -> 0 | Q30: =SUMIFS('GL Data'!$S:$S,'GL Data'!$B:$B,$A30) -> 0 | R30: =SUMIFS('GL Data'!$T:$T,'GL Data'!$B:$B,$A30) -> 0 | S30: =SUMIFS('GL Data'!$U:$U,'GL Data'!$B:$B,$A30) -> 0 | T30: =SUMIFS('GL Data'!$V:$V,'GL Data'!$B:$B,$A30) -> 0 | U30: =SUMIFS('GL Data'!$W:$W,'GL Data'!$B:$B,$A30) -> 97 | V30: =SUMIFS('GL Data'!$X:$X,'GL Data'!$B:$B,$A30) -> 0 | W30: =SUMIFS('GL Data'!$Y:$Y,'GL Data'!$B:$B,$A30) -> 0 | X30: =SUMIFS('GL Data'!$Z:$Z,'GL Data'!$B:$B,$A30) -> 0 | Y30: =SUMIFS('GL Data'!$AA:$AA,'GL Data'!$B:$B,$A30) -> 0 | Z30: =SUMIFS('GL Data'!$AB:$AB,'GL Data'!$B:$B,$A30) -> 0 | AA30: =SUMIFS('GL Data'!$AC:$AC,'GL Data'!$B:$B,$A30) -> 3.46
A31: VA Pay - Marketing | C31: =SUMIFS('GL Data'!$E:$E,'GL Data'!$B:$B,$A31) -> 4510.08 | D31: =SUMIFS('GL Data'!$F:$F,'GL Data'!$B:$B,$A31) -> 4160.89 | E31: =SUMIFS('GL Data'!$G:$G,'GL Data'!$B:$B,$A31) -> 4387.96 | F31: =SUMIFS('GL Data'!$H:$H,'GL Data'!$B:$B,$A31) -> 3850.96 | G31: =SUMIFS('GL Data'!$I:$I,'GL Data'!$B:$B,$A31) -> 4025.92 | H31: =SUMIFS('GL Data'!$J:$J,'GL Data'!$B:$B,$A31) -> 3198.27 | I31: =SUMIFS('GL Data'!$K:$K,'GL Data'!$B:$B,$A31) -> 2695.19 | J31: =SUMIFS('GL Data'!$L:$L,'GL Data'!$B:$B,$A31) -> 2513.97 | K31: =SUMIFS('GL Data'!$M:$M,'GL Data'!$B:$B,$A31) -> 3010.22 | L31: =SUMIFS('GL Data'!$N:$N,'GL Data'!$B:$B,$A31) -> 2861.52 | M31: =SUMIFS('GL Data'!$O:$O,'GL Data'!$B:$B,$A31) -> 2868.74 | N31: =SUMIFS('GL Data'!$P:$P,'GL Data'!$B:$B,$A31) -> 3063.17 | O31: =SUMIFS('GL Data'!$Q:$Q,'GL Data'!$B:$B,$A31) -> 3158.78 | P31: =SUMIFS('GL Data'!$R:$R,'GL Data'!$B:$B,$A31) -> 3552.28 | Q31: =SUMIFS('GL Data'!$S:$S,'GL Data'!$B:$B,$A31) -> 3706.08 | R31: =SUMIFS('GL Data'!$T:$T,'GL Data'!$B:$B,$A31) -> 2873.17 | S31: =SUMIFS('GL Data'!$U:$U,'GL Data'!$B:$B,$A31) -> 3028.44 | T31: =SUMIFS('GL Data'!$V:$V,'GL Data'!$B:$B,$A31) -> 3159.05 | U31: =SUMIFS('GL Data'!$W:$W,'GL Data'!$B:$B,$A31) -> 3285.06 | V31: =SUMIFS('GL Data'!$X:$X,'GL Data'!$B:$B,$A31) -> 2642.71 | W31: =SUMIFS('GL Data'!$Y:$Y,'GL Data'!$B:$B,$A31) -> 3502.91 | X31: =SUMIFS('GL Data'!$Z:$Z,'GL Data'!$B:$B,$A31) -> 2983.35 | Y31: =SUMIFS('GL Data'!$AA:$AA,'GL Data'!$B:$B,$A31) -> 3467.93 | Z31: =SUMIFS('GL Data'!$AB:$AB,'GL Data'!$B:$B,$A31) -> 3470.88 | AA31: =SUMIFS('GL Data'!$AC:$AC,'GL Data'!$B:$B,$A31) -> 3010.89
A32: Website Fees | C32: =SUMIFS('GL Data'!$E:$E,'GL Data'!$B:$B,$A32) -> 196.32 | D32: =SUMIFS('GL Data'!$F:$F,'GL Data'!$B:$B,$A32) -> 101.81 | E32: =SUMIFS('GL Data'!$G:$G,'GL Data'!$B:$B,$A32) -> 101.81 | F32: =SUMIFS('GL Data'!$H:$H,'GL Data'!$B:$B,$A32) -> 110.39 | G32: =SUMIFS('GL Data'!$I:$I,'GL Data'!$B:$B,$A32) -> 110.39 | H32: =SUMIFS('GL Data'!$J:$J,'GL Data'!$B:$B,$A32) -> 360.65 | I32: =SUMIFS('GL Data'!$K:$K,'GL Data'!$B:$B,$A32) -> 176.9 | J32: =SUMIFS('GL Data'!$L:$L,'GL Data'!$B:$B,$A32) -> 132.56 | K32: =SUMIFS('GL Data'!$M:$M,'GL Data'!$B:$B,$A32) -> 110.39 | L32: =SUMIFS('GL Data'!$N:$N,'GL Data'!$B:$B,$A32) -> 110.39 | M32: =SUMIFS('GL Data'!$O:$O,'GL Data'!$B:$B,$A32) -> 110.39 | N32: =SUMIFS('GL Data'!$P:$P,'GL Data'!$B:$B,$A32) -> 134.7 | O32: =SUMIFS('GL Data'!$Q:$Q,'GL Data'!$B:$B,$A32) -> 156.87 | P32: =SUMIFS('GL Data'!$R:$R,'GL Data'!$B:$B,$A32) -> 112.53 | Q32: =SUMIFS('GL Data'!$S:$S,'GL Data'!$B:$B,$A32) -> 112.53 | R32: =SUMIFS('GL Data'!$T:$T,'GL Data'!$B:$B,$A32) -> 112.53 | S32: =SUMIFS('GL Data'!$U:$U,'GL Data'!$B:$B,$A32) -> 112.53 | T32: =SUMIFS('GL Data'!$V:$V,'GL Data'!$B:$B,$A32) -> 318.45 | U32: =SUMIFS('GL Data'!$W:$W,'GL Data'!$B:$B,$A32) -> 112.53 | V32: =SUMIFS('GL Data'!$X:$X,'GL Data'!$B:$B,$A32) -> 112.53 | W32: =SUMIFS('GL Data'!$Y:$Y,'GL Data'!$B:$B,$A32) -> 112.53 | X32: =SUMIFS('GL Data'!$Z:$Z,'GL Data'!$B:$B,$A32) -> 112.53 | Y32: =SUMIFS('GL Data'!$AA:$AA,'GL Data'!$B:$B,$A32) -> 112.53 | Z32: =SUMIFS('GL Data'!$AB:$AB,'GL Data'!$B:$B,$A32) -> 138.5 | AA32: =SUMIFS('GL Data'!$AC:$AC,'GL Data'!$B:$B,$A32) -> 112.53
A33: Total Marketing Expenses | C33: =SUM(C28:C32) -> 6195.94 | D33: =SUM(D28:D32) -> 5324.56 | E33: =SUM(E28:E32) -> 5816.16 | F33: =SUM(F28:F32) -> 5321.84 | G33: =SUM(G28:G32) -> 5184.37 | H33: =SUM(H28:H32) -> 4721.06 | I33: =SUM(I28:I32) -> 4359.13 | J33: =SUM(J28:J32) -> 3364.12 | ... AA33: =SUM(AA28:AA32) -> 4566.32
A35: Personnel & Leadership
A36: OPS Team - Basic | C36: =SUMIFS('GL Data'!$E:$E,'GL Data'!$B:$B,$A36) -> 11779.55 | D36: =SUMIFS('GL Data'!$F:$F,'GL Data'!$B:$B,$A36) -> 12032.11 | E36: =SUMIFS('GL Data'!$G:$G,'GL Data'!$B:$B,$A36) -> 15357.32 | F36: =SUMIFS('GL Data'!$H:$H,'GL Data'!$B:$B,$A36) -> 14044.21 | G36: =SUMIFS('GL Data'!$I:$I,'GL Data'!$B:$B,$A36) -> 14640.15 | H36: =SUMIFS('GL Data'!$J:$J,'GL Data'!$B:$B,$A36) -> 15409.31 | I36: =SUMIFS('GL Data'!$K:$K,'GL Data'!$B:$B,$A36) -> 12769.29 | J36: =SUMIFS('GL Data'!$L:$L,'GL Data'!$B:$B,$A36) -> 11111.23 | K36: =SUMIFS('GL Data'!$M:$M,'GL Data'!$B:$B,$A36) -> 12139.79 | L36: =SUMIFS('GL Data'!$N:$N,'GL Data'!$B:$B,$A36) -> 10917.12 | M36: =SUMIFS('GL Data'!$O:$O,'GL Data'!$B:$B,$A36) -> 10277.49 | N36: =SUMIFS('GL Data'!$P:$P,'GL Data'!$B:$B,$A36) -> 11593.37 | O36: =SUMIFS('GL Data'!$Q:$Q,'GL Data'!$B:$B,$A36) -> 9872.63 | P36: =SUMIFS('GL Data'!$R:$R,'GL Data'!$B:$B,$A36) -> 12363.8 | Q36: =SUMIFS('GL Data'!$S:$S,'GL Data'!$B:$B,$A36) -> 13595.44 | R36: =SUMIFS('GL Data'!$T:$T,'GL Data'!$B:$B,$A36) -> 11428.59 | S36: =SUMIFS('GL Data'!$U:$U,'GL Data'!$B:$B,$A36) -> 11668.9 | T36: =SUMIFS('GL Data'!$V:$V,'GL Data'!$B:$B,$A36) -> 11286.92 | U36: =SUMIFS('GL Data'!$W:$W,'GL Data'!$B:$B,$A36) -> 11367.44 | V36: =SUMIFS('GL Data'!$X:$X,'GL Data'!$B:$B,$A36) -> 11782.14 | W36: =SUMIFS('GL Data'!$Y:$Y,'GL Data'!$B:$B,$A36) -> 12915.24 | X36: =SUMIFS('GL Data'!$Z:$Z,'GL Data'!$B:$B,$A36) -> 11808.97 | Y36: =SUMIFS('GL Data'!$AA:$AA,'GL Data'!$B:$B,$A36) -> 12966.78 | Z36: =SUMIFS('GL Data'!$AB:$AB,'GL Data'!$B:$B,$A36) -> 11805.14 | AA36: =SUMIFS('GL Data'!$AC:$AC,'GL Data'!$B:$B,$A36) -> 12508.21
A37: OPS Team - Other Benefits | C37: =SUMIFS('GL Data'!$E:$E,'GL Data'!$B:$B,$A37) -> 1490.14 | D37: =SUMIFS('GL Data'!$F:$F,'GL Data'!$B:$B,$A37) -> 1563.68 | E37: =SUMIFS('GL Data'!$G:$G,'GL Data'!$B:$B,$A37) -> 1827.66 | F37: =SUMIFS('GL Data'!$H:$H,'GL Data'!$B:$B,$A37) -> 2332.16 | G37: =SUMIFS('GL Data'!$I:$I,'GL Data'!$B:$B,$A37) -> 3929.96 | H37: =SUMIFS('GL Data'!$J:$J,'GL Data'!$B:$B,$A37) -> 2043.02 | I37: =SUMIFS('GL Data'!$K:$K,'GL Data'!$B:$B,$A37) -> 1038.37 | J37: =SUMIFS('GL Data'!$L:$L,'GL Data'!$B:$B,$A37) -> 5453.48 | K37: =SUMIFS('GL Data'!$M:$M,'GL Data'!$B:$B,$A37) -> 3421.45 | L37: =SUMIFS('GL Data'!$N:$N,'GL Data'!$B:$B,$A37) -> 2730.7 | M37: =SUMIFS('GL Data'!$O:$O,'GL Data'!$B:$B,$A37) -> 3818.62 | N37: =SUMIFS('GL Data'!$P:$P,'GL Data'!$B:$B,$A37) -> 1910.73 | O37: =SUMIFS('GL Data'!$Q:$Q,'GL Data'!$B:$B,$A37) -> 2083.84 | P37: =SUMIFS('GL Data'!$R:$R,'GL Data'!$B:$B,$A37) -> 1658.96 | Q37: =SUMIFS('GL Data'!$S:$S,'GL Data'!$B:$B,$A37) -> 946.53 | R37: =SUMIFS('GL Data'!$T:$T,'GL Data'!$B:$B,$A37) -> 2249.35 | S37: =SUMIFS('GL Data'!$U:$U,'GL Data'!$B:$B,$A37) -> 2621.64 | T37: =SUMIFS('GL Data'!$V:$V,'GL Data'!$B:$B,$A37) -> 2197.01 | U37: =SUMIFS('GL Data'!$W:$W,'GL Data'!$B:$B,$A37) -> 2255.66 | V37: =SUMIFS('GL Data'!$X:$X,'GL Data'!$B:$B,$A37) -> 6460.81 | W37: =SUMIFS('GL Data'!$Y:$Y,'GL Data'!$B:$B,$A37) -> 3284.9 | X37: =SUMIFS('GL Data'!$Z:$Z,'GL Data'!$B:$B,$A37) -> 2781.52 | Y37: =SUMIFS('GL Data'!$AA:$AA,'GL Data'!$B:$B,$A37) -> 2659.46 | Z37: =SUMIFS('GL Data'!$AB:$AB,'GL Data'!$B:$B,$A37) -> 3408.61 | AA37: =SUMIFS('GL Data'!$AC:$AC,'GL Data'!$B:$B,$A37) -> 1917.63
A38: OPS - Incentives | C38: =SUMIFS('GL Data'!$E:$E,'GL Data'!$B:$B,$A38) -> 116.69 | D38: =SUMIFS('GL Data'!$F:$F,'GL Data'!$B:$B,$A38) -> 1832.08 | E38: =SUMIFS('GL Data'!$G:$G,'GL Data'!$B:$B,$A38) -> 200.16 | F38: =SUMIFS('GL Data'!$H:$H,'GL Data'!$B:$B,$A38) -> 203.75 | G38: =SUMIFS('GL Data'!$I:$I,'GL Data'!$B:$B,$A38) -> 1767.49 | H38: =SUMIFS('GL Data'!$J:$J,'GL Data'!$B:$B,$A38) -> 160.09 | I38: =SUMIFS('GL Data'!$K:$K,'GL Data'!$B:$B,$A38) -> 68.64 | J38: =SUMIFS('GL Data'!$L:$L,'GL Data'!$B:$B,$A38) -> 1110.8 | K38: =SUMIFS('GL Data'!$M:$M,'GL Data'!$B:$B,$A38) -> 43.53 | L38: =SUMIFS('GL Data'!$N:$N,'GL Data'!$B:$B,$A38) -> 193.3 | M38: =SUMIFS('GL Data'!$O:$O,'GL Data'!$B:$B,$A38) -> 1150.33 | N38: =SUMIFS('GL Data'!$P:$P,'GL Data'!$B:$B,$A38) -> 54.35 | O38: =SUMIFS('GL Data'!$Q:$Q,'GL Data'!$B:$B,$A38) -> 78.76 | P38: =SUMIFS('GL Data'!$R:$R,'GL Data'!$B:$B,$A38) -> 1347.09 | Q38: =SUMIFS('GL Data'!$S:$S,'GL Data'!$B:$B,$A38) -> 150.44 | R38: =SUMIFS('GL Data'!$T:$T,'GL Data'!$B:$B,$A38) -> 119.76 | S38: =SUMIFS('GL Data'!$U:$U,'GL Data'!$B:$B,$A38) -> 1783.78 | T38: =SUMIFS('GL Data'!$V:$V,'GL Data'!$B:$B,$A38) -> 82.18 | U38: =SUMIFS('GL Data'!$W:$W,'GL Data'!$B:$B,$A38) -> 152.4 | V38: =SUMIFS('GL Data'!$X:$X,'GL Data'!$B:$B,$A38) -> 1741.25 | W38: =SUMIFS('GL Data'!$Y:$Y,'GL Data'!$B:$B,$A38) -> 320.65 | X38: =SUMIFS('GL Data'!$Z:$Z,'GL Data'!$B:$B,$A38) -> 152.34 | Y38: =SUMIFS('GL Data'!$AA:$AA,'GL Data'!$B:$B,$A38) -> 1454.05 | Z38: =SUMIFS('GL Data'!$AB:$AB,'GL Data'!$B:$B,$A38) -> 309.75 | AA38: =SUMIFS('GL Data'!$AC:$AC,'GL Data'!$B:$B,$A38) -> 427.85
A39: Salaries and Wages | C39: =SUMIFS('GL Data'!$E:$E,'GL Data'!$B:$B,$A39) -> 3601.58 | D39: =SUMIFS('GL Data'!$F:$F,'GL Data'!$B:$B,$A39) -> 2851.58 | E39: =SUMIFS('GL Data'!$G:$G,'GL Data'!$B:$B,$A39) -> 2101.58 | F39: =SUMIFS('GL Data'!$H:$H,'GL Data'!$B:$B,$A39) -> 2101.58 | G39: =SUMIFS('GL Data'!$I:$I,'GL Data'!$B:$B,$A39) -> 2101.58 | H39: =SUMIFS('GL Data'!$J:$J,'GL Data'!$B:$B,$A39) -> 2101.58 | I39: =SUMIFS('GL Data'!$K:$K,'GL Data'!$B:$B,$A39) -> 2101.58 | J39: =SUMIFS('GL Data'!$L:$L,'GL Data'!$B:$B,$A39) -> 2101.58 | K39: =SUMIFS('GL Data'!$M:$M,'GL Data'!$B:$B,$A39) -> 2101.58 | L39: =SUMIFS('GL Data'!$N:$N,'GL Data'!$B:$B,$A39) -> 2101.58 | M39: =SUMIFS('GL Data'!$O:$O,'GL Data'!$B:$B,$A39) -> 2101.58 | N39: =SUMIFS('GL Data'!$P:$P,'GL Data'!$B:$B,$A39) -> 2101.58 | O39: =SUMIFS('GL Data'!$Q:$Q,'GL Data'!$B:$B,$A39) -> 2101.58 | P39: =SUMIFS('GL Data'!$R:$R,'GL Data'!$B:$B,$A39) -> 2101.58 | Q39: =SUMIFS('GL Data'!$S:$S,'GL Data'!$B:$B,$A39) -> 2101.58 | R39: =SUMIFS('GL Data'!$T:$T,'GL Data'!$B:$B,$A39) -> 2101.58 | S39: =SUMIFS('GL Data'!$U:$U,'GL Data'!$B:$B,$A39) -> 2101.59 | T39: =SUMIFS('GL Data'!$V:$V,'GL Data'!$B:$B,$A39) -> 2101.58 | U39: =SUMIFS('GL Data'!$W:$W,'GL Data'!$B:$B,$A39) -> 2101.58 | V39: =SUMIFS('GL Data'!$X:$X,'GL Data'!$B:$B,$A39) -> 2101.58 | W39: =SUMIFS('GL Data'!$Y:$Y,'GL Data'!$B:$B,$A39) -> 2101.58 | X39: =SUMIFS('GL Data'!$Z:$Z,'GL Data'!$B:$B,$A39) -> 2101.58 | Y39: =SUMIFS('GL Data'!$AA:$AA,'GL Data'!$B:$B,$A39) -> 2101.58 | Z39: =SUMIFS('GL Data'!$AB:$AB,'GL Data'!$B:$B,$A39) -> 2101.58 | AA39: =SUMIFS('GL Data'!$AC:$AC,'GL Data'!$B:$B,$A39) -> 2101.58
A40: Owner's Pay | C40: =SUMIFS('GL Data'!$E:$E,'GL Data'!$B:$B,$A40) -> 3564.92 | D40: =SUMIFS('GL Data'!$F:$F,'GL Data'!$B:$B,$A40) -> 3564.92 | E40: =SUMIFS('GL Data'!$G:$G,'GL Data'!$B:$B,$A40) -> 3564.92 | F40: =SUMIFS('GL Data'!$H:$H,'GL Data'!$B:$B,$A40) -> 3564.92 | G40: =SUMIFS('GL Data'!$I:$I,'GL Data'!$B:$B,$A40) -> 3564.92 | H40: =SUMIFS('GL Data'!$J:$J,'GL Data'!$B:$B,$A40) -> 3564.92 | I40: =SUMIFS('GL Data'!$K:$K,'GL Data'!$B:$B,$A40) -> 3564.92 | J40: =SUMIFS('GL Data'!$L:$L,'GL Data'!$B:$B,$A40) -> 3564.92 | K40: =SUMIFS('GL Data'!$M:$M,'GL Data'!$B:$B,$A40) -> 3564.92 | L40: =SUMIFS('GL Data'!$N:$N,'GL Data'!$B:$B,$A40) -> 3564.92 | M40: =SUMIFS('GL Data'!$O:$O,'GL Data'!$B:$B,$A40) -> 3564.92 | N40: =SUMIFS('GL Data'!$P:$P,'GL Data'!$B:$B,$A40) -> 3564.92 | O40: =SUMIFS('GL Data'!$Q:$Q,'GL Data'!$B:$B,$A40) -> 3564.92 | P40: =SUMIFS('GL Data'!$R:$R,'GL Data'!$B:$B,$A40) -> 3564.92 | Q40: =SUMIFS('GL Data'!$S:$S,'GL Data'!$B:$B,$A40) -> 3564.92 | R40: =SUMIFS('GL Data'!$T:$T,'GL Data'!$B:$B,$A40) -> 3564.92 | S40: =SUMIFS('GL Data'!$U:$U,'GL Data'!$B:$B,$A40) -> 3564.91 | T40: =SUMIFS('GL Data'!$V:$V,'GL Data'!$B:$B,$A40) -> 8564.92 | U40: =SUMIFS('GL Data'!$W:$W,'GL Data'!$B:$B,$A40) -> 8564.92 | V40: =SUMIFS('GL Data'!$X:$X,'GL Data'!$B:$B,$A40) -> 5000 | W40: =SUMIFS('GL Data'!$Y:$Y,'GL Data'!$B:$B,$A40) -> 5000 | X40: =SUMIFS('GL Data'!$Z:$Z,'GL Data'!$B:$B,$A40) -> 5000 | Y40: =SUMIFS('GL Data'!$AA:$AA,'GL Data'!$B:$B,$A40) -> 5000 | Z40: =SUMIFS('GL Data'!$AB:$AB,'GL Data'!$B:$B,$A40) -> 5000 | AA40: =SUMIFS('GL Data'!$AC:$AC,'GL Data'!$B:$B,$A40) -> 5000
A41: VA Pay - Smart VA Academy | C41: =SUMIFS('GL Data'!$E:$E,'GL Data'!$B:$B,$A41) -> 590.05 | D41: =SUMIFS('GL Data'!$F:$F,'GL Data'!$B:$B,$A41) -> 437.05 | E41: =SUMIFS('GL Data'!$G:$G,'GL Data'!$B:$B,$A41) -> 565.24 | F41: =SUMIFS('GL Data'!$H:$H,'GL Data'!$B:$B,$A41) -> 481.09 | G41: =SUMIFS('GL Data'!$I:$I,'GL Data'!$B:$B,$A41) -> 396.1 | H41: =SUMIFS('GL Data'!$J:$J,'GL Data'!$B:$B,$A41) -> 529.38 | I41: =SUMIFS('GL Data'!$K:$K,'GL Data'!$B:$B,$A41) -> 441.61 | J41: =SUMIFS('GL Data'!$L:$L,'GL Data'!$B:$B,$A41) -> 37.38 | K41: =SUMIFS('GL Data'!$M:$M,'GL Data'!$B:$B,$A41) -> 336.95 | L41: =SUMIFS('GL Data'!$N:$N,'GL Data'!$B:$B,$A41) -> 137.89 | M41: =SUMIFS('GL Data'!$O:$O,'GL Data'!$B:$B,$A41) -> 217.37 | N41: =SUMIFS('GL Data'!$P:$P,'GL Data'!$B:$B,$A41) -> 373.36 | O41: =SUMIFS('GL Data'!$Q:$Q,'GL Data'!$B:$B,$A41) -> 366.36 | P41: =SUMIFS('GL Data'!$R:$R,'GL Data'!$B:$B,$A41) -> 332.1 | Q41: =SUMIFS('GL Data'!$S:$S,'GL Data'!$B:$B,$A41) -> 227.73 | R41: =SUMIFS('GL Data'!$T:$T,'GL Data'!$B:$B,$A41) -> 358.54 | S41: =SUMIFS('GL Data'!$U:$U,'GL Data'!$B:$B,$A41) -> 181.9 | T41: =SUMIFS('GL Data'!$V:$V,'GL Data'!$B:$B,$A41) -> 194.92 | U41: =SUMIFS('GL Data'!$W:$W,'GL Data'!$B:$B,$A41) -> 65.27 | V41: =SUMIFS('GL Data'!$X:$X,'GL Data'!$B:$B,$A41) -> 87.13 | W41: =SUMIFS('GL Data'!$Y:$Y,'GL Data'!$B:$B,$A41) -> 158.24 | X41: =SUMIFS('GL Data'!$Z:$Z,'GL Data'!$B:$B,$A41) -> 62.3 | Y41: =SUMIFS('GL Data'!$AA:$AA,'GL Data'!$B:$B,$A41) -> 106.41 | Z41: =SUMIFS('GL Data'!$AB:$AB,'GL Data'!$B:$B,$A41) -> 2.48 | AA41: =SUMIFS('GL Data'!$AC:$AC,'GL Data'!$B:$B,$A41) -> 0
A42: Retirement Expense | C42: =SUMIFS('GL Data'!$E:$E,'GL Data'!$B:$B,$A42) -> 214.98 | D42: =SUMIFS('GL Data'!$F:$F,'GL Data'!$B:$B,$A42) -> 192.48 | E42: =SUMIFS('GL Data'!$G:$G,'GL Data'!$B:$B,$A42) -> 169.98 | F42: =SUMIFS('GL Data'!$H:$H,'GL Data'!$B:$B,$A42) -> 169.98 | G42: =SUMIFS('GL Data'!$I:$I,'GL Data'!$B:$B,$A42) -> 169.98 | H42: =SUMIFS('GL Data'!$J:$J,'GL Data'!$B:$B,$A42) -> 169.98 | I42: =SUMIFS('GL Data'!$K:$K,'GL Data'!$B:$B,$A42) -> 169.98 | J42: =SUMIFS('GL Data'!$L:$L,'GL Data'!$B:$B,$A42) -> 169.98 | K42: =SUMIFS('GL Data'!$M:$M,'GL Data'!$B:$B,$A42) -> 169.98 | L42: =SUMIFS('GL Data'!$N:$N,'GL Data'!$B:$B,$A42) -> 169.98 | M42: =SUMIFS('GL Data'!$O:$O,'GL Data'!$B:$B,$A42) -> 169.98 | N42: =SUMIFS('GL Data'!$P:$P,'GL Data'!$B:$B,$A42) -> 169.98 | O42: =SUMIFS('GL Data'!$Q:$Q,'GL Data'!$B:$B,$A42) -> 169.98 | P42: =SUMIFS('GL Data'!$R:$R,'GL Data'!$B:$B,$A42) -> 169.98 | Q42: =SUMIFS('GL Data'!$S:$S,'GL Data'!$B:$B,$A42) -> 169.98 | R42: =SUMIFS('GL Data'!$T:$T,'GL Data'!$B:$B,$A42) -> 169.98 | S42: =SUMIFS('GL Data'!$U:$U,'GL Data'!$B:$B,$A42) -> 169.98 | T42: =SUMIFS('GL Data'!$V:$V,'GL Data'!$B:$B,$A42) -> 319.98 | U42: =SUMIFS('GL Data'!$W:$W,'GL Data'!$B:$B,$A42) -> 319.98 | V42: =SUMIFS('GL Data'!$X:$X,'GL Data'!$B:$B,$A42) -> 213.04 | W42: =SUMIFS('GL Data'!$Y:$Y,'GL Data'!$B:$B,$A42) -> 213.04 | X42: =SUMIFS('GL Data'!$Z:$Z,'GL Data'!$B:$B,$A42) -> 213.04 | Y42: =SUMIFS('GL Data'!$AA:$AA,'GL Data'!$B:$B,$A42) -> 213.04 | Z42: =SUMIFS('GL Data'!$AB:$AB,'GL Data'!$B:$B,$A42) -> 213.04 | AA42: =SUMIFS('GL Data'!$AC:$AC,'GL Data'!$B:$B,$A42) -> 213.04
A43: Payroll Tax | C43: =SUMIFS('GL Data'!$E:$E,'GL Data'!$B:$B,$A43) -> 548.24 | D43: =SUMIFS('GL Data'!$F:$F,'GL Data'!$B:$B,$A43) -> 490.87 | E43: =SUMIFS('GL Data'!$G:$G,'GL Data'!$B:$B,$A43) -> 433.5 | F43: =SUMIFS('GL Data'!$H:$H,'GL Data'!$B:$B,$A43) -> 433.5 | G43: =SUMIFS('GL Data'!$I:$I,'GL Data'!$B:$B,$A43) -> 433.5 | H43: =SUMIFS('GL Data'!$J:$J,'GL Data'!$B:$B,$A43) -> 433.5 | I43: =SUMIFS('GL Data'!$K:$K,'GL Data'!$B:$B,$A43) -> 433.5 | J43: =SUMIFS('GL Data'!$L:$L,'GL Data'!$B:$B,$A43) -> 580.82 | K43: =SUMIFS('GL Data'!$M:$M,'GL Data'!$B:$B,$A43) -> 580.05 | L43: =SUMIFS('GL Data'!$N:$N,'GL Data'!$B:$B,$A43) -> 525.54 | M43: =SUMIFS('GL Data'!$O:$O,'GL Data'!$B:$B,$A43) -> 479.71 | N43: =SUMIFS('GL Data'!$P:$P,'GL Data'!$B:$B,$A43) -> 445.37 | O43: =SUMIFS('GL Data'!$Q:$Q,'GL Data'!$B:$B,$A43) -> 433.5 | P43: =SUMIFS('GL Data'!$R:$R,'GL Data'!$B:$B,$A43) -> 433.5 | Q43: =SUMIFS('GL Data'!$S:$S,'GL Data'!$B:$B,$A43) -> 433.5 | R43: =SUMIFS('GL Data'!$T:$T,'GL Data'!$B:$B,$A43) -> 433.5 | S43: =SUMIFS('GL Data'!$U:$U,'GL Data'!$B:$B,$A43) -> 433.5 | T43: =SUMIFS('GL Data'!$V:$V,'GL Data'!$B:$B,$A43) -> 816 | U43: =SUMIFS('GL Data'!$W:$W,'GL Data'!$B:$B,$A43) -> 816 | V43: =SUMIFS('GL Data'!$X:$X,'GL Data'!$B:$B,$A43) -> 727.92 | W43: =SUMIFS('GL Data'!$Y:$Y,'GL Data'!$B:$B,$A43) -> 689.92 | X43: =SUMIFS('GL Data'!$Z:$Z,'GL Data'!$B:$B,$A43) -> 597.92 | Y43: =SUMIFS('GL Data'!$AA:$AA,'GL Data'!$B:$B,$A43) -> 545.97 | Z43: =SUMIFS('GL Data'!$AB:$AB,'GL Data'!$B:$B,$A43) -> 553.67 | AA43: =SUMIFS('GL Data'!$AC:$AC,'GL Data'!$B:$B,$A43) -> 543.28
A44: Employee Appreciation | C44: =SUMIFS('GL Data'!$E:$E,'GL Data'!$B:$B,$A44) -> 142.75 | D44: =SUMIFS('GL Data'!$F:$F,'GL Data'!$B:$B,$A44) -> 39.34 | E44: =SUMIFS('GL Data'!$G:$G,'GL Data'!$B:$B,$A44) -> 89.43 | F44: =SUMIFS('GL Data'!$H:$H,'GL Data'!$B:$B,$A44) -> 268.82 | G44: =SUMIFS('GL Data'!$I:$I,'GL Data'!$B:$B,$A44) -> 0 | H44: =SUMIFS('GL Data'!$J:$J,'GL Data'!$B:$B,$A44) -> 0 | I44: =SUMIFS('GL Data'!$K:$K,'GL Data'!$B:$B,$A44) -> 17967.81 | J44: =SUMIFS('GL Data'!$L:$L,'GL Data'!$B:$B,$A44) -> 0 | K44: =SUMIFS('GL Data'!$M:$M,'GL Data'!$B:$B,$A44) -> 48.47 | L44: =SUMIFS('GL Data'!$N:$N,'GL Data'!$B:$B,$A44) -> 1728.93 | M44: =SUMIFS('GL Data'!$O:$O,'GL Data'!$B:$B,$A44) -> 827.55 | N44: =SUMIFS('GL Data'!$P:$P,'GL Data'!$B:$B,$A44) -> 91.55 | O44: =SUMIFS('GL Data'!$Q:$Q,'GL Data'!$B:$B,$A44) -> 0 | P44: =SUMIFS('GL Data'!$R:$R,'GL Data'!$B:$B,$A44) -> 110.39 | Q44: =SUMIFS('GL Data'!$S:$S,'GL Data'!$B:$B,$A44) -> 85.49 | R44: =SUMIFS('GL Data'!$T:$T,'GL Data'!$B:$B,$A44) -> 0 | S44: =SUMIFS('GL Data'!$U:$U,'GL Data'!$B:$B,$A44) -> 968.74 | T44: =SUMIFS('GL Data'!$V:$V,'GL Data'!$B:$B,$A44) -> 211.24 | U44: =SUMIFS('GL Data'!$W:$W,'GL Data'!$B:$B,$A44) -> 14667.56 | V44: =SUMIFS('GL Data'!$X:$X,'GL Data'!$B:$B,$A44) -> 107.77 | W44: =SUMIFS('GL Data'!$Y:$Y,'GL Data'!$B:$B,$A44) -> 0 | X44: =SUMIFS('GL Data'!$Z:$Z,'GL Data'!$B:$B,$A44) -> 112.41 | Y44: =SUMIFS('GL Data'!$AA:$AA,'GL Data'!$B:$B,$A44) -> 1363.44 | Z44: =SUMIFS('GL Data'!$AB:$AB,'GL Data'!$B:$B,$A44) -> 164.53 | AA44: =SUMIFS('GL Data'!$AC:$AC,'GL Data'!$B:$B,$A44) -> 105.83
A45: Total Personnel & Leadership | C45: =SUM(C36:C44) -> 22048.9 | D45: =SUM(D36:D44) -> 23004.11 | E45: =SUM(E36:E44) -> 24309.79 | F45: =SUM(F36:F44) -> 23600.01 | G45: =SUM(G36:G44) -> 27003.68 | H45: =SUM(H36:H44) -> 24411.78 | I45: =SUM(I36:I44) -> 38555.7 | J45: =SUM(J36:J44) -> 24130.19 | ... AA45: =SUM(AA36:AA44) -> 22817.42
A47: General & Administrative
A48: Softwares | C48: =SUMIFS('GL Data'!$E:$E,'GL Data'!$B:$B,$A48) -> 2402.06 | D48: =SUMIFS('GL Data'!$F:$F,'GL Data'!$B:$B,$A48) -> 2624.52 | E48: =SUMIFS('GL Data'!$G:$G,'GL Data'!$B:$B,$A48) -> 2308.82 | F48: =SUMIFS('GL Data'!$H:$H,'GL Data'!$B:$B,$A48) -> 3030.72 | G48: =SUMIFS('GL Data'!$I:$I,'GL Data'!$B:$B,$A48) -> 5964.57 | H48: =SUMIFS('GL Data'!$J:$J,'GL Data'!$B:$B,$A48) -> 4063.52 | I48: =SUMIFS('GL Data'!$K:$K,'GL Data'!$B:$B,$A48) -> 4065.77 | J48: =SUMIFS('GL Data'!$L:$L,'GL Data'!$B:$B,$A48) -> 4135.55 | K48: =SUMIFS('GL Data'!$M:$M,'GL Data'!$B:$B,$A48) -> 4204.92 | L48: =SUMIFS('GL Data'!$N:$N,'GL Data'!$B:$B,$A48) -> 2583.92 | M48: =SUMIFS('GL Data'!$O:$O,'GL Data'!$B:$B,$A48) -> 2823.01 | N48: =SUMIFS('GL Data'!$P:$P,'GL Data'!$B:$B,$A48) -> 2502.8 | O48: =SUMIFS('GL Data'!$Q:$Q,'GL Data'!$B:$B,$A48) -> 2615.99 | P48: =SUMIFS('GL Data'!$R:$R,'GL Data'!$B:$B,$A48) -> 2433.48 | Q48: =SUMIFS('GL Data'!$S:$S,'GL Data'!$B:$B,$A48) -> 2510.1 | R48: =SUMIFS('GL Data'!$T:$T,'GL Data'!$B:$B,$A48) -> 4551.99 | S48: =SUMIFS('GL Data'!$U:$U,'GL Data'!$B:$B,$A48) -> 6270.21 | T48: =SUMIFS('GL Data'!$V:$V,'GL Data'!$B:$B,$A48) -> 2649.38 | U48: =SUMIFS('GL Data'!$W:$W,'GL Data'!$B:$B,$A48) -> 2730.43 | V48: =SUMIFS('GL Data'!$X:$X,'GL Data'!$B:$B,$A48) -> 4149.82 | W48: =SUMIFS('GL Data'!$Y:$Y,'GL Data'!$B:$B,$A48) -> 2813.77 | X48: =SUMIFS('GL Data'!$Z:$Z,'GL Data'!$B:$B,$A48) -> 2117.83 | Y48: =SUMIFS('GL Data'!$AA:$AA,'GL Data'!$B:$B,$A48) -> 2940.96 | Z48: =SUMIFS('GL Data'!$AB:$AB,'GL Data'!$B:$B,$A48) -> 2550.81 | AA48: =SUMIFS('GL Data'!$AC:$AC,'GL Data'!$B:$B,$A48) -> 2514.33
A49: Hub Expenses | C49: =SUMIFS('GL Data'!$E:$E,'GL Data'!$B:$B,$A49) -> 232.81 | D49: =SUMIFS('GL Data'!$F:$F,'GL Data'!$B:$B,$A49) -> 330.59 | E49: =SUMIFS('GL Data'!$G:$G,'GL Data'!$B:$B,$A49) -> 331.85 | F49: =SUMIFS('GL Data'!$H:$H,'GL Data'!$B:$B,$A49) -> 473.56 | G49: =SUMIFS('GL Data'!$I:$I,'GL Data'!$B:$B,$A49) -> 193.99 | H49: =SUMIFS('GL Data'!$J:$J,'GL Data'!$B:$B,$A49) -> 308.29 | I49: =SUMIFS('GL Data'!$K:$K,'GL Data'!$B:$B,$A49) -> 76.3 | J49: =SUMIFS('GL Data'!$L:$L,'GL Data'!$B:$B,$A49) -> 192.21 | K49: =SUMIFS('GL Data'!$M:$M,'GL Data'!$B:$B,$A49) -> 176.12 | L49: =SUMIFS('GL Data'!$N:$N,'GL Data'!$B:$B,$A49) -> 256.53 | M49: =SUMIFS('GL Data'!$O:$O,'GL Data'!$B:$B,$A49) -> 161.64 | N49: =SUMIFS('GL Data'!$P:$P,'GL Data'!$B:$B,$A49) -> 22.84 | O49: =SUMIFS('GL Data'!$Q:$Q,'GL Data'!$B:$B,$A49) -> 0 | P49: =SUMIFS('GL Data'!$R:$R,'GL Data'!$B:$B,$A49) -> 0 | Q49: =SUMIFS('GL Data'!$S:$S,'GL Data'!$B:$B,$A49) -> 0 | R49: =SUMIFS('GL Data'!$T:$T,'GL Data'!$B:$B,$A49) -> 0 | S49: =SUMIFS('GL Data'!$U:$U,'GL Data'!$B:$B,$A49) -> 0 | T49: =SUMIFS('GL Data'!$V:$V,'GL Data'!$B:$B,$A49) -> 0 | U49: =SUMIFS('GL Data'!$W:$W,'GL Data'!$B:$B,$A49) -> 0 | V49: =SUMIFS('GL Data'!$X:$X,'GL Data'!$B:$B,$A49) -> 0 | W49: =SUMIFS('GL Data'!$Y:$Y,'GL Data'!$B:$B,$A49) -> 0 | X49: =SUMIFS('GL Data'!$Z:$Z,'GL Data'!$B:$B,$A49) -> 0 | Y49: =SUMIFS('GL Data'!$AA:$AA,'GL Data'!$B:$B,$A49) -> 0 | Z49: =SUMIFS('GL Data'!$AB:$AB,'GL Data'!$B:$B,$A49) -> 0 | AA49: =SUMIFS('GL Data'!$AC:$AC,'GL Data'!$B:$B,$A49) -> 0
A50: Client Appreciation | C50: =SUMIFS('GL Data'!$E:$E,'GL Data'!$B:$B,$A50) -> 0 | D50: =SUMIFS('GL Data'!$F:$F,'GL Data'!$B:$B,$A50) -> 0 | E50: =SUMIFS('GL Data'!$G:$G,'GL Data'!$B:$B,$A50) -> 0 | F50: =SUMIFS('GL Data'!$H:$H,'GL Data'!$B:$B,$A50) -> 0 | G50: =SUMIFS('GL Data'!$I:$I,'GL Data'!$B:$B,$A50) -> 175.36 | H50: =SUMIFS('GL Data'!$J:$J,'GL Data'!$B:$B,$A50) -> 31.18 | I50: =SUMIFS('GL Data'!$K:$K,'GL Data'!$B:$B,$A50) -> 0 | J50: =SUMIFS('GL Data'!$L:$L,'GL Data'!$B:$B,$A50) -> 0 | K50: =SUMIFS('GL Data'!$M:$M,'GL Data'!$B:$B,$A50) -> 0 | L50: =SUMIFS('GL Data'!$N:$N,'GL Data'!$B:$B,$A50) -> 0 | M50: =SUMIFS('GL Data'!$O:$O,'GL Data'!$B:$B,$A50) -> 0 | N50: =SUMIFS('GL Data'!$P:$P,'GL Data'!$B:$B,$A50) -> 0 | O50: =SUMIFS('GL Data'!$Q:$Q,'GL Data'!$B:$B,$A50) -> 113.9 | P50: =SUMIFS('GL Data'!$R:$R,'GL Data'!$B:$B,$A50) -> 0 | Q50: =SUMIFS('GL Data'!$S:$S,'GL Data'!$B:$B,$A50) -> 0 | R50: =SUMIFS('GL Data'!$T:$T,'GL Data'!$B:$B,$A50) -> 0 | S50: =SUMIFS('GL Data'!$U:$U,'GL Data'!$B:$B,$A50) -> 0 | T50: =SUMIFS('GL Data'!$V:$V,'GL Data'!$B:$B,$A50) -> 0 | U50: =SUMIFS('GL Data'!$W:$W,'GL Data'!$B:$B,$A50) -> 547.61 | V50: =SUMIFS('GL Data'!$X:$X,'GL Data'!$B:$B,$A50) -> 0 | W50: =SUMIFS('GL Data'!$Y:$Y,'GL Data'!$B:$B,$A50) -> 0 | X50: =SUMIFS('GL Data'!$Z:$Z,'GL Data'!$B:$B,$A50) -> 0 | Y50: =SUMIFS('GL Data'!$AA:$AA,'GL Data'!$B:$B,$A50) -> 0 | Z50: =SUMIFS('GL Data'!$AB:$AB,'GL Data'!$B:$B,$A50) -> 0 | AA50: =SUMIFS('GL Data'!$AC:$AC,'GL Data'!$B:$B,$A50) -> 0
A51: Phone & Internet | C51: =SUMIFS('GL Data'!$E:$E,'GL Data'!$B:$B,$A51) -> 99.99 | D51: =SUMIFS('GL Data'!$F:$F,'GL Data'!$B:$B,$A51) -> 99.99 | E51: =SUMIFS('GL Data'!$G:$G,'GL Data'!$B:$B,$A51) -> 99.99 | F51: =SUMIFS('GL Data'!$H:$H,'GL Data'!$B:$B,$A51) -> 104.99 | G51: =SUMIFS('GL Data'!$I:$I,'GL Data'!$B:$B,$A51) -> 104.99 | H51: =SUMIFS('GL Data'!$J:$J,'GL Data'!$B:$B,$A51) -> 104.99 | I51: =SUMIFS('GL Data'!$K:$K,'GL Data'!$B:$B,$A51) -> 104.99 | J51: =SUMIFS('GL Data'!$L:$L,'GL Data'!$B:$B,$A51) -> 104.99 | K51: =SUMIFS('GL Data'!$M:$M,'GL Data'!$B:$B,$A51) -> 104.99 | L51: =SUMIFS('GL Data'!$N:$N,'GL Data'!$B:$B,$A51) -> 114.99 | M51: =SUMIFS('GL Data'!$O:$O,'GL Data'!$B:$B,$A51) -> 114.99 | N51: =SUMIFS('GL Data'!$P:$P,'GL Data'!$B:$B,$A51) -> 114.99 | O51: =SUMIFS('GL Data'!$Q:$Q,'GL Data'!$B:$B,$A51) -> 114.99 | P51: =SUMIFS('GL Data'!$R:$R,'GL Data'!$B:$B,$A51) -> 114.99 | Q51: =SUMIFS('GL Data'!$S:$S,'GL Data'!$B:$B,$A51) -> 114.99 | R51: =SUMIFS('GL Data'!$T:$T,'GL Data'!$B:$B,$A51) -> 114.99 | S51: =SUMIFS('GL Data'!$U:$U,'GL Data'!$B:$B,$A51) -> 114.99 | T51: =SUMIFS('GL Data'!$V:$V,'GL Data'!$B:$B,$A51) -> 114.99 | U51: =SUMIFS('GL Data'!$W:$W,'GL Data'!$B:$B,$A51) -> 114.99 | V51: =SUMIFS('GL Data'!$X:$X,'GL Data'!$B:$B,$A51) -> 114.99 | W51: =SUMIFS('GL Data'!$Y:$Y,'GL Data'!$B:$B,$A51) -> 114.99 | X51: =SUMIFS('GL Data'!$Z:$Z,'GL Data'!$B:$B,$A51) -> 129.99 | Y51: =SUMIFS('GL Data'!$AA:$AA,'GL Data'!$B:$B,$A51) -> 129.99 | Z51: =SUMIFS('GL Data'!$AB:$AB,'GL Data'!$B:$B,$A51) -> 129.99 | AA51: =SUMIFS('GL Data'!$AC:$AC,'GL Data'!$B:$B,$A51) -> 129.99
A52: Postage | C52: =SUMIFS('GL Data'!$E:$E,'GL Data'!$B:$B,$A52) -> 25.39 | D52: =SUMIFS('GL Data'!$F:$F,'GL Data'!$B:$B,$A52) -> 14.99 | E52: =SUMIFS('GL Data'!$G:$G,'GL Data'!$B:$B,$A52) -> 17.32 | F52: =SUMIFS('GL Data'!$H:$H,'GL Data'!$B:$B,$A52) -> 14.99 | G52: =SUMIFS('GL Data'!$I:$I,'GL Data'!$B:$B,$A52) -> 30.4 | H52: =SUMIFS('GL Data'!$J:$J,'GL Data'!$B:$B,$A52) -> 34.29 | I52: =SUMIFS('GL Data'!$K:$K,'GL Data'!$B:$B,$A52) -> 14.99 | J52: =SUMIFS('GL Data'!$L:$L,'GL Data'!$B:$B,$A52) -> 17.32 | K52: =SUMIFS('GL Data'!$M:$M,'GL Data'!$B:$B,$A52) -> 14.99 | L52: =SUMIFS('GL Data'!$N:$N,'GL Data'!$B:$B,$A52) -> 30.84 | M52: =SUMIFS('GL Data'!$O:$O,'GL Data'!$B:$B,$A52) -> 14.99 | N52: =SUMIFS('GL Data'!$P:$P,'GL Data'!$B:$B,$A52) -> 20.94 | O52: =SUMIFS('GL Data'!$Q:$Q,'GL Data'!$B:$B,$A52) -> 17.32 | P52: =SUMIFS('GL Data'!$R:$R,'GL Data'!$B:$B,$A52) -> 14.99 | Q52: =SUMIFS('GL Data'!$S:$S,'GL Data'!$B:$B,$A52) -> 14.99 | R52: =SUMIFS('GL Data'!$T:$T,'GL Data'!$B:$B,$A52) -> 14.99 | S52: =SUMIFS('GL Data'!$U:$U,'GL Data'!$B:$B,$A52) -> 27.49 | T52: =SUMIFS('GL Data'!$V:$V,'GL Data'!$B:$B,$A52) -> 14.99 | U52: =SUMIFS('GL Data'!$W:$W,'GL Data'!$B:$B,$A52) -> 17.38 | V52: =SUMIFS('GL Data'!$X:$X,'GL Data'!$B:$B,$A52) -> 14.99 | W52: =SUMIFS('GL Data'!$Y:$Y,'GL Data'!$B:$B,$A52) -> 14.99 | X52: =SUMIFS('GL Data'!$Z:$Z,'GL Data'!$B:$B,$A52) -> 27.2 | Y52: =SUMIFS('GL Data'!$AA:$AA,'GL Data'!$B:$B,$A52) -> 14.99 | Z52: =SUMIFS('GL Data'!$AB:$AB,'GL Data'!$B:$B,$A52) -> 14.99 | AA52: =SUMIFS('GL Data'!$AC:$AC,'GL Data'!$B:$B,$A52) -> 22.18
A53: Office Supplies | C53: =SUMIFS('GL Data'!$E:$E,'GL Data'!$B:$B,$A53) -> 0 | D53: =SUMIFS('GL Data'!$F:$F,'GL Data'!$B:$B,$A53) -> 257.55 | E53: =SUMIFS('GL Data'!$G:$G,'GL Data'!$B:$B,$A53) -> 0 | F53: =SUMIFS('GL Data'!$H:$H,'GL Data'!$B:$B,$A53) -> 0 | G53: =SUMIFS('GL Data'!$I:$I,'GL Data'!$B:$B,$A53) -> 0 | H53: =SUMIFS('GL Data'!$J:$J,'GL Data'!$B:$B,$A53) -> 19.84 | I53: =SUMIFS('GL Data'!$K:$K,'GL Data'!$B:$B,$A53) -> 149 | J53: =SUMIFS('GL Data'!$L:$L,'GL Data'!$B:$B,$A53) -> 0 | K53: =SUMIFS('GL Data'!$M:$M,'GL Data'!$B:$B,$A53) -> 0 | L53: =SUMIFS('GL Data'!$N:$N,'GL Data'!$B:$B,$A53) -> 0 | M53: =SUMIFS('GL Data'!$O:$O,'GL Data'!$B:$B,$A53) -> 0 | N53: =SUMIFS('GL Data'!$P:$P,'GL Data'!$B:$B,$A53) -> 12.86 | O53: =SUMIFS('GL Data'!$Q:$Q,'GL Data'!$B:$B,$A53) -> 0 | P53: =SUMIFS('GL Data'!$R:$R,'GL Data'!$B:$B,$A53) -> 55.43 | Q53: =SUMIFS('GL Data'!$S:$S,'GL Data'!$B:$B,$A53) -> 0 | R53: =SUMIFS('GL Data'!$T:$T,'GL Data'!$B:$B,$A53) -> 0 | S53: =SUMIFS('GL Data'!$U:$U,'GL Data'!$B:$B,$A53) -> 0 | T53: =SUMIFS('GL Data'!$V:$V,'GL Data'!$B:$B,$A53) -> 0 | U53: =SUMIFS('GL Data'!$W:$W,'GL Data'!$B:$B,$A53) -> 0 | V53: =SUMIFS('GL Data'!$X:$X,'GL Data'!$B:$B,$A53) -> 0 | W53: =SUMIFS('GL Data'!$Y:$Y,'GL Data'!$B:$B,$A53) -> 0 | X53: =SUMIFS('GL Data'!$Z:$Z,'GL Data'!$B:$B,$A53) -> 0 | Y53: =SUMIFS('GL Data'!$AA:$AA,'GL Data'!$B:$B,$A53) -> 0 | Z53: =SUMIFS('GL Data'!$AB:$AB,'GL Data'!$B:$B,$A53) -> 0 | AA53: =SUMIFS('GL Data'!$AC:$AC,'GL Data'!$B:$B,$A53) -> 0
A54: Travel | C54: =SUMIFS('GL Data'!$E:$E,'GL Data'!$B:$B,$A54) -> 415.49 | D54: =SUMIFS('GL Data'!$F:$F,'GL Data'!$B:$B,$A54) -> 415.46 | E54: =SUMIFS('GL Data'!$G:$G,'GL Data'!$B:$B,$A54) -> 0 | F54: =SUMIFS('GL Data'!$H:$H,'GL Data'!$B:$B,$A54) -> 0 | G54: =SUMIFS('GL Data'!$I:$I,'GL Data'!$B:$B,$A54) -> 0 | H54: =SUMIFS('GL Data'!$J:$J,'GL Data'!$B:$B,$A54) -> 0 | I54: =SUMIFS('GL Data'!$K:$K,'GL Data'!$B:$B,$A54) -> 966.45 | J54: =SUMIFS('GL Data'!$L:$L,'GL Data'!$B:$B,$A54) -> 571.53 | K54: =SUMIFS('GL Data'!$M:$M,'GL Data'!$B:$B,$A54) -> 571.53 | L54: =SUMIFS('GL Data'!$N:$N,'GL Data'!$B:$B,$A54) -> 1726.64 | M54: =SUMIFS('GL Data'!$O:$O,'GL Data'!$B:$B,$A54) -> -442.91 | N54: =SUMIFS('GL Data'!$P:$P,'GL Data'!$B:$B,$A54) -> 571 | O54: =SUMIFS('GL Data'!$Q:$Q,'GL Data'!$B:$B,$A54) -> 0 | P54: =SUMIFS('GL Data'!$R:$R,'GL Data'!$B:$B,$A54) -> 0 | Q54: =SUMIFS('GL Data'!$S:$S,'GL Data'!$B:$B,$A54) -> 0 | R54: =SUMIFS('GL Data'!$T:$T,'GL Data'!$B:$B,$A54) -> 0 | S54: =SUMIFS('GL Data'!$U:$U,'GL Data'!$B:$B,$A54) -> 0 | T54: =SUMIFS('GL Data'!$V:$V,'GL Data'!$B:$B,$A54) -> 0 | U54: =SUMIFS('GL Data'!$W:$W,'GL Data'!$B:$B,$A54) -> 0 | V54: =SUMIFS('GL Data'!$X:$X,'GL Data'!$B:$B,$A54) -> 582.28 | W54: =SUMIFS('GL Data'!$Y:$Y,'GL Data'!$B:$B,$A54) -> 0 | X54: =SUMIFS('GL Data'!$Z:$Z,'GL Data'!$B:$B,$A54) -> 0 | Y54: =SUMIFS('GL Data'!$AA:$AA,'GL Data'!$B:$B,$A54) -> 0 | Z54: =SUMIFS('GL Data'!$AB:$AB,'GL Data'!$B:$B,$A54) -> 0 | AA54: =SUMIFS('GL Data'!$AC:$AC,'GL Data'!$B:$B,$A54) -> 1191.54
A55: Meals | C55: =SUMIFS('GL Data'!$E:$E,'GL Data'!$B:$B,$A55) -> 0 | D55: =SUMIFS('GL Data'!$F:$F,'GL Data'!$B:$B,$A55) -> 0 | E55: =SUMIFS('GL Data'!$G:$G,'GL Data'!$B:$B,$A55) -> 0 | F55: =SUMIFS('GL Data'!$H:$H,'GL Data'!$B:$B,$A55) -> 0 | G55: =SUMIFS('GL Data'!$I:$I,'GL Data'!$B:$B,$A55) -> 0 | H55: =SUMIFS('GL Data'!$J:$J,'GL Data'!$B:$B,$A55) -> 0 | I55: =SUMIFS('GL Data'!$K:$K,'GL Data'!$B:$B,$A55) -> 0 | J55: =SUMIFS('GL Data'!$L:$L,'GL Data'!$B:$B,$A55) -> 0 | K55: =SUMIFS('GL Data'!$M:$M,'GL Data'!$B:$B,$A55) -> 0 | L55: =SUMIFS('GL Data'!$N:$N,'GL Data'!$B:$B,$A55) -> 0 | M55: =SUMIFS('GL Data'!$O:$O,'GL Data'!$B:$B,$A55) -> 0 | N55: =SUMIFS('GL Data'!$P:$P,'GL Data'!$B:$B,$A55) -> 0 | O55: =SUMIFS('GL Data'!$Q:$Q,'GL Data'!$B:$B,$A55) -> 0 | P55: =SUMIFS('GL Data'!$R:$R,'GL Data'!$B:$B,$A55) -> 0 | Q55: =SUMIFS('GL Data'!$S:$S,'GL Data'!$B:$B,$A55) -> 0 | R55: =SUMIFS('GL Data'!$T:$T,'GL Data'!$B:$B,$A55) -> 0 | S55: =SUMIFS('GL Data'!$U:$U,'GL Data'!$B:$B,$A55) -> 0 | T55: =SUMIFS('GL Data'!$V:$V,'GL Data'!$B:$B,$A55) -> 0 | U55: =SUMIFS('GL Data'!$W:$W,'GL Data'!$B:$B,$A55) -> 0 | V55: =SUMIFS('GL Data'!$X:$X,'GL Data'!$B:$B,$A55) -> 0 | W55: =SUMIFS('GL Data'!$Y:$Y,'GL Data'!$B:$B,$A55) -> 0 | X55: =SUMIFS('GL Data'!$Z:$Z,'GL Data'!$B:$B,$A55) -> 0 | Y55: =SUMIFS('GL Data'!$AA:$AA,'GL Data'!$B:$B,$A55) -> 0 | Z55: =SUMIFS('GL Data'!$AB:$AB,'GL Data'!$B:$B,$A55) -> 0 | AA55: =SUMIFS('GL Data'!$AC:$AC,'GL Data'!$B:$B,$A55) -> 0
A56: Training and Development | C56: =SUMIFS('GL Data'!$E:$E,'GL Data'!$B:$B,$A56) -> 52.26 | D56: =SUMIFS('GL Data'!$F:$F,'GL Data'!$B:$B,$A56) -> 442 | E56: =SUMIFS('GL Data'!$G:$G,'GL Data'!$B:$B,$A56) -> 463 | F56: =SUMIFS('GL Data'!$H:$H,'GL Data'!$B:$B,$A56) -> 49.57 | G56: =SUMIFS('GL Data'!$I:$I,'GL Data'!$B:$B,$A56) -> 47 | H56: =SUMIFS('GL Data'!$J:$J,'GL Data'!$B:$B,$A56) -> 47 | I56: =SUMIFS('GL Data'!$K:$K,'GL Data'!$B:$B,$A56) -> 47 | J56: =SUMIFS('GL Data'!$L:$L,'GL Data'!$B:$B,$A56) -> 74.64 | K56: =SUMIFS('GL Data'!$M:$M,'GL Data'!$B:$B,$A56) -> 27 | L56: =SUMIFS('GL Data'!$N:$N,'GL Data'!$B:$B,$A56) -> 0 | M56: =SUMIFS('GL Data'!$O:$O,'GL Data'!$B:$B,$A56) -> 0 | N56: =SUMIFS('GL Data'!$P:$P,'GL Data'!$B:$B,$A56) -> 0 | O56: =SUMIFS('GL Data'!$Q:$Q,'GL Data'!$B:$B,$A56) -> 0 | P56: =SUMIFS('GL Data'!$R:$R,'GL Data'!$B:$B,$A56) -> 0 | Q56: =SUMIFS('GL Data'!$S:$S,'GL Data'!$B:$B,$A56) -> 89.17 | R56: =SUMIFS('GL Data'!$T:$T,'GL Data'!$B:$B,$A56) -> 0 | S56: =SUMIFS('GL Data'!$U:$U,'GL Data'!$B:$B,$A56) -> 1145 | T56: =SUMIFS('GL Data'!$V:$V,'GL Data'!$B:$B,$A56) -> 0 | U56: =SUMIFS('GL Data'!$W:$W,'GL Data'!$B:$B,$A56) -> 500 | V56: =SUMIFS('GL Data'!$X:$X,'GL Data'!$B:$B,$A56) -> 0 | W56: =SUMIFS('GL Data'!$Y:$Y,'GL Data'!$B:$B,$A56) -> 107.25 | X56: =SUMIFS('GL Data'!$Z:$Z,'GL Data'!$B:$B,$A56) -> 0 | Y56: =SUMIFS('GL Data'!$AA:$AA,'GL Data'!$B:$B,$A56) -> 0 | Z56: =SUMIFS('GL Data'!$AB:$AB,'GL Data'!$B:$B,$A56) -> 0 | AA56: =SUMIFS('GL Data'!$AC:$AC,'GL Data'!$B:$B,$A56) -> 0
A57: Rent Expense | C57: =SUMIFS('GL Data'!$E:$E,'GL Data'!$B:$B,$A57) -> 327.05 | D57: =SUMIFS('GL Data'!$F:$F,'GL Data'!$B:$B,$A57) -> 330.63 | E57: =SUMIFS('GL Data'!$G:$G,'GL Data'!$B:$B,$A57) -> 0 | F57: =SUMIFS('GL Data'!$H:$H,'GL Data'!$B:$B,$A57) -> 684.7 | G57: =SUMIFS('GL Data'!$I:$I,'GL Data'!$B:$B,$A57) -> 330.9 | H57: =SUMIFS('GL Data'!$J:$J,'GL Data'!$B:$B,$A57) -> 326.22 | I57: =SUMIFS('GL Data'!$K:$K,'GL Data'!$B:$B,$A57) -> 327.07 | J57: =SUMIFS('GL Data'!$L:$L,'GL Data'!$B:$B,$A57) -> 327.64 | K57: =SUMIFS('GL Data'!$M:$M,'GL Data'!$B:$B,$A57) -> 331.33 | L57: =SUMIFS('GL Data'!$N:$N,'GL Data'!$B:$B,$A57) -> 0 | M57: =SUMIFS('GL Data'!$O:$O,'GL Data'!$B:$B,$A57) -> 0 | N57: =SUMIFS('GL Data'!$P:$P,'GL Data'!$B:$B,$A57) -> 0 | O57: =SUMIFS('GL Data'!$Q:$Q,'GL Data'!$B:$B,$A57) -> 0 | P57: =SUMIFS('GL Data'!$R:$R,'GL Data'!$B:$B,$A57) -> 0 | Q57: =SUMIFS('GL Data'!$S:$S,'GL Data'!$B:$B,$A57) -> 0 | R57: =SUMIFS('GL Data'!$T:$T,'GL Data'!$B:$B,$A57) -> 0 | S57: =SUMIFS('GL Data'!$U:$U,'GL Data'!$B:$B,$A57) -> 0 | T57: =SUMIFS('GL Data'!$V:$V,'GL Data'!$B:$B,$A57) -> 0 | U57: =SUMIFS('GL Data'!$W:$W,'GL Data'!$B:$B,$A57) -> 0 | V57: =SUMIFS('GL Data'!$X:$X,'GL Data'!$B:$B,$A57) -> 0 | W57: =SUMIFS('GL Data'!$Y:$Y,'GL Data'!$B:$B,$A57) -> 0 | X57: =SUMIFS('GL Data'!$Z:$Z,'GL Data'!$B:$B,$A57) -> 0 | Y57: =SUMIFS('GL Data'!$AA:$AA,'GL Data'!$B:$B,$A57) -> 0 | Z57: =SUMIFS('GL Data'!$AB:$AB,'GL Data'!$B:$B,$A57) -> 0 | AA57: =SUMIFS('GL Data'!$AC:$AC,'GL Data'!$B:$B,$A57) -> 0
A58: Legal & Professional Services | C58: =SUMIFS('GL Data'!$E:$E,'GL Data'!$B:$B,$A58) -> 721.57 | D58: =SUMIFS('GL Data'!$F:$F,'GL Data'!$B:$B,$A58) -> 2778.75 | E58: =SUMIFS('GL Data'!$G:$G,'GL Data'!$B:$B,$A58) -> 1910 | F58: =SUMIFS('GL Data'!$H:$H,'GL Data'!$B:$B,$A58) -> 3291.25 | G58: =SUMIFS('GL Data'!$I:$I,'GL Data'!$B:$B,$A58) -> 2759.15 | H58: =SUMIFS('GL Data'!$J:$J,'GL Data'!$B:$B,$A58) -> 3190.62 | I58: =SUMIFS('GL Data'!$K:$K,'GL Data'!$B:$B,$A58) -> 6380.7 | J58: =SUMIFS('GL Data'!$L:$L,'GL Data'!$B:$B,$A58) -> 3271.8 | K58: =SUMIFS('GL Data'!$M:$M,'GL Data'!$B:$B,$A58) -> 1925 | L58: =SUMIFS('GL Data'!$N:$N,'GL Data'!$B:$B,$A58) -> 425 | M58: =SUMIFS('GL Data'!$O:$O,'GL Data'!$B:$B,$A58) -> 425 | N58: =SUMIFS('GL Data'!$P:$P,'GL Data'!$B:$B,$A58) -> 1777.15 | O58: =SUMIFS('GL Data'!$Q:$Q,'GL Data'!$B:$B,$A58) -> 1112.5 | P58: =SUMIFS('GL Data'!$R:$R,'GL Data'!$B:$B,$A58) -> 425 | Q58: =SUMIFS('GL Data'!$S:$S,'GL Data'!$B:$B,$A58) -> 425 | R58: =SUMIFS('GL Data'!$T:$T,'GL Data'!$B:$B,$A58) -> 1387.5 | S58: =SUMIFS('GL Data'!$U:$U,'GL Data'!$B:$B,$A58) -> 425 | T58: =SUMIFS('GL Data'!$V:$V,'GL Data'!$B:$B,$A58) -> 700 | U58: =SUMIFS('GL Data'!$W:$W,'GL Data'!$B:$B,$A58) -> 700 | V58: =SUMIFS('GL Data'!$X:$X,'GL Data'!$B:$B,$A58) -> 425 | W58: =SUMIFS('GL Data'!$Y:$Y,'GL Data'!$B:$B,$A58) -> 425 | X58: =SUMIFS('GL Data'!$Z:$Z,'GL Data'!$B:$B,$A58) -> 425 | Y58: =SUMIFS('GL Data'!$AA:$AA,'GL Data'!$B:$B,$A58) -> 425 | Z58: =SUMIFS('GL Data'!$AB:$AB,'GL Data'!$B:$B,$A58) -> 425 | AA58: =SUMIFS('GL Data'!$AC:$AC,'GL Data'!$B:$B,$A58) -> 425
A59: Charitable Contributions | C59: =SUMIFS('GL Data'!$E:$E,'GL Data'!$B:$B,$A59) -> 0 | D59: =SUMIFS('GL Data'!$F:$F,'GL Data'!$B:$B,$A59) -> 0 | E59: =SUMIFS('GL Data'!$G:$G,'GL Data'!$B:$B,$A59) -> 0 | F59: =SUMIFS('GL Data'!$H:$H,'GL Data'!$B:$B,$A59) -> 0 | G59: =SUMIFS('GL Data'!$I:$I,'GL Data'!$B:$B,$A59) -> 0 | H59: =SUMIFS('GL Data'!$J:$J,'GL Data'!$B:$B,$A59) -> 0 | I59: =SUMIFS('GL Data'!$K:$K,'GL Data'!$B:$B,$A59) -> 0 | J59: =SUMIFS('GL Data'!$L:$L,'GL Data'!$B:$B,$A59) -> 0 | K59: =SUMIFS('GL Data'!$M:$M,'GL Data'!$B:$B,$A59) -> 0 | L59: =SUMIFS('GL Data'!$N:$N,'GL Data'!$B:$B,$A59) -> 0 | M59: =SUMIFS('GL Data'!$O:$O,'GL Data'!$B:$B,$A59) -> 0 | N59: =SUMIFS('GL Data'!$P:$P,'GL Data'!$B:$B,$A59) -> 0 | O59: =SUMIFS('GL Data'!$Q:$Q,'GL Data'!$B:$B,$A59) -> 0 | P59: =SUMIFS('GL Data'!$R:$R,'GL Data'!$B:$B,$A59) -> 0 | Q59: =SUMIFS('GL Data'!$S:$S,'GL Data'!$B:$B,$A59) -> 0 | R59: =SUMIFS('GL Data'!$T:$T,'GL Data'!$B:$B,$A59) -> 0 | S59: =SUMIFS('GL Data'!$U:$U,'GL Data'!$B:$B,$A59) -> 100 | T59: =SUMIFS('GL Data'!$V:$V,'GL Data'!$B:$B,$A59) -> 0 | U59: =SUMIFS('GL Data'!$W:$W,'GL Data'!$B:$B,$A59) -> 200 | V59: =SUMIFS('GL Data'!$X:$X,'GL Data'!$B:$B,$A59) -> 100 | W59: =SUMIFS('GL Data'!$Y:$Y,'GL Data'!$B:$B,$A59) -> 100 | X59: =SUMIFS('GL Data'!$Z:$Z,'GL Data'!$B:$B,$A59) -> 100 | Y59: =SUMIFS('GL Data'!$AA:$AA,'GL Data'!$B:$B,$A59) -> 100 | Z59: =SUMIFS('GL Data'!$AB:$AB,'GL Data'!$B:$B,$A59) -> 100 | AA59: =SUMIFS('GL Data'!$AC:$AC,'GL Data'!$B:$B,$A59) -> 100
... A63: Unapplied Cash Bill Payments | C63: =SUMIFS('GL Data'!$E:$E,'GL Data'!$B:$B,$A63) -> 0 | D63: =SUMIFS('GL Data'!$F:$F,'GL Data'!$B:$B,$A63) -> 0 | E63: =SUMIFS('GL Data'!$G:$G,'GL Data'!$B:$B,$A63) -> 0 | F63: =SUMIFS('GL Data'!$H:$H,'GL Data'!$B:$B,$A63) -> 0 | G63: =SUMIFS('GL Data'!$I:$I,'GL Data'!$B:$B,$A63) -> 0 | H63: =SUMIFS('GL Data'!$J:$J,'GL Data'!$B:$B,$A63) -> 0 | I63: =SUMIFS('GL Data'!$K:$K,'GL Data'!$B:$B,$A63) -> 0 | J63: =SUMIFS('GL Data'!$L:$L,'GL Data'!$B:$B,$A63) -> 0 | K63: =SUMIFS('GL Data'!$M:$M,'GL Data'!$B:$B,$A63) -> 0 | L63: =SUMIFS('GL Data'!$N:$N,'GL Data'!$B:$B,$A63) -> 0 | M63: =SUMIFS('GL Data'!$O:$O,'GL Data'!$B:$B,$A63) -> 0 | N63: =SUMIFS('GL Data'!$P:$P,'GL Data'!$B:$B,$A63) -> 0 | O63: =SUMIFS('GL Data'!$Q:$Q,'GL Data'!$B:$B,$A63) -> 0 | P63: =SUMIFS('GL Data'!$R:$R,'GL Data'!$B:$B,$A63) -> 0 | Q63: =SUMIFS('GL Data'!$S:$S,'GL Data'!$B:$B,$A63) -> 0 | R63: =SUMIFS('GL Data'!$T:$T,'GL Data'!$B:$B,$A63) -> 0 | S63: =SUMIFS('GL Data'!$U:$U,'GL Data'!$B:$B,$A63) -> 0 | T63: =SUMIFS('GL Data'!$V:$V,'GL Data'!$B:$B,$A63) -> 0 | U63: =SUMIFS('GL Data'!$W:$W,'GL Data'!$B:$B,$A63) -> 0 | V63: =SUMIFS('GL Data'!$X:$X,'GL Data'!$B:$B,$A63) -> 0 | W63: =SUMIFS('GL Data'!$Y:$Y,'GL Data'!$B:$B,$A63) -> 0 | X63: =SUMIFS('GL Data'!$Z:$Z,'GL Data'!$B:$B,$A63) -> 0 | Y63: =SUMIFS('GL Data'!$AA:$AA,'GL Data'!$B:$B,$A63) -> 0 | Z63: =SUMIFS('GL Data'!$AB:$AB,'GL Data'!$B:$B,$A63) -> 0 | AA63: =SUMIFS('GL Data'!$AC:$AC,'GL Data'!$B:$B,$A63) -> 0
A64: Total General & Administrative | C64: =SUM(C48:C63) -> 4277.29 | D64: =SUM(D48:D63) -> 7295.15 | E64: =SUM(E48:E63) -> 5131.65 | F64: =SUM(F48:F63) -> 7649.78 | G64: =SUM(G48:G63) -> 9611.54 | H64: =SUM(H48:H63) -> 8128.07 | I64: =SUM(I48:I63) -> 23559.24 | J64: =SUM(J48:J63) -> 8697.25 | ... AA64: =SUM(AA48:AA63) -> 4383.04
A66: Fees and Charges
A67: Bank Charges & Fees | C67: =SUMIFS('GL Data'!$E:$E,'GL Data'!$B:$B,$A67) -> 470.33 | D67: =SUMIFS('GL Data'!$F:$F,'GL Data'!$B:$B,$A67) -> 462.12 | E67: =SUMIFS('GL Data'!$G:$G,'GL Data'!$B:$B,$A67) -> 397 | F67: =SUMIFS('GL Data'!$H:$H,'GL Data'!$B:$B,$A67) -> 319.04 | G67: =SUMIFS('GL Data'!$I:$I,'GL Data'!$B:$B,$A67) -> 320.48 | H67: =SUMIFS('GL Data'!$J:$J,'GL Data'!$B:$B,$A67) -> 441.55 | I67: =SUMIFS('GL Data'!$K:$K,'GL Data'!$B:$B,$A67) -> 386.42 | J67: =SUMIFS('GL Data'!$L:$L,'GL Data'!$B:$B,$A67) -> 262.14 | K67: =SUMIFS('GL Data'!$M:$M,'GL Data'!$B:$B,$A67) -> 410.33 | L67: =SUMIFS('GL Data'!$N:$N,'GL Data'!$B:$B,$A67) -> 471.14 | M67: =SUMIFS('GL Data'!$O:$O,'GL Data'!$B:$B,$A67) -> 543.1 | N67: =SUMIFS('GL Data'!$P:$P,'GL Data'!$B:$B,$A67) -> 542.49 | O67: =SUMIFS('GL Data'!$Q:$Q,'GL Data'!$B:$B,$A67) -> 393.98 | P67: =SUMIFS('GL Data'!$R:$R,'GL Data'!$B:$B,$A67) -> 633.66 | Q67: =SUMIFS('GL Data'!$S:$S,'GL Data'!$B:$B,$A67) -> 306.38 | R67: =SUMIFS('GL Data'!$T:$T,'GL Data'!$B:$B,$A67) -> 238.38 | S67: =SUMIFS('GL Data'!$U:$U,'GL Data'!$B:$B,$A67) -> 50 | T67: =SUMIFS('GL Data'!$V:$V,'GL Data'!$B:$B,$A67) -> 200 | U67: =SUMIFS('GL Data'!$W:$W,'GL Data'!$B:$B,$A67) -> 75 | V67: =SUMIFS('GL Data'!$X:$X,'GL Data'!$B:$B,$A67) -> 50 | W67: =SUMIFS('GL Data'!$Y:$Y,'GL Data'!$B:$B,$A67) -> 50 | X67: =SUMIFS('GL Data'!$Z:$Z,'GL Data'!$B:$B,$A67) -> 50 | Y67: =SUMIFS('GL Data'!$AA:$AA,'GL Data'!$B:$B,$A67) -> 50 | Z67: =SUMIFS('GL Data'!$AB:$AB,'GL Data'!$B:$B,$A67) -> 50 | AA67: =SUMIFS('GL Data'!$AC:$AC,'GL Data'!$B:$B,$A67) -> 50
A68: Credit Card Fees | C68: =SUMIFS('GL Data'!$E:$E,'GL Data'!$B:$B,$A68) -> 2021.82 | D68: =SUMIFS('GL Data'!$F:$F,'GL Data'!$B:$B,$A68) -> 2238.34 | E68: =SUMIFS('GL Data'!$G:$G,'GL Data'!$B:$B,$A68) -> 2179.75 | F68: =SUMIFS('GL Data'!$H:$H,'GL Data'!$B:$B,$A68) -> 2056.74 | G68: =SUMIFS('GL Data'!$I:$I,'GL Data'!$B:$B,$A68) -> 2287.53 | H68: =SUMIFS('GL Data'!$J:$J,'GL Data'!$B:$B,$A68) -> 2147.83 | I68: =SUMIFS('GL Data'!$K:$K,'GL Data'!$B:$B,$A68) -> 2006.63 | J68: =SUMIFS('GL Data'!$L:$L,'GL Data'!$B:$B,$A68) -> 2006.58 | K68: =SUMIFS('GL Data'!$M:$M,'GL Data'!$B:$B,$A68) -> 1829.52 | L68: =SUMIFS('GL Data'!$N:$N,'GL Data'!$B:$B,$A68) -> 2056.43 | M68: =SUMIFS('GL Data'!$O:$O,'GL Data'!$B:$B,$A68) -> 2372.6 | N68: =SUMIFS('GL Data'!$P:$P,'GL Data'!$B:$B,$A68) -> 2474.8 | O68: =SUMIFS('GL Data'!$Q:$Q,'GL Data'!$B:$B,$A68) -> 1536.15 | P68: =SUMIFS('GL Data'!$R:$R,'GL Data'!$B:$B,$A68) -> 2923.12 | Q68: =SUMIFS('GL Data'!$S:$S,'GL Data'!$B:$B,$A68) -> 1991.18 | R68: =SUMIFS('GL Data'!$T:$T,'GL Data'!$B:$B,$A68) -> 2192.39 | S68: =SUMIFS('GL Data'!$U:$U,'GL Data'!$B:$B,$A68) -> 2815.59 | T68: =SUMIFS('GL Data'!$V:$V,'GL Data'!$B:$B,$A68) -> 2522.76 | U68: =SUMIFS('GL Data'!$W:$W,'GL Data'!$B:$B,$A68) -> 2423.45 | V68: =SUMIFS('GL Data'!$X:$X,'GL Data'!$B:$B,$A68) -> 2564.93 | W68: =SUMIFS('GL Data'!$Y:$Y,'GL Data'!$B:$B,$A68) -> 1955.47 | X68: =SUMIFS('GL Data'!$Z:$Z,'GL Data'!$B:$B,$A68) -> 2117.68 | Y68: =SUMIFS('GL Data'!$AA:$AA,'GL Data'!$B:$B,$A68) -> 2729.73 | Z68: =SUMIFS('GL Data'!$AB:$AB,'GL Data'!$B:$B,$A68) -> 2337.59 | AA68: =SUMIFS('GL Data'!$AC:$AC,'GL Data'!$B:$B,$A68) -> 1878.05
A69: Total Fees and Charges | C69: =SUM(C67:C68) -> 2492.15 | D69: =SUM(D67:D68) -> 2700.46 | E69: =SUM(E67:E68) -> 2576.75 | F69: =SUM(F67:F68) -> 2375.78 | G69: =SUM(G67:G68) -> 2608.01 | H69: =SUM(H67:H68) -> 2589.38 | I69: =SUM(I67:I68) -> 2393.05 | J69: =SUM(J67:J68) -> 2268.72 | ... AA69: =SUM(AA67:AA68) -> 1928.05
A71: Total Operating Expenses | C71: =C33+C45+C64+C69 -> 35014.28 | D71: =D33+D45+D64+D69 -> 38324.28 | E71: =E33+E45+E64+E69 -> 37834.35 | F71: =F33+F45+F64+F69 -> 38947.41 | G71: =G33+G45+G64+G69 -> 44407.6 | H71: =H33+H45+H64+H69 -> 39850.29 | I71: =I33+I45+I64+I69 -> 68867.12 | J71: =J33+J45+J64+J69 -> 38460.28 | ... AA71: =AA33+AA45+AA64+AA69 -> 33694.83
A72: Operating Income (EBIT) | C72: =C23-C71 -> 1862.72 | D72: =D23-D71 -> 14730.61 | E72: =E23-E71 -> 5394.2 | F72: =F23-F71 -> 5117.37 | G72: =G23-G71 -> 3179.2 | H72: =H23-H71 -> 2867.69 | I72: =I23-I71 -> -24398.48 | J72: =J23-J71 -> 1079.46 | ... AA72: =AA23-AA71 -> 3709.61
A73: Operating Margin % | C73: =IFERROR(C72/C15,0) -> 0.028429992 | D73: =IFERROR(D72/D15,0) -> 0.1875138 | E73: =IFERROR(E72/E15,0) -> 0.07767597 | F73: =IFERROR(F72/F15,0) -> 0.073715736 | G73: =IFERROR(G72/G15,0) -> 0.042615102 | H73: =IFERROR(H72/H15,0) -> 0.041229348 | I73: =IFERROR(I72/I15,0) -> -0.35721289 | J73: =IFERROR(J72/J15,0) -> 0.016458841 | ... AA73: =IFERROR(AA72/AA15,0) -> 0.057847666
A75: Other Income / (Expense)
A76: Interest Earned | C76: =-SUMIFS('GL Data'!$E:$E,'GL Data'!$B:$B,$A76) -> 0.12 | D76: =-SUMIFS('GL Data'!$F:$F,'GL Data'!$B:$B,$A76) -> 0.12 | E76: =-SUMIFS('GL Data'!$G:$G,'GL Data'!$B:$B,$A76) -> 0.12 | F76: =-SUMIFS('GL Data'!$H:$H,'GL Data'!$B:$B,$A76) -> 0.12 | G76: =-SUMIFS('GL Data'!$I:$I,'GL Data'!$B:$B,$A76) -> 12.54 | H76: =-SUMIFS('GL Data'!$J:$J,'GL Data'!$B:$B,$A76) -> 43.97 | I76: =-SUMIFS('GL Data'!$K:$K,'GL Data'!$B:$B,$A76) -> 33.61 | J76: =-SUMIFS('GL Data'!$L:$L,'GL Data'!$B:$B,$A76) -> 25.37 | K76: =-SUMIFS('GL Data'!$M:$M,'GL Data'!$B:$B,$A76) -> 24.25 | L76: =-SUMIFS('GL Data'!$N:$N,'GL Data'!$B:$B,$A76) -> 31.69 | M76: =-SUMIFS('GL Data'!$O:$O,'GL Data'!$B:$B,$A76) -> 33.56 | N76: =-SUMIFS('GL Data'!$P:$P,'GL Data'!$B:$B,$A76) -> 45.92 | O76: =-SUMIFS('GL Data'!$Q:$Q,'GL Data'!$B:$B,$A76) -> 51.11 | P76: =-SUMIFS('GL Data'!$R:$R,'GL Data'!$B:$B,$A76) -> 55.77 | Q76: =-SUMIFS('GL Data'!$S:$S,'GL Data'!$B:$B,$A76) -> 56.27 | R76: =-SUMIFS('GL Data'!$T:$T,'GL Data'!$B:$B,$A76) -> 62.91 | S76: =-SUMIFS('GL Data'!$U:$U,'GL Data'!$B:$B,$A76) -> 83.06 | T76: =-SUMIFS('GL Data'!$V:$V,'GL Data'!$B:$B,$A76) -> 86.23 | U76: =-SUMIFS('GL Data'!$W:$W,'GL Data'!$B:$B,$A76) -> 80.73 | V76: =-SUMIFS('GL Data'!$X:$X,'GL Data'!$B:$B,$A76) -> 83.65 | W76: =-SUMIFS('GL Data'!$Y:$Y,'GL Data'!$B:$B,$A76) -> 82.45 | X76: =-SUMIFS('GL Data'!$Z:$Z,'GL Data'!$B:$B,$A76) -> 85.91 | Y76: =-SUMIFS('GL Data'!$AA:$AA,'GL Data'!$B:$B,$A76) -> 85.59 | Z76: =-SUMIFS('GL Data'!$AB:$AB,'GL Data'!$B:$B,$A76) -> 101.83 | AA76: =-SUMIFS('GL Data'!$AC:$AC,'GL Data'!$B:$B,$A76) -> 104.7
A77: Credit Card Rewards | C77: =-SUMIFS('GL Data'!$E:$E,'GL Data'!$B:$B,$A77) -> 23.47 | D77: =-SUMIFS('GL Data'!$F:$F,'GL Data'!$B:$B,$A77) -> 24.66 | E77: =-SUMIFS('GL Data'!$G:$G,'GL Data'!$B:$B,$A77) -> 39.71 | F77: =-SUMIFS('GL Data'!$H:$H,'GL Data'!$B:$B,$A77) -> 41.08 | G77: =-SUMIFS('GL Data'!$I:$I,'GL Data'!$B:$B,$A77) -> 34.78 | H77: =-SUMIFS('GL Data'!$J:$J,'GL Data'!$B:$B,$A77) -> 25.85 | I77: =-SUMIFS('GL Data'!$K:$K,'GL Data'!$B:$B,$A77) -> 36.47 | J77: =-SUMIFS('GL Data'!$L:$L,'GL Data'!$B:$B,$A77) -> 48.14 | K77: =-SUMIFS('GL Data'!$M:$M,'GL Data'!$B:$B,$A77) -> 36.84 | L77: =-SUMIFS('GL Data'!$N:$N,'GL Data'!$B:$B,$A77) -> 23.1 | M77: =-SUMIFS('GL Data'!$O:$O,'GL Data'!$B:$B,$A77) -> 25.27 | N77: =-SUMIFS('GL Data'!$P:$P,'GL Data'!$B:$B,$A77) -> 21.8 | O77: =-SUMIFS('GL Data'!$Q:$Q,'GL Data'!$B:$B,$A77) -> 20.88 | P77: =-SUMIFS('GL Data'!$R:$R,'GL Data'!$B:$B,$A77) -> 34.71 | Q77: =-SUMIFS('GL Data'!$S:$S,'GL Data'!$B:$B,$A77) -> 24.8 | R77: =-SUMIFS('GL Data'!$T:$T,'GL Data'!$B:$B,$A77) -> 20.02 | S77: =-SUMIFS('GL Data'!$U:$U,'GL Data'!$B:$B,$A77) -> 57.24 | T77: =-SUMIFS('GL Data'!$V:$V,'GL Data'!$B:$B,$A77) -> 75.19 | U77: =-SUMIFS('GL Data'!$W:$W,'GL Data'!$B:$B,$A77) -> 39.14 | V77: =-SUMIFS('GL Data'!$X:$X,'GL Data'!$B:$B,$A77) -> 30.22 | W77: =-SUMIFS('GL Data'!$Y:$Y,'GL Data'!$B:$B,$A77) -> 0 | X77: =-SUMIFS('GL Data'!$Z:$Z,'GL Data'!$B:$B,$A77) -> 101.61 | Y77: =-SUMIFS('GL Data'!$AA:$AA,'GL Data'!$B:$B,$A77) -> 16.1 | Z77: =-SUMIFS('GL Data'!$AB:$AB,'GL Data'!$B:$B,$A77) -> 21.59 | AA77: =-SUMIFS('GL Data'!$AC:$AC,'GL Data'!$B:$B,$A77) -> 21.89
A78: Interest Expense on Loan | C78: =-SUMIFS('GL Data'!$E:$E,'GL Data'!$B:$B,$A78) -> -386.68 | D78: =-SUMIFS('GL Data'!$F:$F,'GL Data'!$B:$B,$A78) -> -239.14 | E78: =-SUMIFS('GL Data'!$G:$G,'GL Data'!$B:$B,$A78) -> -164.06 | F78: =-SUMIFS('GL Data'!$H:$H,'GL Data'!$B:$B,$A78) -> 0 | G78: =-SUMIFS('GL Data'!$I:$I,'GL Data'!$B:$B,$A78) -> 0 | H78: =-SUMIFS('GL Data'!$J:$J,'GL Data'!$B:$B,$A78) -> 0 | I78: =-SUMIFS('GL Data'!$K:$K,'GL Data'!$B:$B,$A78) -> -1050 | J78: =-SUMIFS('GL Data'!$L:$L,'GL Data'!$B:$B,$A78) -> -350 | K78: =-SUMIFS('GL Data'!$M:$M,'GL Data'!$B:$B,$A78) -> 0 | L78: =-SUMIFS('GL Data'!$N:$N,'GL Data'!$B:$B,$A78) -> -700 | M78: =-SUMIFS('GL Data'!$O:$O,'GL Data'!$B:$B,$A78) -> -100 | N78: =-SUMIFS('GL Data'!$P:$P,'GL Data'!$B:$B,$A78) -> -100 | O78: =-SUMIFS('GL Data'!$Q:$Q,'GL Data'!$B:$B,$A78) -> -100 | P78: =-SUMIFS('GL Data'!$R:$R,'GL Data'!$B:$B,$A78) -> -100 | Q78: =-SUMIFS('GL Data'!$S:$S,'GL Data'!$B:$B,$A78) -> -100 | R78: =-SUMIFS('GL Data'!$T:$T,'GL Data'!$B:$B,$A78) -> -100 | S78: =-SUMIFS('GL Data'!$U:$U,'GL Data'!$B:$B,$A78) -> 0 | T78: =-SUMIFS('GL Data'!$V:$V,'GL Data'!$B:$B,$A78) -> 0 | U78: =-SUMIFS('GL Data'!$W:$W,'GL Data'!$B:$B,$A78) -> 0 | V78: =-SUMIFS('GL Data'!$X:$X,'GL Data'!$B:$B,$A78) -> 0 | W78: =-SUMIFS('GL Data'!$Y:$Y,'GL Data'!$B:$B,$A78) -> 0 | X78: =-SUMIFS('GL Data'!$Z:$Z,'GL Data'!$B:$B,$A78) -> 0 | Y78: =-SUMIFS('GL Data'!$AA:$AA,'GL Data'!$B:$B,$A78) -> 0 | Z78: =-SUMIFS('GL Data'!$AB:$AB,'GL Data'!$B:$B,$A78) -> 0 | AA78: =-SUMIFS('GL Data'!$AC:$AC,'GL Data'!$B:$B,$A78) -> 0
A79: Interest Expense on Line of Credit (modeled) | C79: =C258 -> 0 | D79: =D258 -> 0 | E79: =E258 -> 0 | F79: =F258 -> 0 | G79: =G258 -> 0 | H79: =H258 -> 0 | I79: =I258 -> 0 | J79: =J258 -> 0 | ... AA79: =AA258 -> 0
A80: Total Other Income / (Expense) | C80: =SUM(C76:C78)-C79 -> -363.09 | D80: =SUM(D76:D78)-D79 -> -214.36 | E80: =SUM(E76:E78)-E79 -> -124.23 | F80: =SUM(F76:F78)-F79 -> 41.2 | G80: =SUM(G76:G78)-G79 -> 47.32 | H80: =SUM(H76:H78)-H79 -> 69.82 | I80: =SUM(I76:I78)-I79 -> -979.92 | J80: =SUM(J76:J78)-J79 -> -276.49 | ... AA80: =SUM(AA76:AA78)-AA79 -> 126.59
A81: Net Income | C81: =C72+C80 -> 1499.63 | D81: =D72+D80 -> 14516.25 | E81: =E72+E80 -> 5269.97 | F81: =F72+F80 -> 5158.57 | G81: =G72+G80 -> 3226.52 | H81: =H72+H80 -> 2937.51 | I81: =I72+I80 -> -25378.4 | J81: =J72+J80 -> 802.97 | ... AA81: =AA72+AA80 -> 3836.2
A82: Net Margin % | C82: =IFERROR(C81/C15,0) -> 0.022888286 | D82: =IFERROR(D81/D15,0) -> 0.1847851 | E82: =IFERROR(E81/E15,0) -> 0.07588707 | F82: =IFERROR(F81/F15,0) -> 0.074309222 | G82: =IFERROR(G81/G15,0) -> 0.043249396 | H82: =IFERROR(H81/H15,0) -> 0.042233164 | I82: =IFERROR(I81/I15,0) -> -0.37155969 | J82: =IFERROR(J81/J15,0) -> 0.012243117 | ... AA82: =IFERROR(AA81/AA15,0) -> 0.059821711
A85: BALANCE SHEET
B86: TB 5/31/24 | C86: Jun-24 | D86: Jul-24 | E86: Aug-24 | F86: Sep-24 | G86: Oct-24 | H86: Nov-24 | I86: Dec-24 | J86: Jan-25 | K86: Feb-25 | L86: Mar-25 | M86: Apr-25 | N86: May-25 | O86: Jun-25 | P86: Jul-25 | Q86: Aug-25 | R86: Sep-25 | S86: Oct-25 | T86: Nov-25 | U86: Dec-25 | V86: Jan-26 | W86: Feb-26 | X86: Mar-26 | Y86: Apr-26 | Z86: May-26 | AA86: Jun-26
A87: Current Assets
A88: Smart VAs AMEX Checking | B88: =SUMIFS('GL Data'!$D:$D,'GL Data'!$B:$B,$A88) -> 114.5 | C88: =B88+SUMIFS('GL Data'!$E:$E,'GL Data'!$B:$B,$A88) -> 114.62 | D88: =C88+SUMIFS('GL Data'!$F:$F,'GL Data'!$B:$B,$A88) -> 114.74 | E88: =D88+SUMIFS('GL Data'!$G:$G,'GL Data'!$B:$B,$A88) -> 114.86 | F88: =E88+SUMIFS('GL Data'!$H:$H,'GL Data'!$B:$B,$A88) -> 114.98 | G88: =F88+SUMIFS('GL Data'!$I:$I,'GL Data'!$B:$B,$A88) -> 40137.01 | H88: =G88+SUMIFS('GL Data'!$J:$J,'GL Data'!$B:$B,$A88) -> 31791.94 | I88: =H88+SUMIFS('GL Data'!$K:$K,'GL Data'!$B:$B,$A88) -> 18681.29 | J88: =I88+SUMIFS('GL Data'!$L:$L,'GL Data'!$B:$B,$A88) -> 23435.92 | K88: =J88+SUMIFS('GL Data'!$M:$M,'GL Data'!$B:$B,$A88) -> 19360.72 | L88: =K88+SUMIFS('GL Data'!$N:$N,'GL Data'!$B:$B,$A88) -> 29554.67 | M88: =L88+SUMIFS('GL Data'!$O:$O,'GL Data'!$B:$B,$A88) -> 35451.09 | N88: =M88+SUMIFS('GL Data'!$P:$P,'GL Data'!$B:$B,$A88) -> 52681.4 | O88: =N88+SUMIFS('GL Data'!$Q:$Q,'GL Data'!$B:$B,$A88) -> 38830.07 | P88: =O88+SUMIFS('GL Data'!$R:$R,'GL Data'!$B:$B,$A88) -> 63924.19 | Q88: =P88+SUMIFS('GL Data'!$S:$S,'GL Data'!$B:$B,$A88) -> 44829.49 | R88: =Q88+SUMIFS('GL Data'!$T:$T,'GL Data'!$B:$B,$A88) -> 53999.5 | S88: =R88+SUMIFS('GL Data'!$U:$U,'GL Data'!$B:$B,$A88) -> 72739.61 | T88: =S88+SUMIFS('GL Data'!$V:$V,'GL Data'!$B:$B,$A88) -> 72588.9 | U88: =T88+SUMIFS('GL Data'!$W:$W,'GL Data'!$B:$B,$A88) -> 61335.8 | V88: =U88+SUMIFS('GL Data'!$X:$X,'GL Data'!$B:$B,$A88) -> 82533.33 | W88: =V88+SUMIFS('GL Data'!$Y:$Y,'GL Data'!$B:$B,$A88) -> 73427.05 | X88: =W88+SUMIFS('GL Data'!$Z:$Z,'GL Data'!$B:$B,$A88) -> 69359.56 | Y88: =X88+SUMIFS('GL Data'!$AA:$AA,'GL Data'!$B:$B,$A88) -> 87470.52 | Z88: =Y88+SUMIFS('GL Data'!$AB:$AB,'GL Data'!$B:$B,$A88) -> 92436.02 | AA88: =Z88+SUMIFS('GL Data'!$AC:$AC,'GL Data'!$B:$B,$A88) -> 87171.6
A89: SMARTVAS Checking | B89: =SUMIFS('GL Data'!$D:$D,'GL Data'!$B:$B,$A89) -> 28165.66 | C89: =B89+SUMIFS('GL Data'!$E:$E,'GL Data'!$B:$B,$A89) -> 23170.62 | D89: =C89+SUMIFS('GL Data'!$F:$F,'GL Data'!$B:$B,$A89) -> 21918.75 | E89: =D89+SUMIFS('GL Data'!$G:$G,'GL Data'!$B:$B,$A89) -> 22853.39 | F89: =E89+SUMIFS('GL Data'!$H:$H,'GL Data'!$B:$B,$A89) -> 19881.97 | G89: =F89+SUMIFS('GL Data'!$I:$I,'GL Data'!$B:$B,$A89) -> 182.96 | H89: =G89+SUMIFS('GL Data'!$J:$J,'GL Data'!$B:$B,$A89) -> 144.96 | I89: =H89+SUMIFS('GL Data'!$K:$K,'GL Data'!$B:$B,$A89) -> 2.7569058e-12 | J89: =I89+SUMIFS('GL Data'!$L:$L,'GL Data'!$B:$B,$A89) -> 2.7569058e-12 | K89: =J89+SUMIFS('GL Data'!$M:$M,'GL Data'!$B:$B,$A89) -> 2.7569058e-12 | L89: =K89+SUMIFS('GL Data'!$N:$N,'GL Data'!$B:$B,$A89) -> 2.7569058e-12 | M89: =L89+SUMIFS('GL Data'!$O:$O,'GL Data'!$B:$B,$A89) -> 2.7569058e-12 | N89: =M89+SUMIFS('GL Data'!$P:$P,'GL Data'!$B:$B,$A89) -> 2.7569058e-12 | O89: =N89+SUMIFS('GL Data'!$Q:$Q,'GL Data'!$B:$B,$A89) -> 2.7569058e-12 | P89: =O89+SUMIFS('GL Data'!$R:$R,'GL Data'!$B:$B,$A89) -> 2.7569058e-12 | Q89: =P89+SUMIFS('GL Data'!$S:$S,'GL Data'!$B:$B,$A89) -> 2.7569058e-12 | R89: =Q89+SUMIFS('GL Data'!$T:$T,'GL Data'!$B:$B,$A89) -> 2.7569058e-12 | S89: =R89+SUMIFS('GL Data'!$U:$U,'GL Data'!$B:$B,$A89) -> 2.7569058e-12 | T89: =S89+SUMIFS('GL Data'!$V:$V,'GL Data'!$B:$B,$A89) -> 2.7569058e-12 | U89: =T89+SUMIFS('GL Data'!$W:$W,'GL Data'!$B:$B,$A89) -> 2.7569058e-12 | V89: =U89+SUMIFS('GL Data'!$X:$X,'GL Data'!$B:$B,$A89) -> 2.7569058e-12 | W89: =V89+SUMIFS('GL Data'!$Y:$Y,'GL Data'!$B:$B,$A89) -> 2.7569058e-12 | X89: =W89+SUMIFS('GL Data'!$Z:$Z,'GL Data'!$B:$B,$A89) -> 2.7569058e-12 | Y89: =X89+SUMIFS('GL Data'!$AA:$AA,'GL Data'!$B:$B,$A89) -> 2.7569058e-12 | Z89: =Y89+SUMIFS('GL Data'!$AB:$AB,'GL Data'!$B:$B,$A89) -> 2.7569058e-12 | AA89: =Z89+SUMIFS('GL Data'!$AC:$AC,'GL Data'!$B:$B,$A89) -> 2.7569058e-12
A90: Unionbank | B90: =SUMIFS('GL Data'!$D:$D,'GL Data'!$B:$B,$A90) -> 79.67 | C90: =B90+SUMIFS('GL Data'!$E:$E,'GL Data'!$B:$B,$A90) -> 79.67 | D90: =C90+SUMIFS('GL Data'!$F:$F,'GL Data'!$B:$B,$A90) -> 79.67 | E90: =D90+SUMIFS('GL Data'!$G:$G,'GL Data'!$B:$B,$A90) -> 79.67 | F90: =E90+SUMIFS('GL Data'!$H:$H,'GL Data'!$B:$B,$A90) -> 79.67 | G90: =F90+SUMIFS('GL Data'!$I:$I,'GL Data'!$B:$B,$A90) -> 79.67 | H90: =G90+SUMIFS('GL Data'!$J:$J,'GL Data'!$B:$B,$A90) -> 79.67 | I90: =H90+SUMIFS('GL Data'!$K:$K,'GL Data'!$B:$B,$A90) -> 79.67 | J90: =I90+SUMIFS('GL Data'!$L:$L,'GL Data'!$B:$B,$A90) -> 79.67 | K90: =J90+SUMIFS('GL Data'!$M:$M,'GL Data'!$B:$B,$A90) -> 79.67 | L90: =K90+SUMIFS('GL Data'!$N:$N,'GL Data'!$B:$B,$A90) -> 0 | M90: =L90+SUMIFS('GL Data'!$O:$O,'GL Data'!$B:$B,$A90) -> 0 | N90: =M90+SUMIFS('GL Data'!$P:$P,'GL Data'!$B:$B,$A90) -> 0 | O90: =N90+SUMIFS('GL Data'!$Q:$Q,'GL Data'!$B:$B,$A90) -> 0 | P90: =O90+SUMIFS('GL Data'!$R:$R,'GL Data'!$B:$B,$A90) -> 0 | Q90: =P90+SUMIFS('GL Data'!$S:$S,'GL Data'!$B:$B,$A90) -> 0 | R90: =Q90+SUMIFS('GL Data'!$T:$T,'GL Data'!$B:$B,$A90) -> 0 | S90: =R90+SUMIFS('GL Data'!$U:$U,'GL Data'!$B:$B,$A90) -> 0 | T90: =S90+SUMIFS('GL Data'!$V:$V,'GL Data'!$B:$B,$A90) -> 0 | U90: =T90+SUMIFS('GL Data'!$W:$W,'GL Data'!$B:$B,$A90) -> 0 | V90: =U90+SUMIFS('GL Data'!$X:$X,'GL Data'!$B:$B,$A90) -> 0 | W90: =V90+SUMIFS('GL Data'!$Y:$Y,'GL Data'!$B:$B,$A90) -> 0 | X90: =W90+SUMIFS('GL Data'!$Z:$Z,'GL Data'!$B:$B,$A90) -> 0 | Y90: =X90+SUMIFS('GL Data'!$AA:$AA,'GL Data'!$B:$B,$A90) -> 0 | Z90: =Y90+SUMIFS('GL Data'!$AB:$AB,'GL Data'!$B:$B,$A90) -> 0 | AA90: =Z90+SUMIFS('GL Data'!$AC:$AC,'GL Data'!$B:$B,$A90) -> 0
A91: Wise Fund | B91: =SUMIFS('GL Data'!$D:$D,'GL Data'!$B:$B,$A91) -> 9.83 | C91: =B91+SUMIFS('GL Data'!$E:$E,'GL Data'!$B:$B,$A91) -> 6.2 | D91: =C91+SUMIFS('GL Data'!$F:$F,'GL Data'!$B:$B,$A91) -> 6.2 | E91: =D91+SUMIFS('GL Data'!$G:$G,'GL Data'!$B:$B,$A91) -> 2.55 | F91: =E91+SUMIFS('GL Data'!$H:$H,'GL Data'!$B:$B,$A91) -> 2.55 | G91: =F91+SUMIFS('GL Data'!$I:$I,'GL Data'!$B:$B,$A91) -> 2.55 | H91: =G91+SUMIFS('GL Data'!$J:$J,'GL Data'!$B:$B,$A91) -> 2.55 | I91: =H91+SUMIFS('GL Data'!$K:$K,'GL Data'!$B:$B,$A91) -> 2.55 | J91: =I91+SUMIFS('GL Data'!$L:$L,'GL Data'!$B:$B,$A91) -> 2.55 | K91: =J91+SUMIFS('GL Data'!$M:$M,'GL Data'!$B:$B,$A91) -> 2.55 | L91: =K91+SUMIFS('GL Data'!$N:$N,'GL Data'!$B:$B,$A91) -> 2.55 | M91: =L91+SUMIFS('GL Data'!$O:$O,'GL Data'!$B:$B,$A91) -> 2.55 | N91: =M91+SUMIFS('GL Data'!$P:$P,'GL Data'!$B:$B,$A91) -> 2.55 | O91: =N91+SUMIFS('GL Data'!$Q:$Q,'GL Data'!$B:$B,$A91) -> 2.55 | P91: =O91+SUMIFS('GL Data'!$R:$R,'GL Data'!$B:$B,$A91) -> 2.55 | Q91: =P91+SUMIFS('GL Data'!$S:$S,'GL Data'!$B:$B,$A91) -> 2.55 | R91: =Q91+SUMIFS('GL Data'!$T:$T,'GL Data'!$B:$B,$A91) -> 2.55 | S91: =R91+SUMIFS('GL Data'!$U:$U,'GL Data'!$B:$B,$A91) -> 2.55 | T91: =S91+SUMIFS('GL Data'!$V:$V,'GL Data'!$B:$B,$A91) -> 2.55 | U91: =T91+SUMIFS('GL Data'!$W:$W,'GL Data'!$B:$B,$A91) -> 2.55 | V91: =U91+SUMIFS('GL Data'!$X:$X,'GL Data'!$B:$B,$A91) -> 2.55 | W91: =V91+SUMIFS('GL Data'!$Y:$Y,'GL Data'!$B:$B,$A91) -> 2.55 | X91: =W91+SUMIFS('GL Data'!$Z:$Z,'GL Data'!$B:$B,$A91) -> 2.55 | Y91: =X91+SUMIFS('GL Data'!$AA:$AA,'GL Data'!$B:$B,$A91) -> 2.55 | Z91: =Y91+SUMIFS('GL Data'!$AB:$AB,'GL Data'!$B:$B,$A91) -> 2.55 | AA91: =Z91+SUMIFS('GL Data'!$AC:$AC,'GL Data'!$B:$B,$A91) -> 2.55
A92: Accounts Receivable | B92: =SUMIFS('GL Data'!$D:$D,'GL Data'!$B:$B,$A92) -> 532.65 | C92: =B92+SUMIFS('GL Data'!$E:$E,'GL Data'!$B:$B,$A92) -> 532.65 | D92: =C92+SUMIFS('GL Data'!$F:$F,'GL Data'!$B:$B,$A92) -> 532.65 | E92: =D92+SUMIFS('GL Data'!$G:$G,'GL Data'!$B:$B,$A92) -> 1248.11 | F92: =E92+SUMIFS('GL Data'!$H:$H,'GL Data'!$B:$B,$A92) -> 2149.25 | G92: =F92+SUMIFS('GL Data'!$I:$I,'GL Data'!$B:$B,$A92) -> 3016.93 | H92: =G92+SUMIFS('GL Data'!$J:$J,'GL Data'!$B:$B,$A92) -> 3872.33 | I92: =H92+SUMIFS('GL Data'!$K:$K,'GL Data'!$B:$B,$A92) -> 656.25 | J92: =I92+SUMIFS('GL Data'!$L:$L,'GL Data'!$B:$B,$A92) -> 1686.67 | K92: =J92+SUMIFS('GL Data'!$M:$M,'GL Data'!$B:$B,$A92) -> 3674.81 | L92: =K92+SUMIFS('GL Data'!$N:$N,'GL Data'!$B:$B,$A92) -> 1542.54 | M92: =L92+SUMIFS('GL Data'!$O:$O,'GL Data'!$B:$B,$A92) -> 656.25 | N92: =M92+SUMIFS('GL Data'!$P:$P,'GL Data'!$B:$B,$A92) -> 656.25 | O92: =N92+SUMIFS('GL Data'!$Q:$Q,'GL Data'!$B:$B,$A92) -> 656.25 | P92: =O92+SUMIFS('GL Data'!$R:$R,'GL Data'!$B:$B,$A92) -> 2271.07 | Q92: =P92+SUMIFS('GL Data'!$S:$S,'GL Data'!$B:$B,$A92) -> 2555.47 | R92: =Q92+SUMIFS('GL Data'!$T:$T,'GL Data'!$B:$B,$A92) -> 2271.07 | S92: =R92+SUMIFS('GL Data'!$U:$U,'GL Data'!$B:$B,$A92) -> 2271.07 | T92: =S92+SUMIFS('GL Data'!$V:$V,'GL Data'!$B:$B,$A92) -> -6578.79 | U92: =T92+SUMIFS('GL Data'!$W:$W,'GL Data'!$B:$B,$A92) -> -2768.95 | V92: =U92+SUMIFS('GL Data'!$X:$X,'GL Data'!$B:$B,$A92) -> 656.25 | W92: =V92+SUMIFS('GL Data'!$Y:$Y,'GL Data'!$B:$B,$A92) -> 656.25 | X92: =W92+SUMIFS('GL Data'!$Z:$Z,'GL Data'!$B:$B,$A92) -> 656.25 | Y92: =X92+SUMIFS('GL Data'!$AA:$AA,'GL Data'!$B:$B,$A92) -> 656.25 | Z92: =Y92+SUMIFS('GL Data'!$AB:$AB,'GL Data'!$B:$B,$A92) -> 656.25 | AA92: =Z92+SUMIFS('GL Data'!$AC:$AC,'GL Data'!$B:$B,$A92) -> 656.25
A93: Other Receivables | B93: =SUMIFS('GL Data'!$D:$D,'GL Data'!$B:$B,$A93) -> 0 | C93: =B93+SUMIFS('GL Data'!$E:$E,'GL Data'!$B:$B,$A93) -> 0 | D93: =C93+SUMIFS('GL Data'!$F:$F,'GL Data'!$B:$B,$A93) -> 3917.33 | E93: =D93+SUMIFS('GL Data'!$G:$G,'GL Data'!$B:$B,$A93) -> 0 | F93: =E93+SUMIFS('GL Data'!$H:$H,'GL Data'!$B:$B,$A93) -> 0 | G93: =F93+SUMIFS('GL Data'!$I:$I,'GL Data'!$B:$B,$A93) -> 0 | H93: =G93+SUMIFS('GL Data'!$J:$J,'GL Data'!$B:$B,$A93) -> 987.55 | I93: =H93+SUMIFS('GL Data'!$K:$K,'GL Data'!$B:$B,$A93) -> 0 | J93: =I93+SUMIFS('GL Data'!$L:$L,'GL Data'!$B:$B,$A93) -> 0 | K93: =J93+SUMIFS('GL Data'!$M:$M,'GL Data'!$B:$B,$A93) -> 0 | L93: =K93+SUMIFS('GL Data'!$N:$N,'GL Data'!$B:$B,$A93) -> 0 | M93: =L93+SUMIFS('GL Data'!$O:$O,'GL Data'!$B:$B,$A93) -> 0 | N93: =M93+SUMIFS('GL Data'!$P:$P,'GL Data'!$B:$B,$A93) -> 0 | O93: =N93+SUMIFS('GL Data'!$Q:$Q,'GL Data'!$B:$B,$A93) -> 0 | P93: =O93+SUMIFS('GL Data'!$R:$R,'GL Data'!$B:$B,$A93) -> 0 | Q93: =P93+SUMIFS('GL Data'!$S:$S,'GL Data'!$B:$B,$A93) -> 0 | R93: =Q93+SUMIFS('GL Data'!$T:$T,'GL Data'!$B:$B,$A93) -> 0 | S93: =R93+SUMIFS('GL Data'!$U:$U,'GL Data'!$B:$B,$A93) -> 0 | T93: =S93+SUMIFS('GL Data'!$V:$V,'GL Data'!$B:$B,$A93) -> 0 | U93: =T93+SUMIFS('GL Data'!$W:$W,'GL Data'!$B:$B,$A93) -> 0 | V93: =U93+SUMIFS('GL Data'!$X:$X,'GL Data'!$B:$B,$A93) -> 0 | W93: =V93+SUMIFS('GL Data'!$Y:$Y,'GL Data'!$B:$B,$A93) -> 0 | X93: =W93+SUMIFS('GL Data'!$Z:$Z,'GL Data'!$B:$B,$A93) -> 0 | Y93: =X93+SUMIFS('GL Data'!$AA:$AA,'GL Data'!$B:$B,$A93) -> 0 | Z93: =Y93+SUMIFS('GL Data'!$AB:$AB,'GL Data'!$B:$B,$A93) -> 0 | AA93: =Z93+SUMIFS('GL Data'!$AC:$AC,'GL Data'!$B:$B,$A93) -> 0
A94: Advances subject to Liquidation | B94: =SUMIFS('GL Data'!$D:$D,'GL Data'!$B:$B,$A94) -> 302.46 | C94: =B94+SUMIFS('GL Data'!$E:$E,'GL Data'!$B:$B,$A94) -> 347.01 | D94: =C94+SUMIFS('GL Data'!$F:$F,'GL Data'!$B:$B,$A94) -> 445.11 | E94: =D94+SUMIFS('GL Data'!$G:$G,'GL Data'!$B:$B,$A94) -> 471.25 | F94: =E94+SUMIFS('GL Data'!$H:$H,'GL Data'!$B:$B,$A94) -> 247.49 | G94: =F94+SUMIFS('GL Data'!$I:$I,'GL Data'!$B:$B,$A94) -> 231.33 | H94: =G94+SUMIFS('GL Data'!$J:$J,'GL Data'!$B:$B,$A94) -> 269.79 | I94: =H94+SUMIFS('GL Data'!$K:$K,'GL Data'!$B:$B,$A94) -> 603.76 | J94: =I94+SUMIFS('GL Data'!$L:$L,'GL Data'!$B:$B,$A94) -> 336.91 | K94: =J94+SUMIFS('GL Data'!$M:$M,'GL Data'!$B:$B,$A94) -> 160.79 | L94: =K94+SUMIFS('GL Data'!$N:$N,'GL Data'!$B:$B,$A94) -> -104.95 | M94: =L94+SUMIFS('GL Data'!$O:$O,'GL Data'!$B:$B,$A94) -> 140.66 | N94: =M94+SUMIFS('GL Data'!$P:$P,'GL Data'!$B:$B,$A94) -> 117.82 | O94: =N94+SUMIFS('GL Data'!$Q:$Q,'GL Data'!$B:$B,$A94) -> 117.82 | P94: =O94+SUMIFS('GL Data'!$R:$R,'GL Data'!$B:$B,$A94) -> 117.82 | Q94: =P94+SUMIFS('GL Data'!$S:$S,'GL Data'!$B:$B,$A94) -> 41.21 | R94: =Q94+SUMIFS('GL Data'!$T:$T,'GL Data'!$B:$B,$A94) -> 0 | S94: =R94+SUMIFS('GL Data'!$U:$U,'GL Data'!$B:$B,$A94) -> 0 | T94: =S94+SUMIFS('GL Data'!$V:$V,'GL Data'!$B:$B,$A94) -> 0 | U94: =T94+SUMIFS('GL Data'!$W:$W,'GL Data'!$B:$B,$A94) -> 0 | V94: =U94+SUMIFS('GL Data'!$X:$X,'GL Data'!$B:$B,$A94) -> 0 | W94: =V94+SUMIFS('GL Data'!$Y:$Y,'GL Data'!$B:$B,$A94) -> 0 | X94: =W94+SUMIFS('GL Data'!$Z:$Z,'GL Data'!$B:$B,$A94) -> 0 | Y94: =X94+SUMIFS('GL Data'!$AA:$AA,'GL Data'!$B:$B,$A94) -> 0 | Z94: =Y94+SUMIFS('GL Data'!$AB:$AB,'GL Data'!$B:$B,$A94) -> 0 | AA94: =Z94+SUMIFS('GL Data'!$AC:$AC,'GL Data'!$B:$B,$A94) -> 0
A95: Advances to Contractors | B95: =SUMIFS('GL Data'!$D:$D,'GL Data'!$B:$B,$A95) -> 414.91 | C95: =B95+SUMIFS('GL Data'!$E:$E,'GL Data'!$B:$B,$A95) -> 191.41 | D95: =C95+SUMIFS('GL Data'!$F:$F,'GL Data'!$B:$B,$A95) -> 871.87 | E95: =D95+SUMIFS('GL Data'!$G:$G,'GL Data'!$B:$B,$A95) -> 782.62 | F95: =E95+SUMIFS('GL Data'!$H:$H,'GL Data'!$B:$B,$A95) -> 1623.27 | G95: =F95+SUMIFS('GL Data'!$I:$I,'GL Data'!$B:$B,$A95) -> 1107.41 | H95: =G95+SUMIFS('GL Data'!$J:$J,'GL Data'!$B:$B,$A95) -> 1925.67 | I95: =H95+SUMIFS('GL Data'!$K:$K,'GL Data'!$B:$B,$A95) -> 1483.64 | J95: =I95+SUMIFS('GL Data'!$L:$L,'GL Data'!$B:$B,$A95) -> 1282.65 | K95: =J95+SUMIFS('GL Data'!$M:$M,'GL Data'!$B:$B,$A95) -> 1104.98 | L95: =K95+SUMIFS('GL Data'!$N:$N,'GL Data'!$B:$B,$A95) -> 1105.53 | M95: =L95+SUMIFS('GL Data'!$O:$O,'GL Data'!$B:$B,$A95) -> 1220.81 | N95: =M95+SUMIFS('GL Data'!$P:$P,'GL Data'!$B:$B,$A95) -> 1338.8 | O95: =N95+SUMIFS('GL Data'!$Q:$Q,'GL Data'!$B:$B,$A95) -> 1105.78 | P95: =O95+SUMIFS('GL Data'!$R:$R,'GL Data'!$B:$B,$A95) -> 1300.46 | Q95: =P95+SUMIFS('GL Data'!$S:$S,'GL Data'!$B:$B,$A95) -> 1790.98 | R95: =Q95+SUMIFS('GL Data'!$T:$T,'GL Data'!$B:$B,$A95) -> 1385.54 | S95: =R95+SUMIFS('GL Data'!$U:$U,'GL Data'!$B:$B,$A95) -> 1221.37 | T95: =S95+SUMIFS('GL Data'!$V:$V,'GL Data'!$B:$B,$A95) -> 1422.85 | U95: =T95+SUMIFS('GL Data'!$W:$W,'GL Data'!$B:$B,$A95) -> 1465.15 | V95: =U95+SUMIFS('GL Data'!$X:$X,'GL Data'!$B:$B,$A95) -> 1399.55 | W95: =V95+SUMIFS('GL Data'!$Y:$Y,'GL Data'!$B:$B,$A95) -> 674.19 | X95: =W95+SUMIFS('GL Data'!$Z:$Z,'GL Data'!$B:$B,$A95) -> 377.76 | Y95: =X95+SUMIFS('GL Data'!$AA:$AA,'GL Data'!$B:$B,$A95) -> 188.37 | Z95: =Y95+SUMIFS('GL Data'!$AB:$AB,'GL Data'!$B:$B,$A95) -> 105.65 | AA95: =Z95+SUMIFS('GL Data'!$AC:$AC,'GL Data'!$B:$B,$A95) -> -2.8421709e-13
A96: Prepaid Expenses | B96: =SUMIFS('GL Data'!$D:$D,'GL Data'!$B:$B,$A96) -> 331.33 | C96: =B96+SUMIFS('GL Data'!$E:$E,'GL Data'!$B:$B,$A96) -> 331.33 | D96: =C96+SUMIFS('GL Data'!$F:$F,'GL Data'!$B:$B,$A96) -> 331.33 | E96: =D96+SUMIFS('GL Data'!$G:$G,'GL Data'!$B:$B,$A96) -> 331.33 | F96: =E96+SUMIFS('GL Data'!$H:$H,'GL Data'!$B:$B,$A96) -> 331.33 | G96: =F96+SUMIFS('GL Data'!$I:$I,'GL Data'!$B:$B,$A96) -> 331.33 | H96: =G96+SUMIFS('GL Data'!$J:$J,'GL Data'!$B:$B,$A96) -> 331.33 | I96: =H96+SUMIFS('GL Data'!$K:$K,'GL Data'!$B:$B,$A96) -> 331.33 | J96: =I96+SUMIFS('GL Data'!$L:$L,'GL Data'!$B:$B,$A96) -> 331.33 | K96: =J96+SUMIFS('GL Data'!$M:$M,'GL Data'!$B:$B,$A96) -> 0 | L96: =K96+SUMIFS('GL Data'!$N:$N,'GL Data'!$B:$B,$A96) -> 0 | M96: =L96+SUMIFS('GL Data'!$O:$O,'GL Data'!$B:$B,$A96) -> 0 | N96: =M96+SUMIFS('GL Data'!$P:$P,'GL Data'!$B:$B,$A96) -> 0 | O96: =N96+SUMIFS('GL Data'!$Q:$Q,'GL Data'!$B:$B,$A96) -> 0 | P96: =O96+SUMIFS('GL Data'!$R:$R,'GL Data'!$B:$B,$A96) -> 0 | Q96: =P96+SUMIFS('GL Data'!$S:$S,'GL Data'!$B:$B,$A96) -> 0 | R96: =Q96+SUMIFS('GL Data'!$T:$T,'GL Data'!$B:$B,$A96) -> 0 | S96: =R96+SUMIFS('GL Data'!$U:$U,'GL Data'!$B:$B,$A96) -> 0 | T96: =S96+SUMIFS('GL Data'!$V:$V,'GL Data'!$B:$B,$A96) -> 0 | U96: =T96+SUMIFS('GL Data'!$W:$W,'GL Data'!$B:$B,$A96) -> 0 | V96: =U96+SUMIFS('GL Data'!$X:$X,'GL Data'!$B:$B,$A96) -> 0 | W96: =V96+SUMIFS('GL Data'!$Y:$Y,'GL Data'!$B:$B,$A96) -> 0 | X96: =W96+SUMIFS('GL Data'!$Z:$Z,'GL Data'!$B:$B,$A96) -> 0 | Y96: =X96+SUMIFS('GL Data'!$AA:$AA,'GL Data'!$B:$B,$A96) -> 0 | Z96: =Y96+SUMIFS('GL Data'!$AB:$AB,'GL Data'!$B:$B,$A96) -> 0 | AA96: =Z96+SUMIFS('GL Data'!$AC:$AC,'GL Data'!$B:$B,$A96) -> 0
A97: Due from Meet 5-Star Pros | B97: =SUMIFS('GL Data'!$D:$D,'GL Data'!$B:$B,$A97) -> 0 | C97: =B97+SUMIFS('GL Data'!$E:$E,'GL Data'!$B:$B,$A97) -> 0 | D97: =C97+SUMIFS('GL Data'!$F:$F,'GL Data'!$B:$B,$A97) -> 0 | E97: =D97+SUMIFS('GL Data'!$G:$G,'GL Data'!$B:$B,$A97) -> 0 | F97: =E97+SUMIFS('GL Data'!$H:$H,'GL Data'!$B:$B,$A97) -> 0 | G97: =F97+SUMIFS('GL Data'!$I:$I,'GL Data'!$B:$B,$A97) -> 0 | H97: =G97+SUMIFS('GL Data'!$J:$J,'GL Data'!$B:$B,$A97) -> 0 | I97: =H97+SUMIFS('GL Data'!$K:$K,'GL Data'!$B:$B,$A97) -> 0 | J97: =I97+SUMIFS('GL Data'!$L:$L,'GL Data'!$B:$B,$A97) -> 0 | K97: =J97+SUMIFS('GL Data'!$M:$M,'GL Data'!$B:$B,$A97) -> 0 | L97: =K97+SUMIFS('GL Data'!$N:$N,'GL Data'!$B:$B,$A97) -> 0 | M97: =L97+SUMIFS('GL Data'!$O:$O,'GL Data'!$B:$B,$A97) -> 0 | N97: =M97+SUMIFS('GL Data'!$P:$P,'GL Data'!$B:$B,$A97) -> 0 | O97: =N97+SUMIFS('GL Data'!$Q:$Q,'GL Data'!$B:$B,$A97) -> 0 | P97: =O97+SUMIFS('GL Data'!$R:$R,'GL Data'!$B:$B,$A97) -> 0 | Q97: =P97+SUMIFS('GL Data'!$S:$S,'GL Data'!$B:$B,$A97) -> 0 | R97: =Q97+SUMIFS('GL Data'!$T:$T,'GL Data'!$B:$B,$A97) -> 0 | S97: =R97+SUMIFS('GL Data'!$U:$U,'GL Data'!$B:$B,$A97) -> 0 | T97: =S97+SUMIFS('GL Data'!$V:$V,'GL Data'!$B:$B,$A97) -> 5109.09 | U97: =T97+SUMIFS('GL Data'!$W:$W,'GL Data'!$B:$B,$A97) -> 1712.6 | V97: =U97+SUMIFS('GL Data'!$X:$X,'GL Data'!$B:$B,$A97) -> 0 | W97: =V97+SUMIFS('GL Data'!$Y:$Y,'GL Data'!$B:$B,$A97) -> 0 | X97: =W97+SUMIFS('GL Data'!$Z:$Z,'GL Data'!$B:$B,$A97) -> 0 | Y97: =X97+SUMIFS('GL Data'!$AA:$AA,'GL Data'!$B:$B,$A97) -> 0 | Z97: =Y97+SUMIFS('GL Data'!$AB:$AB,'GL Data'!$B:$B,$A97) -> 0 | AA97: =Z97+SUMIFS('GL Data'!$AC:$AC,'GL Data'!$B:$B,$A97) -> 0
A98: Due from Meet 5-star VAs | B98: =SUMIFS('GL Data'!$D:$D,'GL Data'!$B:$B,$A98) -> 0 | C98: =B98+SUMIFS('GL Data'!$E:$E,'GL Data'!$B:$B,$A98) -> 263.97 | D98: =C98+SUMIFS('GL Data'!$F:$F,'GL Data'!$B:$B,$A98) -> -4.38 | E98: =D98+SUMIFS('GL Data'!$G:$G,'GL Data'!$B:$B,$A98) -> 39.59 | F98: =E98+SUMIFS('GL Data'!$H:$H,'GL Data'!$B:$B,$A98) -> 363.15 | G98: =F98+SUMIFS('GL Data'!$I:$I,'GL Data'!$B:$B,$A98) -> 1011.87 | H98: =G98+SUMIFS('GL Data'!$J:$J,'GL Data'!$B:$B,$A98) -> 1037.18 | I98: =H98+SUMIFS('GL Data'!$K:$K,'GL Data'!$B:$B,$A98) -> 1520.08 | J98: =I98+SUMIFS('GL Data'!$L:$L,'GL Data'!$B:$B,$A98) -> -532.65 | K98: =J98+SUMIFS('GL Data'!$M:$M,'GL Data'!$B:$B,$A98) -> -532.65 | L98: =K98+SUMIFS('GL Data'!$N:$N,'GL Data'!$B:$B,$A98) -> -88.34 | M98: =L98+SUMIFS('GL Data'!$O:$O,'GL Data'!$B:$B,$A98) -> -532.65 | N98: =M98+SUMIFS('GL Data'!$P:$P,'GL Data'!$B:$B,$A98) -> -57.25 | O98: =N98+SUMIFS('GL Data'!$Q:$Q,'GL Data'!$B:$B,$A98) -> 672.95 | P98: =O98+SUMIFS('GL Data'!$R:$R,'GL Data'!$B:$B,$A98) -> -532.65 | Q98: =P98+SUMIFS('GL Data'!$S:$S,'GL Data'!$B:$B,$A98) -> -532.65 | R98: =Q98+SUMIFS('GL Data'!$T:$T,'GL Data'!$B:$B,$A98) -> -532.65 | S98: =R98+SUMIFS('GL Data'!$U:$U,'GL Data'!$B:$B,$A98) -> -532.65 | T98: =S98+SUMIFS('GL Data'!$V:$V,'GL Data'!$B:$B,$A98) -> -532.65 | U98: =T98+SUMIFS('GL Data'!$W:$W,'GL Data'!$B:$B,$A98) -> -532.65 | V98: =U98+SUMIFS('GL Data'!$X:$X,'GL Data'!$B:$B,$A98) -> -532.65 | W98: =V98+SUMIFS('GL Data'!$Y:$Y,'GL Data'!$B:$B,$A98) -> -532.65 | X98: =W98+SUMIFS('GL Data'!$Z:$Z,'GL Data'!$B:$B,$A98) -> -532.65 | Y98: =X98+SUMIFS('GL Data'!$AA:$AA,'GL Data'!$B:$B,$A98) -> -532.65 | Z98: =Y98+SUMIFS('GL Data'!$AB:$AB,'GL Data'!$B:$B,$A98) -> -532.65 | AA98: =Z98+SUMIFS('GL Data'!$AC:$AC,'GL Data'!$B:$B,$A98) -> -532.65
A99: Cash — modeled Line of Credit funding | B99: 0 | C99: =C120 -> 0 | D99: =D120 -> 0 | E99: =E120 -> 0 | F99: =F120 -> 0 | G99: =G120 -> 0 | H99: =H120 -> 0 | I99: =I120 -> 0 | J99: =J120 -> 0 | ... AA99: =AA120 -> 0
A100: Total Current Assets | B100: =SUM(B88:B99) -> 29951.01 | C100: =SUM(C88:C99) -> 25037.48 | D100: =SUM(D88:D99) -> 28213.27 | E100: =SUM(E88:E99) -> 25923.37 | F100: =SUM(F88:F99) -> 24793.66 | G100: =SUM(G88:G99) -> 46101.06 | H100: =SUM(H88:H99) -> 40442.97 | I100: =SUM(I88:I99) -> 23358.57 | ... AA100: =SUM(AA88:AA99) -> 87297.75
A102: Non-Current Assets
A103: Office Equipment | B103: =SUMIFS('GL Data'!$D:$D,'GL Data'!$B:$B,$A103) -> 8982.85 | C103: =B103+SUMIFS('GL Data'!$E:$E,'GL Data'!$B:$B,$A103) -> 8982.85 | D103: =C103+SUMIFS('GL Data'!$F:$F,'GL Data'!$B:$B,$A103) -> 8982.85 | E103: =D103+SUMIFS('GL Data'!$G:$G,'GL Data'!$B:$B,$A103) -> 8982.85 | F103: =E103+SUMIFS('GL Data'!$H:$H,'GL Data'!$B:$B,$A103) -> 8982.85 | G103: =F103+SUMIFS('GL Data'!$I:$I,'GL Data'!$B:$B,$A103) -> 8982.85 | H103: =G103+SUMIFS('GL Data'!$J:$J,'GL Data'!$B:$B,$A103) -> 8982.85 | I103: =H103+SUMIFS('GL Data'!$K:$K,'GL Data'!$B:$B,$A103) -> 8982.85 | J103: =I103+SUMIFS('GL Data'!$L:$L,'GL Data'!$B:$B,$A103) -> 8982.85 | K103: =J103+SUMIFS('GL Data'!$M:$M,'GL Data'!$B:$B,$A103) -> 8982.85 | L103: =K103+SUMIFS('GL Data'!$N:$N,'GL Data'!$B:$B,$A103) -> 8982.85 | M103: =L103+SUMIFS('GL Data'!$O:$O,'GL Data'!$B:$B,$A103) -> 8982.85 | N103: =M103+SUMIFS('GL Data'!$P:$P,'GL Data'!$B:$B,$A103) -> 8982.85 | O103: =N103+SUMIFS('GL Data'!$Q:$Q,'GL Data'!$B:$B,$A103) -> 8982.85 | P103: =O103+SUMIFS('GL Data'!$R:$R,'GL Data'!$B:$B,$A103) -> 8982.85 | Q103: =P103+SUMIFS('GL Data'!$S:$S,'GL Data'!$B:$B,$A103) -> 8982.85 | R103: =Q103+SUMIFS('GL Data'!$T:$T,'GL Data'!$B:$B,$A103) -> 8982.85 | S103: =R103+SUMIFS('GL Data'!$U:$U,'GL Data'!$B:$B,$A103) -> 8982.85 | T103: =S103+SUMIFS('GL Data'!$V:$V,'GL Data'!$B:$B,$A103) -> 8982.85 | U103: =T103+SUMIFS('GL Data'!$W:$W,'GL Data'!$B:$B,$A103) -> 8982.85 | V103: =U103+SUMIFS('GL Data'!$X:$X,'GL Data'!$B:$B,$A103) -> 8982.85 | W103: =V103+SUMIFS('GL Data'!$Y:$Y,'GL Data'!$B:$B,$A103) -> 8982.85 | X103: =W103+SUMIFS('GL Data'!$Z:$Z,'GL Data'!$B:$B,$A103) -> 8982.85 | Y103: =X103+SUMIFS('GL Data'!$AA:$AA,'GL Data'!$B:$B,$A103) -> 8982.85 | Z103: =Y103+SUMIFS('GL Data'!$AB:$AB,'GL Data'!$B:$B,$A103) -> 8982.85 | AA103: =Z103+SUMIFS('GL Data'!$AC:$AC,'GL Data'!$B:$B,$A103) -> 8982.85
A104: Office Furniture & Fixtures | B104: =SUMIFS('GL Data'!$D:$D,'GL Data'!$B:$B,$A104) -> 3771.54 | C104: =B104+SUMIFS('GL Data'!$E:$E,'GL Data'!$B:$B,$A104) -> 3771.54 | D104: =C104+SUMIFS('GL Data'!$F:$F,'GL Data'!$B:$B,$A104) -> 3771.54 | E104: =D104+SUMIFS('GL Data'!$G:$G,'GL Data'!$B:$B,$A104) -> 3771.54 | F104: =E104+SUMIFS('GL Data'!$H:$H,'GL Data'!$B:$B,$A104) -> 3771.54 | G104: =F104+SUMIFS('GL Data'!$I:$I,'GL Data'!$B:$B,$A104) -> 3771.54 | H104: =G104+SUMIFS('GL Data'!$J:$J,'GL Data'!$B:$B,$A104) -> 3771.54 | I104: =H104+SUMIFS('GL Data'!$K:$K,'GL Data'!$B:$B,$A104) -> 3771.54 | J104: =I104+SUMIFS('GL Data'!$L:$L,'GL Data'!$B:$B,$A104) -> 3771.54 | K104: =J104+SUMIFS('GL Data'!$M:$M,'GL Data'!$B:$B,$A104) -> 3771.54 | L104: =K104+SUMIFS('GL Data'!$N:$N,'GL Data'!$B:$B,$A104) -> 3771.54 | M104: =L104+SUMIFS('GL Data'!$O:$O,'GL Data'!$B:$B,$A104) -> 3771.54 | N104: =M104+SUMIFS('GL Data'!$P:$P,'GL Data'!$B:$B,$A104) -> 3771.54 | O104: =N104+SUMIFS('GL Data'!$Q:$Q,'GL Data'!$B:$B,$A104) -> 3771.54 | P104: =O104+SUMIFS('GL Data'!$R:$R,'GL Data'!$B:$B,$A104) -> 3771.54 | Q104: =P104+SUMIFS('GL Data'!$S:$S,'GL Data'!$B:$B,$A104) -> 3771.54 | R104: =Q104+SUMIFS('GL Data'!$T:$T,'GL Data'!$B:$B,$A104) -> 3771.54 | S104: =R104+SUMIFS('GL Data'!$U:$U,'GL Data'!$B:$B,$A104) -> 3771.54 | T104: =S104+SUMIFS('GL Data'!$V:$V,'GL Data'!$B:$B,$A104) -> 3771.54 | U104: =T104+SUMIFS('GL Data'!$W:$W,'GL Data'!$B:$B,$A104) -> 3771.54 | V104: =U104+SUMIFS('GL Data'!$X:$X,'GL Data'!$B:$B,$A104) -> 3771.54 | W104: =V104+SUMIFS('GL Data'!$Y:$Y,'GL Data'!$B:$B,$A104) -> 3771.54 | X104: =W104+SUMIFS('GL Data'!$Z:$Z,'GL Data'!$B:$B,$A104) -> 3771.54 | Y104: =X104+SUMIFS('GL Data'!$AA:$AA,'GL Data'!$B:$B,$A104) -> 3771.54 | Z104: =Y104+SUMIFS('GL Data'!$AB:$AB,'GL Data'!$B:$B,$A104) -> 3771.54 | AA104: =Z104+SUMIFS('GL Data'!$AC:$AC,'GL Data'!$B:$B,$A104) -> 3771.54
A105: Accumulated Depreciation | B105: =SUMIFS('GL Data'!$D:$D,'GL Data'!$B:$B,$A105) -> -12754.39 | C105: =B105+SUMIFS('GL Data'!$E:$E,'GL Data'!$B:$B,$A105) -> -12754.39 | D105: =C105+SUMIFS('GL Data'!$F:$F,'GL Data'!$B:$B,$A105) -> -12754.39 | E105: =D105+SUMIFS('GL Data'!$G:$G,'GL Data'!$B:$B,$A105) -> -12754.39 | F105: =E105+SUMIFS('GL Data'!$H:$H,'GL Data'!$B:$B,$A105) -> -12754.39 | G105: =F105+SUMIFS('GL Data'!$I:$I,'GL Data'!$B:$B,$A105) -> -12754.39 | H105: =G105+SUMIFS('GL Data'!$J:$J,'GL Data'!$B:$B,$A105) -> -12754.39 | I105: =H105+SUMIFS('GL Data'!$K:$K,'GL Data'!$B:$B,$A105) -> -12754.39 | J105: =I105+SUMIFS('GL Data'!$L:$L,'GL Data'!$B:$B,$A105) -> -12754.39 | K105: =J105+SUMIFS('GL Data'!$M:$M,'GL Data'!$B:$B,$A105) -> -12754.39 | L105: =K105+SUMIFS('GL Data'!$N:$N,'GL Data'!$B:$B,$A105) -> -12754.39 | M105: =L105+SUMIFS('GL Data'!$O:$O,'GL Data'!$B:$B,$A105) -> -12754.39 | N105: =M105+SUMIFS('GL Data'!$P:$P,'GL Data'!$B:$B,$A105) -> -12754.39 | O105: =N105+SUMIFS('GL Data'!$Q:$Q,'GL Data'!$B:$B,$A105) -> -12754.39 | P105: =O105+SUMIFS('GL Data'!$R:$R,'GL Data'!$B:$B,$A105) -> -12754.39 | Q105: =P105+SUMIFS('GL Data'!$S:$S,'GL Data'!$B:$B,$A105) -> -12754.39 | R105: =Q105+SUMIFS('GL Data'!$T:$T,'GL Data'!$B:$B,$A105) -> -12754.39 | S105: =R105+SUMIFS('GL Data'!$U:$U,'GL Data'!$B:$B,$A105) -> -12754.39 | T105: =S105+SUMIFS('GL Data'!$V:$V,'GL Data'!$B:$B,$A105) -> -12754.39 | U105: =T105+SUMIFS('GL Data'!$W:$W,'GL Data'!$B:$B,$A105) -> -12754.39 | V105: =U105+SUMIFS('GL Data'!$X:$X,'GL Data'!$B:$B,$A105) -> -12754.39 | W105: =V105+SUMIFS('GL Data'!$Y:$Y,'GL Data'!$B:$B,$A105) -> -12754.39 | X105: =W105+SUMIFS('GL Data'!$Z:$Z,'GL Data'!$B:$B,$A105) -> -12754.39 | Y105: =X105+SUMIFS('GL Data'!$AA:$AA,'GL Data'!$B:$B,$A105) -> -12754.39 | Z105: =Y105+SUMIFS('GL Data'!$AB:$AB,'GL Data'!$B:$B,$A105) -> -12754.39 | AA105: =Z105+SUMIFS('GL Data'!$AC:$AC,'GL Data'!$B:$B,$A105) -> -12754.39
A106: Security Deposit | B106: =SUMIFS('GL Data'!$D:$D,'GL Data'!$B:$B,$A106) -> 807.41 | C106: =B106+SUMIFS('GL Data'!$E:$E,'GL Data'!$B:$B,$A106) -> 807.41 | D106: =C106+SUMIFS('GL Data'!$F:$F,'GL Data'!$B:$B,$A106) -> 807.41 | E106: =D106+SUMIFS('GL Data'!$G:$G,'GL Data'!$B:$B,$A106) -> 807.41 | F106: =E106+SUMIFS('GL Data'!$H:$H,'GL Data'!$B:$B,$A106) -> 807.41 | G106: =F106+SUMIFS('GL Data'!$I:$I,'GL Data'!$B:$B,$A106) -> 807.41 | H106: =G106+SUMIFS('GL Data'!$J:$J,'GL Data'!$B:$B,$A106) -> 807.41 | I106: =H106+SUMIFS('GL Data'!$K:$K,'GL Data'!$B:$B,$A106) -> 807.41 | J106: =I106+SUMIFS('GL Data'!$L:$L,'GL Data'!$B:$B,$A106) -> 807.41 | K106: =J106+SUMIFS('GL Data'!$M:$M,'GL Data'!$B:$B,$A106) -> 807.41 | L106: =K106+SUMIFS('GL Data'!$N:$N,'GL Data'!$B:$B,$A106) -> 807.41 | M106: =L106+SUMIFS('GL Data'!$O:$O,'GL Data'!$B:$B,$A106) -> 807.41 | N106: =M106+SUMIFS('GL Data'!$P:$P,'GL Data'!$B:$B,$A106) -> 807.41 | O106: =N106+SUMIFS('GL Data'!$Q:$Q,'GL Data'!$B:$B,$A106) -> 807.41 | P106: =O106+SUMIFS('GL Data'!$R:$R,'GL Data'!$B:$B,$A106) -> 0 | Q106: =P106+SUMIFS('GL Data'!$S:$S,'GL Data'!$B:$B,$A106) -> 0 | R106: =Q106+SUMIFS('GL Data'!$T:$T,'GL Data'!$B:$B,$A106) -> 0 | S106: =R106+SUMIFS('GL Data'!$U:$U,'GL Data'!$B:$B,$A106) -> 0 | T106: =S106+SUMIFS('GL Data'!$V:$V,'GL Data'!$B:$B,$A106) -> 0 | U106: =T106+SUMIFS('GL Data'!$W:$W,'GL Data'!$B:$B,$A106) -> 0 | V106: =U106+SUMIFS('GL Data'!$X:$X,'GL Data'!$B:$B,$A106) -> 0 | W106: =V106+SUMIFS('GL Data'!$Y:$Y,'GL Data'!$B:$B,$A106) -> 0 | X106: =W106+SUMIFS('GL Data'!$Z:$Z,'GL Data'!$B:$B,$A106) -> 0 | Y106: =X106+SUMIFS('GL Data'!$AA:$AA,'GL Data'!$B:$B,$A106) -> 0 | Z106: =Y106+SUMIFS('GL Data'!$AB:$AB,'GL Data'!$B:$B,$A106) -> 0 | AA106: =Z106+SUMIFS('GL Data'!$AC:$AC,'GL Data'!$B:$B,$A106) -> 0
A107: Total Non-Current Assets | B107: =SUM(B103:B106) -> 807.41 | C107: =SUM(C103:C106) -> 807.41 | D107: =SUM(D103:D106) -> 807.41 | E107: =SUM(E103:E106) -> 807.41 | F107: =SUM(F103:F106) -> 807.41 | G107: =SUM(G103:G106) -> 807.41 | H107: =SUM(H103:H106) -> 807.41 | I107: =SUM(I103:I106) -> 807.41 | ... AA107: =SUM(AA103:AA106) -> 0
A108: TOTAL ASSETS | B108: =B100+B107 -> 30758.42 | C108: =C100+C107 -> 25844.89 | D108: =D100+D107 -> 29020.68 | E108: =E100+E107 -> 26730.78 | F108: =F100+F107 -> 25601.07 | G108: =G100+G107 -> 46908.47 | H108: =H100+H107 -> 41250.38 | I108: =I100+I107 -> 24165.98 | ... AA108: =AA100+AA107 -> 87297.75
A110: Current Liabilities
A111: AMEX Credit Card | B111: =-SUMIFS('GL Data'!$D:$D,'GL Data'!$B:$B,$A111) -> 1252.3 | C111: =B111-SUMIFS('GL Data'!$E:$E,'GL Data'!$B:$B,$A111) -> 1393.21 | D111: =C111-SUMIFS('GL Data'!$F:$F,'GL Data'!$B:$B,$A111) -> 1969.95 | E111: =D111-SUMIFS('GL Data'!$G:$G,'GL Data'!$B:$B,$A111) -> 2014.75 | F111: =E111-SUMIFS('GL Data'!$H:$H,'GL Data'!$B:$B,$A111) -> 1697.76 | G111: =F111-SUMIFS('GL Data'!$I:$I,'GL Data'!$B:$B,$A111) -> 1257.94 | H111: =G111-SUMIFS('GL Data'!$J:$J,'GL Data'!$B:$B,$A111) -> 1820.85 | I111: =H111-SUMIFS('GL Data'!$K:$K,'GL Data'!$B:$B,$A111) -> 2370.28 | J111: =I111-SUMIFS('GL Data'!$L:$L,'GL Data'!$B:$B,$A111) -> 1794.08 | K111: =J111-SUMIFS('GL Data'!$M:$M,'GL Data'!$B:$B,$A111) -> 1434.12 | L111: =K111-SUMIFS('GL Data'!$N:$N,'GL Data'!$B:$B,$A111) -> 1240.17 | M111: =L111-SUMIFS('GL Data'!$O:$O,'GL Data'!$B:$B,$A111) -> 1072.26 | N111: =M111-SUMIFS('GL Data'!$P:$P,'GL Data'!$B:$B,$A111) -> 1021.84 | O111: =N111-SUMIFS('GL Data'!$Q:$Q,'GL Data'!$B:$B,$A111) -> 2059.08 | P111: =O111-SUMIFS('GL Data'!$R:$R,'GL Data'!$B:$B,$A111) -> 1205.68 | Q111: =P111-SUMIFS('GL Data'!$S:$S,'GL Data'!$B:$B,$A111) -> 976.15 | R111: =Q111-SUMIFS('GL Data'!$T:$T,'GL Data'!$B:$B,$A111) -> 3116.62 | S111: =R111-SUMIFS('GL Data'!$U:$U,'GL Data'!$B:$B,$A111) -> 4340.67 | T111: =S111-SUMIFS('GL Data'!$V:$V,'GL Data'!$B:$B,$A111) -> 1896.66 | U111: =T111-SUMIFS('GL Data'!$W:$W,'GL Data'!$B:$B,$A111) -> 1486.33 | V111: =U111-SUMIFS('GL Data'!$X:$X,'GL Data'!$B:$B,$A111) -> 3980.35 | W111: =V111-SUMIFS('GL Data'!$Y:$Y,'GL Data'!$B:$B,$A111) -> 5259.59 | X111: =W111-SUMIFS('GL Data'!$Z:$Z,'GL Data'!$B:$B,$A111) -> 703.36 | Y111: =X111-SUMIFS('GL Data'!$AA:$AA,'GL Data'!$B:$B,$A111) -> 1078.18 | Z111: =Y111-SUMIFS('GL Data'!$AB:$AB,'GL Data'!$B:$B,$A111) -> 1087.63 | AA111: =Z111-SUMIFS('GL Data'!$AC:$AC,'GL Data'!$B:$B,$A111) -> 1132.33
A112: Amex Delta Credit Card | B112: =-SUMIFS('GL Data'!$D:$D,'GL Data'!$B:$B,$A112) -> 14166 | C112: =B112-SUMIFS('GL Data'!$E:$E,'GL Data'!$B:$B,$A112) -> 16599.24 | D112: =C112-SUMIFS('GL Data'!$F:$F,'GL Data'!$B:$B,$A112) -> 11108.61 | E112: =D112-SUMIFS('GL Data'!$G:$G,'GL Data'!$B:$B,$A112) -> 9046.35 | F112: =E112-SUMIFS('GL Data'!$H:$H,'GL Data'!$B:$B,$A112) -> 7009.65 | G112: =F112-SUMIFS('GL Data'!$I:$I,'GL Data'!$B:$B,$A112) -> 7235.82 | H112: =G112-SUMIFS('GL Data'!$J:$J,'GL Data'!$B:$B,$A112) -> 7294.03 | I112: =H112-SUMIFS('GL Data'!$K:$K,'GL Data'!$B:$B,$A112) -> 7471.47 | J112: =I112-SUMIFS('GL Data'!$L:$L,'GL Data'!$B:$B,$A112) -> 10003.74 | K112: =J112-SUMIFS('GL Data'!$M:$M,'GL Data'!$B:$B,$A112) -> 9901.5 | L112: =K112-SUMIFS('GL Data'!$N:$N,'GL Data'!$B:$B,$A112) -> 11915.86 | M112: =L112-SUMIFS('GL Data'!$O:$O,'GL Data'!$B:$B,$A112) -> 11836.19 | N112: =M112-SUMIFS('GL Data'!$P:$P,'GL Data'!$B:$B,$A112) -> 11825.88 | O112: =N112-SUMIFS('GL Data'!$Q:$Q,'GL Data'!$B:$B,$A112) -> 9072.89 | P112: =O112-SUMIFS('GL Data'!$R:$R,'GL Data'!$B:$B,$A112) -> 8782.08 | Q112: =P112-SUMIFS('GL Data'!$S:$S,'GL Data'!$B:$B,$A112) -> 4719.76 | R112: =Q112-SUMIFS('GL Data'!$T:$T,'GL Data'!$B:$B,$A112) -> 1630.77 | S112: =R112-SUMIFS('GL Data'!$U:$U,'GL Data'!$B:$B,$A112) -> 1414.79 | T112: =S112-SUMIFS('GL Data'!$V:$V,'GL Data'!$B:$B,$A112) -> 1246.14 | U112: =T112-SUMIFS('GL Data'!$W:$W,'GL Data'!$B:$B,$A112) -> 1882.12 | V112: =U112-SUMIFS('GL Data'!$X:$X,'GL Data'!$B:$B,$A112) -> 4254.08 | W112: =V112-SUMIFS('GL Data'!$Y:$Y,'GL Data'!$B:$B,$A112) -> 1313.31 | X112: =W112-SUMIFS('GL Data'!$Z:$Z,'GL Data'!$B:$B,$A112) -> 1214.53 | Y112: =X112-SUMIFS('GL Data'!$AA:$AA,'GL Data'!$B:$B,$A112) -> 1276.61 | Z112: =Y112-SUMIFS('GL Data'!$AB:$AB,'GL Data'!$B:$B,$A112) -> 1132.86 | AA112: =Z112-SUMIFS('GL Data'!$AC:$AC,'GL Data'!$B:$B,$A112) -> 2062.37
A113: Chase Credit Card 4 (1892) | B113: =-SUMIFS('GL Data'!$D:$D,'GL Data'!$B:$B,$A113) -> 1889.3 | C113: =B113-SUMIFS('GL Data'!$E:$E,'GL Data'!$B:$B,$A113) -> 1435.57 | D113: =C113-SUMIFS('GL Data'!$F:$F,'GL Data'!$B:$B,$A113) -> 1510.74 | E113: =D113-SUMIFS('GL Data'!$G:$G,'GL Data'!$B:$B,$A113) -> 1954.96 | F113: =E113-SUMIFS('GL Data'!$H:$H,'GL Data'!$B:$B,$A113) -> 2442.87 | G113: =F113-SUMIFS('GL Data'!$I:$I,'GL Data'!$B:$B,$A113) -> 5536.54 | H113: =G113-SUMIFS('GL Data'!$J:$J,'GL Data'!$B:$B,$A113) -> 3403.17 | I113: =H113-SUMIFS('GL Data'!$K:$K,'GL Data'!$B:$B,$A113) -> 5834.69 | J113: =I113-SUMIFS('GL Data'!$L:$L,'GL Data'!$B:$B,$A113) -> 8197.12 | K113: =J113-SUMIFS('GL Data'!$M:$M,'GL Data'!$B:$B,$A113) -> 8610.7 | L113: =K113-SUMIFS('GL Data'!$N:$N,'GL Data'!$B:$B,$A113) -> 8579.17 | M113: =L113-SUMIFS('GL Data'!$O:$O,'GL Data'!$B:$B,$A113) -> 6845.36 | N113: =M113-SUMIFS('GL Data'!$P:$P,'GL Data'!$B:$B,$A113) -> 7568.03 | O113: =N113-SUMIFS('GL Data'!$Q:$Q,'GL Data'!$B:$B,$A113) -> 7081.67 | P113: =O113-SUMIFS('GL Data'!$R:$R,'GL Data'!$B:$B,$A113) -> 5554.66 | Q113: =P113-SUMIFS('GL Data'!$S:$S,'GL Data'!$B:$B,$A113) -> 802.3 | R113: =Q113-SUMIFS('GL Data'!$T:$T,'GL Data'!$B:$B,$A113) -> 1451.76 | S113: =R113-SUMIFS('GL Data'!$U:$U,'GL Data'!$B:$B,$A113) -> 2055.89 | T113: =S113-SUMIFS('GL Data'!$V:$V,'GL Data'!$B:$B,$A113) -> 846.57 | U113: =T113-SUMIFS('GL Data'!$W:$W,'GL Data'!$B:$B,$A113) -> 1810.38 | V113: =U113-SUMIFS('GL Data'!$X:$X,'GL Data'!$B:$B,$A113) -> 881.71 | W113: =V113-SUMIFS('GL Data'!$Y:$Y,'GL Data'!$B:$B,$A113) -> 1049.85 | X113: =W113-SUMIFS('GL Data'!$Z:$Z,'GL Data'!$B:$B,$A113) -> 941.12 | Y113: =X113-SUMIFS('GL Data'!$AA:$AA,'GL Data'!$B:$B,$A113) -> 1470.81 | Z113: =Y113-SUMIFS('GL Data'!$AB:$AB,'GL Data'!$B:$B,$A113) -> 1090.63 | AA113: =Z113-SUMIFS('GL Data'!$AC:$AC,'GL Data'!$B:$B,$A113) -> 1740.13
A114: Ohio Dept. of Taxation Payable | B114: =-SUMIFS('GL Data'!$D:$D,'GL Data'!$B:$B,$A114) -> 0 | C114: =B114-SUMIFS('GL Data'!$E:$E,'GL Data'!$B:$B,$A114) -> 0 | D114: =C114-SUMIFS('GL Data'!$F:$F,'GL Data'!$B:$B,$A114) -> 0 | E114: =D114-SUMIFS('GL Data'!$G:$G,'GL Data'!$B:$B,$A114) -> 0 | F114: =E114-SUMIFS('GL Data'!$H:$H,'GL Data'!$B:$B,$A114) -> 0 | G114: =F114-SUMIFS('GL Data'!$I:$I,'GL Data'!$B:$B,$A114) -> 0 | H114: =G114-SUMIFS('GL Data'!$J:$J,'GL Data'!$B:$B,$A114) -> 0 | I114: =H114-SUMIFS('GL Data'!$K:$K,'GL Data'!$B:$B,$A114) -> 0 | J114: =I114-SUMIFS('GL Data'!$L:$L,'GL Data'!$B:$B,$A114) -> 0 | K114: =J114-SUMIFS('GL Data'!$M:$M,'GL Data'!$B:$B,$A114) -> 0 | L114: =K114-SUMIFS('GL Data'!$N:$N,'GL Data'!$B:$B,$A114) -> 0 | M114: =L114-SUMIFS('GL Data'!$O:$O,'GL Data'!$B:$B,$A114) -> 0 | N114: =M114-SUMIFS('GL Data'!$P:$P,'GL Data'!$B:$B,$A114) -> 0 | O114: =N114-SUMIFS('GL Data'!$Q:$Q,'GL Data'!$B:$B,$A114) -> 0 | P114: =O114-SUMIFS('GL Data'!$R:$R,'GL Data'!$B:$B,$A114) -> 0 | Q114: =P114-SUMIFS('GL Data'!$S:$S,'GL Data'!$B:$B,$A114) -> 0 | R114: =Q114-SUMIFS('GL Data'!$T:$T,'GL Data'!$B:$B,$A114) -> 0 | S114: =R114-SUMIFS('GL Data'!$U:$U,'GL Data'!$B:$B,$A114) -> 0 | T114: =S114-SUMIFS('GL Data'!$V:$V,'GL Data'!$B:$B,$A114) -> 0 | U114: =T114-SUMIFS('GL Data'!$W:$W,'GL Data'!$B:$B,$A114) -> 0 | V114: =U114-SUMIFS('GL Data'!$X:$X,'GL Data'!$B:$B,$A114) -> 0 | W114: =V114-SUMIFS('GL Data'!$Y:$Y,'GL Data'!$B:$B,$A114) -> 0 | X114: =W114-SUMIFS('GL Data'!$Z:$Z,'GL Data'!$B:$B,$A114) -> 0 | Y114: =X114-SUMIFS('GL Data'!$AA:$AA,'GL Data'!$B:$B,$A114) -> 0 | Z114: =Y114-SUMIFS('GL Data'!$AB:$AB,'GL Data'!$B:$B,$A114) -> 0 | AA114: =Z114-SUMIFS('GL Data'!$AC:$AC,'GL Data'!$B:$B,$A114) -> 0
A115: Accrued Retirement | B115: =-SUMIFS('GL Data'!$D:$D,'GL Data'!$B:$B,$A115) -> 1289.88 | C115: =B115-SUMIFS('GL Data'!$E:$E,'GL Data'!$B:$B,$A115) -> 429.96 | D115: =C115-SUMIFS('GL Data'!$F:$F,'GL Data'!$B:$B,$A115) -> 384.96 | E115: =D115-SUMIFS('GL Data'!$G:$G,'GL Data'!$B:$B,$A115) -> 339.96 | F115: =E115-SUMIFS('GL Data'!$H:$H,'GL Data'!$B:$B,$A115) -> 339.96 | G115: =F115-SUMIFS('GL Data'!$I:$I,'GL Data'!$B:$B,$A115) -> 0 | H115: =G115-SUMIFS('GL Data'!$J:$J,'GL Data'!$B:$B,$A115) -> 339.96 | I115: =H115-SUMIFS('GL Data'!$K:$K,'GL Data'!$B:$B,$A115) -> 679.92 | J115: =I115-SUMIFS('GL Data'!$L:$L,'GL Data'!$B:$B,$A115) -> 1019.88 | K115: =J115-SUMIFS('GL Data'!$M:$M,'GL Data'!$B:$B,$A115) -> 1359.84 | L115: =K115-SUMIFS('GL Data'!$N:$N,'GL Data'!$B:$B,$A115) -> 1699.8 | M115: =L115-SUMIFS('GL Data'!$O:$O,'GL Data'!$B:$B,$A115) -> 2039.76 | N115: =M115-SUMIFS('GL Data'!$P:$P,'GL Data'!$B:$B,$A115) -> 2379.72 | O115: =N115-SUMIFS('GL Data'!$Q:$Q,'GL Data'!$B:$B,$A115) -> 0 | P115: =O115-SUMIFS('GL Data'!$R:$R,'GL Data'!$B:$B,$A115) -> 0 | Q115: =P115-SUMIFS('GL Data'!$S:$S,'GL Data'!$B:$B,$A115) -> 0 | R115: =Q115-SUMIFS('GL Data'!$T:$T,'GL Data'!$B:$B,$A115) -> 339.96 | S115: =R115-SUMIFS('GL Data'!$U:$U,'GL Data'!$B:$B,$A115) -> 0 | T115: =S115-SUMIFS('GL Data'!$V:$V,'GL Data'!$B:$B,$A115) -> 0 | U115: =T115-SUMIFS('GL Data'!$W:$W,'GL Data'!$B:$B,$A115) -> 0 | V115: =U115-SUMIFS('GL Data'!$X:$X,'GL Data'!$B:$B,$A115) -> 0 | W115: =V115-SUMIFS('GL Data'!$Y:$Y,'GL Data'!$B:$B,$A115) -> 0 | X115: =W115-SUMIFS('GL Data'!$Z:$Z,'GL Data'!$B:$B,$A115) -> 0 | Y115: =X115-SUMIFS('GL Data'!$AA:$AA,'GL Data'!$B:$B,$A115) -> 0 | Z115: =Y115-SUMIFS('GL Data'!$AB:$AB,'GL Data'!$B:$B,$A115) -> 0 | AA115: =Z115-SUMIFS('GL Data'!$AC:$AC,'GL Data'!$B:$B,$A115) -> 0
...

Sheet QOE Summary
A1: Smart VAs LLC — Quality of Earnings (Lite)
A2: TTM Period: July 2025 – June 2026 | Source: Monthly Financials tab (seller GL)
A3: Scope note: this is a lite QOE built solely from the seller’s GL-derived monthly financials already in this workbook. No customer-level, contract-level, or vendor-invoice detail was available, so revenue concentration and contract-quality testing (normally part of a full QOE) are out of scope here — flagged in Section 5.
A5: 1. REVENUE QUALITY (TTM)
B6: TTM $ | C6: % of Net Revenue
A7: Service Revenue (Core VA Staffing) | B7: =SUM('Monthly Financials'!P9:AA9) -> 975916.59
A8: Smart VA Academy Revenue (Non-Core) | B8: =SUM('Monthly Financials'!P10:AA10) -> 303.46
A9: Less: Discounts | B9: =SUM('Monthly Financials'!P13:AA13) -> -22786.5
A10: Less: Refunds | B10: =SUM('Monthly Financials'!P14:AA14) -> -10760.29
A11: Net Revenue | B11: =B7+B8+B9+B10 -> 942673.26
A12: Service Revenue % of Net Revenue | B12: =B7/B11 -> 1.035265
A13: Academy Revenue % of Net Revenue | B13: =B8/B11 -> 0.0003219143
A14: Discounts + Refunds % of Gross Revenue | B14: =-(B9+B10)/(B7+B8) -> 0.034363963
A15: Revenue is almost entirely recurring Service Revenue on a prepaid/subscription-style collection model (see DSO in Section 4) — a favorable revenue-quality signal. Academy Revenue is immaterial.
A17: 2. ADJUSTED EBITDA BRIDGE (TTM)
B18: TTM $ | C18: % of Net Revenue
A19: Reported EBIT / EBITDA (No Historical D&A — PP&E Fully Depreciated) | B19: =SUM('Monthly Financials'!P72:AA72) -> 159212.13
A20: Reported EBITDA Margin % | B20: =B19/B11 -> 0.16889429
A22: Add: Owner’s Pay (Control-Basis Addback) | B22: =SUM('Monthly Financials'!P40:AA40) -> 61389.51
A23: Add: Home Office Deduction (Personal/Tax-Driven) | B23: =SUM('Monthly Financials'!P61:AA61) -> 6986.8
A24: Add: Charitable Contributions (Discretionary) | B24: =SUM('Monthly Financials'!P59:AA59) -> 900
A25: Core Adjusted EBITDA | B25: =B19+B22+B23+B24 -> 228488.44
A26: Core Adjusted EBITDA Margin % | B26: =B25/B11 -> 0.2423835
A28: Memo: Judgment-Call Items (Not Included Above)
A29: Employee/Client Appreciation is common in labor-intensive, remote-retention-dependent staffing models and arguably a real cost of keeping VAs — shown separately rather than force-classified.
A30: Employee Appreciation | B30: =SUM('Monthly Financials'!P44:AA44) -> 17897.4
A31: Client Appreciation | B31: =SUM('Monthly Financials'!P50:AA50) -> 547.61
A32: Adjusted EBITDA Including Judgment Items | B32: =B25+B30+B31 -> 246933.45
A33: Adjusted EBITDA Margin % (Incl. Judgment Items) | B33: =B32/B11 -> 0.2619502
A34: Owner’s Pay is added back on a standard control-basis convention. This lite QOE does not assume a specific replacement-management cost — the buyer-side Assumptions tab already models $60,000 in new Owner Compensation plus a $60,000 new hire, which should be read alongside this bridge, not on top of it.
A36: 3. IMPLIED MULTIPLES AT ASKING PRICE
A37: Asking Price | B37: =Assumptions!E10 -> 540000
A38: Multiple of Reported EBITDA | B38: =IFERROR(B37/B19,0) -> 3.3917014
A39: Multiple of Core Adjusted EBITDA | B39: =IFERROR(B37/B25,0) -> 2.3633581
A40: Multiple of Adjusted EBITDA (Incl. Judgment Items) | B40: =IFERROR(B37/B32,0) -> 2.186824
A42: 4. BALANCE SHEET / WORKING CAPITAL QUALITY (as of Jun-2026)
A43: Accounts Receivable | B43: ='Monthly Financials'!AA92 -> 656.25
A44: Days Sales Outstanding (3-Month Rolling) | B44: ='Monthly Financials'!AA293 -> 0.25957164
A45: Net Working Capital, Ex-Cash | B45: ='Monthly Financials'!AA286 -> -4934.83
A46: Fixed Assets, Net Book Value | B46: ='Monthly Financials'!AA303 -> 0
A47: Loan Payable (Balance Sheet) | B47: ='Monthly Financials'!AA124 -> 0
A48: Line of Credit Drawn | B48: ='Monthly Financials'!AA119 -> 2.7284841e-12
A49: Total Cash | B49: ='Monthly Financials'!AA275 -> 87174.15
A50: Zero balance-sheet debt, negligible AR, and near-zero NWC confirm an asset-light, cash-collect-first operating model. Fixed assets are fully depreciated — favorable for historical D&A, but signals aging equipment a buyer should physically inspect rather than assume has ongoing service life.
A52: 5. KEY QUALITY-OF-EARNINGS OBSERVATIONS
A53: • Add-backs excluding Owner’s Pay total under 1% of Net Revenue — the reported numbers are already fairly clean; Owner’s Pay is the only addback of real size, and it is a normal control-basis adjustment, not a red flag.
A54: • No customer-level or contract-level data was in the GL extract used to build this workbook — customer concentration, contract terms, and churn-by-account could not be tested here. Recommend requesting this before finalizing a deal.
A55: • This Lite QOE measures the SELLER’s historical earning power on an as-recorded and lightly-adjusted basis. It is distinct from the Projections tab, which models FORWARD economics under a new capital structure and two new compensation lines — do not read the two as measuring the same thing.
A56: • Unapplied Cash Payments / Unapplied Cash Bill Payments (GL suspense accounts) were $0 in the TTM window — no adjustment needed currently, but worth confirming these accounts stay clear going forward.
A57: • Revenue collection is effectively immediate (DSO well under 1 day) — consistent with a prepaid or auto-charge billing model; confirm this contractually rather than assuming it persists post-close.

Sheet Assumptions
A1: Smart VAs LLC — Acquisition Model
A2: Buyer-Side Transaction, Financing & Operating Assumptions
A3: Currency: USD, whole dollars. Historical baseline ("TTM") figures link live to the Monthly Financials tab (trailing twelve months, Jul-2025–Jun-2026).
A5: ACTIVE SCENARIO (drives the Projections tab): | C5: Base | D5: ← choose Worst / Base / Best
A7: 1. TRANSACTION STRUCTURE & FINANCING
B8: Worst | C8: Base / Value | D8: Best | E8: Selected (Active) | F8: Source / Notes
A9: Deal Terms
A10: Sale (Purchase) Price | B10: =C10 -> 540000 | C10: 540000 | D10: =C10 -> 540000 | E10: =C10 -> 540000 | F10: Per buyer instruction.
A11: Working Capital Injection — % of Sale Price | B11: =C11 -> 0.055555 | C11: 0.055555 | D11: =C11 -> 0.055555 | E11: =C11 -> 0.055555 | F11: Per buyer instruction: cash injected at close for post-close operating buffer.
A12: Working Capital Injection — $ Amount | E12: =E10*E11 -> 29999.7
A13: Total Uses of Funds | E13: =E10+E12 -> 569999.7
A15: Seller Financing (Note) — Dynamically Linked, Set to 0% for Now
A16: Seller Note — % of Sale Price | B16: =C16 -> 0 | C16: 0 | D16: =C16 -> 0 | E16: =C16 -> 0 | F16: Set to 0% pending negotiated terms. Formula-linked to Sale Price so it can be activated by changing this one cell.
A17: Seller Note — $ Amount | E17: =E10*E16 -> 0
A18: Seller Note — Interest Rate | B18: =C18 -> 0.06 | C18: 0.06 | D18: =C18 -> 0.06 | E18: =C18 -> 0.06 | F18: Typical seller-note coupon is 6–8%; immaterial while the note is $0.
A19: Seller Note — Term (Years) | B19: =C19 -> 5 | C19: 5 | D19: =C19 -> 5 | E19: =C19 -> 5
A20: Seller Note — Annual Payment | E20: =IFERROR(-PMT(E18,E19,E17),0) -> 0
A22: Seller Escrow / Indemnity Holdback — 5% Market Convention, Set to 0% for Now
A23: Escrow Retention — % of Sale Price | B23: =C23 -> 0 | C23: 0 | D23: =C23 -> 0 | E23: =C23 -> 0 | F23: Market-standard indemnity holdback is ~5% of price for 12–18 months; set to 0% until deal terms are finalized. Funded from loan/equity proceeds at closing — reduces the seller’s net cash at close only, not Total Uses.
A24: Escrow Amount — $ | E24: =E10*E23 -> 0
A25: Escrow Release Period (Months) | B25: =C25 -> 12 | C25: 12 | D25: =C25 -> 12 | E25: =C25 -> 12
A27: Senior Debt — SBA 7(a) Term Loan
A28: Prime Rate (Current) | B28: =C28 -> 0.0675 | C28: 0.0675 | D28: =C28 -> 0.0675 | E28: =C28 -> 0.0675 | F28: Source: Federal Reserve H.15 Selected Interest Rates / bank prime loan rate, Aug 3, 2026 (6.75%).
A29: Spread over Prime | B29: =C29 -> 0.0275 | C29: 0.0275 | D29: =C29 -> 0.0275 | E29: =C29 -> 0.0275 | F29: Per buyer instruction; equals the SBA 7(a) maximum spread allowed on loans >$50,000 with terms ≥ 7 years.
A30: All-In Interest Rate | E30: =E28+E29 -> 0.095
A31: Loan Term (Years) | B31: =C31 -> 10 | C31: 10 | D31: =C31 -> 10 | E31: =C31 -> 10 | F31: SBA 7(a) maximum amortization for goodwill/intangible-asset acquisitions with no real estate.
A32: Senior SBA Term Loan — Amount (Plug) | E32: =+E13 -> 569999.7
A34: Sources & Uses of Funds (Check)
A35: Uses: Purchase Price | E35: =E10 -> 540000
A36: Uses: Working Capital Injection | E36: =E12 -> 29999.7
A37: Uses: SBA Gaurantee Fee | E37: 12200
A38: Estimated Closing Costs | E38: 20000
A39: Total Uses | E39: =SUM(E35:E38) -> 602199.7
A41: Sources: Buyer Equity | E41: 60300
A42: Sources: Seller Note | E42: =E17 -> 0
A43: Sources: Senior SBA Term Loan | E43: =+E39-E41-E42 -> 541899.7
A44: Total Sources | E44: =E41+E42+E43 -> 602199.7
A45: Check: Total Sources less Total Uses | E45: =E44-E39 -> 0
A46: Memo: Escrow Holdback (funded from proceeds above) | E46: =E24 -> 0
A48: 2. REVENUE ASSUMPTIONS
B49: Worst | C49: Base / Value | D49: Best | E49: Selected (Active) | F49: Source / Notes
A50: TTM Net Revenue (Baseline, Jul-2025–Jun-2026) | E50: =SUM('Monthly Financials'!P15:AA15) -> 942673.26
A51: Annual Customer Attrition Rate | B51: 0.12 | C51: 0.08 | D51: 0.03 | E51: =CHOOSE(MATCH($C$5,{"Worst","Base","Best"},0),B51,C51,D51) -> 0.08
A52: Annual New-Business Growth Rate | B52: 0.1 | C52: 0.075 | D52: 0.06 | E52: =CHOOSE(MATCH($C$5,{"Worst","Base","Best"},0),B52,C52,D52) -> 0.075 | F52: Industry research (Ibis World) suggests high revenue growth potential, industry expects 2026 growth of 6.5%
A53: Annual Price Indexing / Fee Escalation | B53: 0.02 | C53: 0.05 | D53: 0.06 | E53: =CHOOSE(MATCH($C$5,{"Worst","Base","Best"},0),B53,C53,D53) -> 0.05
A54: Net Revenue Growth Rate (Combined) | B54: =B52+B53-B51 -> 0 | C54: =C52+C53-C51 -> 0.045 | D54: =D52+D53-D51 -> 0.09 | E54: =E52+E53-E51 -> 0.045
A56: 3. COST OF SERVICES (DIRECT LABOR) ASSUMPTIONS
B57: Worst | C57: Base / Value | D57: Best | E57: Selected (Active) | F57: Source / Notes
A58: TTM Total Cost of Services (Direct Contractor Labor) | E58: =SUM('Monthly Financials'!P22:AA22) -> 341777.2
A59: Direct Labor — % of Net Revenue (Baseline) | E59: =E58/E50 -> 0.36256168 | F59: Worst = contractor turnover/backfill cost during ownership transition
A60: Year-1 Transition Efficiency Adjustment (pp added to Direct Labor %) | B60: 0.03 | C60: -0.055 | D60: -0.075 | E60: =CHOOSE(MATCH($C$5,{"Worst","Base","Best"},0),B60,C60,D60) -> -0.055 | F60: Best = buyer identifies quick efficiencies. Reverts to baseline from Year 2 onward.
A62: 4. MARKETING ASSUMPTIONS
B63: Worst | C63: Base / Value | D63: Best | E63: Selected (Active) | F63: Source / Notes
A64: TTM Total Marketing Expenses | E64: =SUM('Monthly Financials'!P33:AA33) -> 50918.49
A65: Marketing — % of Net Revenue (Baseline) | E65: =E64/E50 -> 0.054014993
A66: Annual Marketing Spend Growth Rate | B66: 0.15 | C66: 0.1 | D66: 0.04 | E66: =CHOOSE(MATCH($C$5,{"Worst","Base","Best"},0),B66,C66,D66) -> 0.1 | F66: Worst = must outspend, inefficiently, to fight attrition; Best = efficient spend, growing slower than revenue.
A68: 5. PERSONNEL & LABOR ASSUMPTIONS (INDIRECT)
B69: Worst | C69: Base / Value | D69: Best | E69: Selected (Active) | F69: Source / Notes
A70: TTM Total Personnel & Leadership (per Monthly Financials) | E70: =SUM('Monthly Financials'!P45:AA45) -> 301886.89
A71: TTM Owner's Pay (seller, per Monthly Financials) | E71: =SUM('Monthly Financials'!P40:AA40) -> 61389.51
A72: Existing Indirect Labor, Ex-Owner (Baseline $) | E72: =E70-E71 -> 240497.38
A73: Annual Wage Inflation (Existing Team, Owner & New Hire Comp) | B73: 0.05 | C73: 0.035 | D73: 0.025 | E73: =CHOOSE(MATCH($C$5,{"Worst","Base","Best"},0),B73,C73,D73) -> 0.035
A74: New Owner Compensation (Year 1) | B74: =C74 -> 72000 | C74: 72000 | D74: =C74 -> 72000 | E74: =C74 -> 72000
A75: Additional Contractor/Employee Added at Close (Year 1) | E75: 0
A76: Employer Payroll Tax Rate on New W-2 Positions | B76: =C76 -> 0.084 | C76: 0.084 | D76: =C76 -> 0.084 | E76: =C76 -> 0.084
A78: 6. SOFTWARE & SYSTEMS ASSUMPTIONS
B79: Worst | C79: Base / Value | D79: Best | E79: Selected (Active) | F79: Source / Notes
A80: TTM Software & Systems (G&A Softwares + Marketing Softwares/Subscriptions) | E80: =SUM('Monthly Financials'!P48:AA48)+SUM('Monthly Financials'!P29:AA30) -> 42514.63
A81: Software — % of Net Revenue (Baseline) | E81: =E80/E50 -> 0.04510007
A82: Annual Software Cost Growth Rate (SaaS Price Inflation / Seat Growth) | B82: 0.1 | C82: 0.05 | D82: 0.03 | E82: =CHOOSE(MATCH($C$5,{"Worst","Base","Best"},0),B82,C82,D82) -> 0.05
A84: 7. GENERAL & ADMINISTRATIVE / FEES ASSUMPTIONS
B85: Worst | C85: Base / Value | D85: Best | E85: Selected (Active) | F85: Source / Notes
A86: TTM Total General & Administrative (per Monthly Financials) | E86: =SUM('Monthly Financials'!P64:AA64)+24000 -> 82623.19
A87: TTM G&A, Ex-Software (Baseline $) | E87: =E86-E80 -> 40108.56
A88: TTM Fees and Charges (Bank & Credit Card Fees) | E88: =SUM('Monthly Financials'!P69:AA69) -> 30255.36
A89: Fees & Charges — % of Net Revenue (Baseline) | E89: =E88/E50 -> 0.032095278 | F89: Transaction-linked; held constant as a % of revenue.
A90: Annual G&A Inflation Rate (Ex-Software) | B90: 0.05 | C90: 0.03 | D90: 0.02 | E90: =CHOOSE(MATCH($C$5,{"Worst","Base","Best"},0),B90,C90,D90) -> 0.03
A92: 8. FIXED ASSETS, GOODWILL & AMORTIZATION ASSUMPTIONS
B93: Worst | C93: Base / Value | D93: Best | E93: Selected (Active) | F93: Source / Notes
A94: Tangible Fixed Assets Acquired at Close | B94: =C94 -> 0 | C94: 0 | D94: =C94 -> 0 | E94: =C94 -> 0
A95: Goodwill / Intangible Assets (Purchase Price Allocation) | E95: =E10-E94 -> 540000
A96: Intangible Amortization Period (Years) | B96: =C96 -> 15 | C96: 15 | D96: =C96 -> 15 | E96: =C96 -> 15 | F96: IRS Section 197 standard for acquired goodwill/intangibles.
A97: Annual Intangible Amortization | E97: =E95/E96 -> 36000
A98: Fixed-Asset Depreciation Period (Years) | B98: =C98 -> 5 | C98: 5 | D98: =C98 -> 5 | E98: =C98 -> 5 | F98: Straight-line.
A99: Annual Fixed-Asset Depreciation | E99: =E94/E98 -> 0
A100: Total Annual Depreciation & Amortization | E100: =E97+E99 -> 36000
A102: 9. WORKING CAPITAL ASSUMPTIONS
B103: Worst | C103: Base / Value | D103: Best | E103: Selected (Active) | F103: Source / Notes
A104: Net Working Capital (Ex-Cash) — % of Net Revenue | B104: =C104 -> -0.005 | C104: -0.005 | D104: =C104 -> -0.005 | E104: =C104 -> -0.005 | F104: Actual TTM ratio is approximately −0.52% (per Schedule 7 of Monthly Financials)
A105: Initial Working Capital Injection (Opening Cash at Close) | E105: =E12 -> 29999.7
A107: 10. TAX ASSUMPTIONS (PASS-THROUGH ENTITY)
B108: Worst | C108: Base / Value | D108: Best | E108: Selected (Active) | F108: Source / Notes
A109: LLC pass-through entity: no entity-level federal or state income tax is recorded on the Income Statement. Net income flows to the owner's personal return.
A110: Assumed Owner Effective Tax Rate (for cash-distribution planning only) | B110: =C110 -> 0.15 | C110: 0.15 | D110: =C110 -> 0.15 | E110: =C110 -> 0.15 | F110: Illustrative blended federal + state + self-employment effective rate; not a personal tax projection.
A112: 11. VALUATION (DCF) ASSUMPTIONS
B113: Worst | C113: Base / Value | D113: Best | E113: Selected (Active) | F113: Source / Notes
A114: Discount Rate (WACC Proxy) | B114: =C114 -> 0.115 | C114: 0.115 | D114: =C114 -> 0.115 | E114: =C114 -> 0.115 | F114: Per buyer instruction.
A115: Terminal Growth Rate | B115: =C115 -> 0.03 | C115: 0.03 | D115: =C115 -> 0.03 | E115: =C115 -> 0.03

Sheet Projections
A1: Smart VAs LLC — Acquisition Model
A2: 5-Year Pro Forma Projections — Income Statement, Balance Sheet, Cash Flow, Schedules & DCF
A3: Currency: USD, whole dollars. Driven by the Assumptions tab — change the scenario selector on Assumptions!C5 (Worst / Base / Best) to reflex the entire model. Monthly detail: each year is grouped into 12 monthly columns (M1–M12), hidden by default — click the [+] above the year column to expand. Months are an even 1/12 allocation of each annual figure (balances are straight-lined between year-ends), so every month group foots exactly to its year column and no annual result changes.
A5: INCOME STATEMENT (QUASI-SIMPLIFIED)
C6: M1 | D6: M2 | E6: M3 | F6: M4 | G6: M5 | H6: M6 | I6: M7 | J6: M8 | K6: M9 | L6: M10 | M6: M11 | N6: M12 | O6: Year 1 | P6: M1 | Q6: M2 | R6: M3 | S6: M4 | T6: M5 | U6: M6 | V6: M7 | W6: M8 | X6: M9 | Y6: M10 | Z6: M11 | AA6: M12 | AB6: Year 2 | AC6: M1 | AD6: M2 | AE6: M3 | AF6: M4 | AG6: M5 | AH6: M6 | AI6: M7 | AJ6: M8 | AK6: M9 | AL6: M10 | AM6: M11 | AN6: M12 | AO6: Year 3 | AP6: M1 | AQ6: M2 | AR6: M3 | AS6: M4 | AT6: M5 | AU6: M6 | AV6: M7 | AW6: M8 | AX6: M9 | AY6: M10 | AZ6: M11 | BA6: M12 | BB6: Year 4 | BC6: M1 | BD6: M2 | BE6: M3 | BF6: M4 | BG6: M5 | BH6: M6 | BI6: M7 | BJ6: M8 | BK6: M9 | BL6: M10 | BM6: M11 | BN6: M12 | BO6: Year 5
A7: Net Revenue | C7: =$O7/12 -> 82091.13 | D7: =$O7/12 -> 82091.13 | E7: =$O7/12 -> 82091.13 | F7: =$O7/12 -> 82091.13 | G7: =$O7/12 -> 82091.13 | H7: =$O7/12 -> 82091.13 | I7: =$O7/12 -> 82091.13 | J7: =$O7/12 -> 82091.13 | ... N7: =$O7/12 -> 82091.13 | O7: =Assumptions!E50*(1+Assumptions!E54) -> 985093.56 | P7: =$AB7/12 -> 85785.231 | Q7: =$AB7/12 -> 85785.231 | R7: =$AB7/12 -> 85785.231 | S7: =$AB7/12 -> 85785.231 | T7: =$AB7/12 -> 85785.231 | U7: =$AB7/12 -> 85785.231 | V7: =$AB7/12 -> 85785.231 | W7: =$AB7/12 -> 85785.231 | ... AA7: =$AB7/12 -> 85785.231 | AB7: =O7*(1+Assumptions!E54) -> 1029422.8 | AC7: =$AO7/12 -> 89645.566 | AD7: =$AO7/12 -> 89645.566 | AE7: =$AO7/12 -> 89645.566 | AF7: =$AO7/12 -> 89645.566 | AG7: =$AO7/12 -> 89645.566 | AH7: =$AO7/12 -> 89645.566 | AI7: =$AO7/12 -> 89645.566 | AJ7: =$AO7/12 -> 89645.566 | ... AN7: =$AO7/12 -> 89645.566 | AO7: =AB7*(1+Assumptions!E54) -> 1075746.8 | AP7: =$BB7/12 -> 93679.616 | AQ7: =$BB7/12 -> 93679.616 | AR7: =$BB7/12 -> 93679.616 | AS7: =$BB7/12 -> 93679.616 | AT7: =$BB7/12 -> 93679.616 | AU7: =$BB7/12 -> 93679.616 | AV7: =$BB7/12 -> 93679.616 | AW7: =$BB7/12 -> 93679.616 | ... BA7: =$BB7/12 -> 93679.616 | BB7: =AO7*(1+Assumptions!E54) -> 1124155.4 | BC7: =$BO7/12 -> 97895.199 | BD7: =$BO7/12 -> 97895.199 | BE7: =$BO7/12 -> 97895.199 | BF7: =$BO7/12 -> 97895.199 | BG7: =$BO7/12 -> 97895.199 | BH7: =$BO7/12 -> 97895.199 | BI7: =$BO7/12 -> 97895.199 | BJ7: =$BO7/12 -> 97895.199 | ... BN7: =$BO7/12 -> 97895.199 | BO7: =BB7*(1+Assumptions!E54) -> 1174742.4
A8: Direct Labor — % of Net Revenue | C8: =$O8 -> 0.30756168 | D8: =$O8 -> 0.30756168 | E8: =$O8 -> 0.30756168 | F8: =$O8 -> 0.30756168 | G8: =$O8 -> 0.30756168 | H8: =$O8 -> 0.30756168 | I8: =$O8 -> 0.30756168 | J8: =$O8 -> 0.30756168 | ... N8: =$O8 -> 0.30756168 | O8: =Assumptions!E59+Assumptions!E60 -> 0.30756168 | P8: =$AB8 -> 0.36256168 | Q8: =$AB8 -> 0.36256168 | R8: =$AB8 -> 0.36256168 | S8: =$AB8 -> 0.36256168 | T8: =$AB8 -> 0.36256168 | U8: =$AB8 -> 0.36256168 | V8: =$AB8 -> 0.36256168 | W8: =$AB8 -> 0.36256168 | ... AA8: =$AB8 -> 0.36256168 | AB8: =Assumptions!E59 -> 0.36256168 | AC8: =$AO8 -> 0.36256168 | AD8: =$AO8 -> 0.36256168 | AE8: =$AO8 -> 0.36256168 | AF8: =$AO8 -> 0.36256168 | AG8: =$AO8 -> 0.36256168 | AH8: =$AO8 -> 0.36256168 | AI8: =$AO8 -> 0.36256168 | AJ8: =$AO8 -> 0.36256168 | ... AN8: =$AO8 -> 0.36256168 | AO8: =Assumptions!E59 -> 0.36256168 | AP8: =$BB8 -> 0.36256168 | AQ8: =$BB8 -> 0.36256168 | AR8: =$BB8 -> 0.36256168 | AS8: =$BB8 -> 0.36256168 | AT8: =$BB8 -> 0.36256168 | AU8: =$BB8 -> 0.36256168 | AV8: =$BB8 -> 0.36256168 | AW8: =$BB8 -> 0.36256168 | ... BA8: =$BB8 -> 0.36256168 | BB8: =Assumptions!E59 -> 0.36256168 | BC8: =$BO8 -> 0.36256168 | BD8: =$BO8 -> 0.36256168 | BE8: =$BO8 -> 0.36256168 | BF8: =$BO8 -> 0.36256168 | BG8: =$BO8 -> 0.36256168 | BH8: =$BO8 -> 0.36256168 | BI8: =$BO8 -> 0.36256168 | BJ8: =$BO8 -> 0.36256168 | ... BN8: =$BO8 -> 0.36256168 | BO8: =Assumptions!E59 -> 0.36256168
A9: Direct Labor (Cost of Services — Contractors) | C9: =C7*C8 -> 25248.086 | D9: =D7*D8 -> 25248.086 | E9: =E7*E8 -> 25248.086 | F9: =F7*F8 -> 25248.086 | G9: =G7*G8 -> 25248.086 | H9: =H7*H8 -> 25248.086 | I9: =I7*I8 -> 25248.086 | J9: =J7*J8 -> 25248.086 | ... BO9: =BO7*BO8 -> 425916.57
A10: Gross Profit | C10: =C7-C9 -> 56843.044 | D10: =D7-D9 -> 56843.044 | E10: =E7-E9 -> 56843.044 | F10: =F7-F9 -> 56843.044 | G10: =G7-G9 -> 56843.044 | H10: =H7-H9 -> 56843.044 | I10: =I7-I9 -> 56843.044 | J10: =J7-J9 -> 56843.044 | ... BO10: =BO7-BO9 -> 748825.82
A11: Gross Margin % | C11: =IFERROR(C10/C7,0) -> 0.69243832 | D11: =IFERROR(D10/D7,0) -> 0.69243832 | E11: =IFERROR(E10/E7,0) -> 0.69243832 | F11: =IFERROR(F10/F7,0) -> 0.69243832 | G11: =IFERROR(G10/G7,0) -> 0.69243832 | H11: =IFERROR(H10/H7,0) -> 0.69243832 | I11: =IFERROR(I10/I7,0) -> 0.69243832 | J11: =IFERROR(J10/J7,0) -> 0.69243832 | ... BO11: =IFERROR(BO10/BO7,0) -> 0.63743832
A13: Operating Expenses
A14: Marketing | C14: =$O14/12 -> 4667.5283 | D14: =$O14/12 -> 4667.5283 | E14: =$O14/12 -> 4667.5283 | F14: =$O14/12 -> 4667.5283 | G14: =$O14/12 -> 4667.5283 | H14: =$O14/12 -> 4667.5283 | I14: =$O14/12 -> 4667.5283 | J14: =$O14/12 -> 4667.5283 | ... N14: =$O14/12 -> 4667.5283 | O14: =Assumptions!E64*(1+Assumptions!E66) -> 56010.339 | P14: =$AB14/12 -> 5134.2811 | Q14: =$AB14/12 -> 5134.2811 | R14: =$AB14/12 -> 5134.2811 | S14: =$AB14/12 -> 5134.2811 | T14: =$AB14/12 -> 5134.2811 | U14: =$AB14/12 -> 5134.2811 | V14: =$AB14/12 -> 5134.2811 | W14: =$AB14/12 -> 5134.2811 | ... AA14: =$AB14/12 -> 5134.2811 | AB14: =O14*(1+Assumptions!E66) -> 61611.373 | AC14: =$AO14/12 -> 5647.7092 | AD14: =$AO14/12 -> 5647.7092 | AE14: =$AO14/12 -> 5647.7092 | AF14: =$AO14/12 -> 5647.7092 | AG14: =$AO14/12 -> 5647.7092 | AH14: =$AO14/12 -> 5647.7092 | AI14: =$AO14/12 -> 5647.7092 | AJ14: =$AO14/12 -> 5647.7092 | ... AN14: =$AO14/12 -> 5647.7092 | AO14: =AB14*(1+Assumptions!E66) -> 67772.51 | AP14: =$BB14/12 -> 6212.4801 | AQ14: =$BB14/12 -> 6212.4801 | AR14: =$BB14/12 -> 6212.4801 | AS14: =$BB14/12 -> 6212.4801 | AT14: =$BB14/12 -> 6212.4801 | AU14: =$BB14/12 -> 6212.4801 | AV14: =$BB14/12 -> 6212.4801 | AW14: =$BB14/12 -> 6212.4801 | ... BA14: =$BB14/12 -> 6212.4801 | BB14: =AO14*(1+Assumptions!E66) -> 74549.761 | BC14: =$BO14/12 -> 6833.7281 | BD14: =$BO14/12 -> 6833.7281 | BE14: =$BO14/12 -> 6833.7281 | BF14: =$BO14/12 -> 6833.7281 | BG14: =$BO14/12 -> 6833.7281 | BH14: =$BO14/12 -> 6833.7281 | BI14: =$BO14/12 -> 6833.7281 | BJ14: =$BO14/12 -> 6833.7281 | ... BN14: =$BO14/12 -> 6833.7281 | BO14: =BB14*(1+Assumptions!E66) -> 82004.737
A15: Indirect Labor — Existing Team | C15: =$O15/12 -> 20742.899 | D15: =$O15/12 -> 20742.899 | E15: =$O15/12 -> 20742.899 | F15: =$O15/12 -> 20742.899 | G15: =$O15/12 -> 20742.899 | H15: =$O15/12 -> 20742.899 | I15: =$O15/12 -> 20742.899 | J15: =$O15/12 -> 20742.899 | ... N15: =$O15/12 -> 20742.899 | O15: =Assumptions!E72*(1+Assumptions!E73) -> 248914.79 | P15: =$AB15/12 -> 21468.9 | Q15: =$AB15/12 -> 21468.9 | R15: =$AB15/12 -> 21468.9 | S15: =$AB15/12 -> 21468.9 | T15: =$AB15/12 -> 21468.9 | U15: =$AB15/12 -> 21468.9 | V15: =$AB15/12 -> 21468.9 | W15: =$AB15/12 -> 21468.9 | ... AA15: =$AB15/12 -> 21468.9 | AB15: =O15*(1+Assumptions!E73) -> 257626.81 | AC15: =$AO15/12 -> 22220.312 | AD15: =$AO15/12 -> 22220.312 | AE15: =$AO15/12 -> 22220.312 | AF15: =$AO15/12 -> 22220.312 | AG15: =$AO15/12 -> 22220.312 | AH15: =$AO15/12 -> 22220.312 | AI15: =$AO15/12 -> 22220.312 | AJ15: =$AO15/12 -> 22220.312 | ... AN15: =$AO15/12 -> 22220.312 | AO15: =AB15*(1+Assumptions!E73) -> 266643.74 | AP15: =$BB15/12 -> 22998.023 | AQ15: =$BB15/12 -> 22998.023 | AR15: =$BB15/12 -> 22998.023 | AS15: =$BB15/12 -> 22998.023 | AT15: =$BB15/12 -> 22998.023 | AU15: =$BB15/12 -> 22998.023 | AV15: =$BB15/12 -> 22998.023 | AW15: =$BB15/12 -> 22998.023 | ... BA15: =$BB15/12 -> 22998.023 | BB15: =AO15*(1+Assumptions!E73) -> 275976.28 | BC15: =$BO15/12 -> 23802.954 | BD15: =$BO15/12 -> 23802.954 | BE15: =$BO15/12 -> 23802.954 | BF15: =$BO15/12 -> 23802.954 | BG15: =$BO15/12 -> 23802.954 | BH15: =$BO15/12 -> 23802.954 | BI15: =$BO15/12 -> 23802.954 | BJ15: =$BO15/12 -> 23802.954 | ... BN15: =$BO15/12 -> 23802.954 | BO15: =BB15*(1+Assumptions!E73) -> 285635.44
A16: Owner Compensation (New) | C16: =$O16/12 -> 6000 | D16: =$O16/12 -> 6000 | E16: =$O16/12 -> 6000 | F16: =$O16/12 -> 6000 | G16: =$O16/12 -> 6000 | H16: =$O16/12 -> 6000 | I16: =$O16/12 -> 6000 | J16: =$O16/12 -> 6000 | ... N16: =$O16/12 -> 6000 | O16: =Assumptions!E74 -> 72000 | P16: =$AB16/12 -> 6210 | Q16: =$AB16/12 -> 6210 | R16: =$AB16/12 -> 6210 | S16: =$AB16/12 -> 6210 | T16: =$AB16/12 -> 6210 | U16: =$AB16/12 -> 6210 | V16: =$AB16/12 -> 6210 | W16: =$AB16/12 -> 6210 | ... AA16: =$AB16/12 -> 6210 | AB16: =O16*(1+Assumptions!E73) -> 74520 | AC16: =$AO16/12 -> 6427.35 | AD16: =$AO16/12 -> 6427.35 | AE16: =$AO16/12 -> 6427.35 | AF16: =$AO16/12 -> 6427.35 | AG16: =$AO16/12 -> 6427.35 | AH16: =$AO16/12 -> 6427.35 | AI16: =$AO16/12 -> 6427.35 | AJ16: =$AO16/12 -> 6427.35 | ... AN16: =$AO16/12 -> 6427.35 | AO16: =AB16*(1+Assumptions!E73) -> 77128.2 | AP16: =$BB16/12 -> 6652.3072 | AQ16: =$BB16/12 -> 6652.3072 | AR16: =$BB16/12 -> 6652.3072 | AS16: =$BB16/12 -> 6652.3072 | AT16: =$BB16/12 -> 6652.3072 | AU16: =$BB16/12 -> 6652.3072 | AV16: =$BB16/12 -> 6652.3072 | AW16: =$BB16/12 -> 6652.3072 | ... BA16: =$BB16/12 -> 6652.3072 | BB16: =AO16*(1+Assumptions!E73) -> 79827.687 | BC16: =$BO16/12 -> 6885.138 | BD16: =$BO16/12 -> 6885.138 | BE16: =$BO16/12 -> 6885.138 | BF16: =$BO16/12 -> 6885.138 | BG16: =$BO16/12 -> 6885.138 | BH16: =$BO16/12 -> 6885.138 | BI16: =$BO16/12 -> 6885.138 | BJ16: =$BO16/12 -> 6885.138 | ... BN16: =$BO16/12 -> 6885.138 | BO16: =BB16*(1+Assumptions!E73) -> 82621.656
A17: Additional Contractor/Employee Added at Close | C17: =$O17/12 -> 0 | D17: =$O17/12 -> 0 | E17: =$O17/12 -> 0 | F17: =$O17/12 -> 0 | G17: =$O17/12 -> 0 | H17: =$O17/12 -> 0 | I17: =$O17/12 -> 0 | J17: =$O17/12 -> 0 | ... N17: =$O17/12 -> 0 | O17: =Assumptions!E75 -> 0 | P17: =$AB17/12 -> 0 | Q17: =$AB17/12 -> 0 | R17: =$AB17/12 -> 0 | S17: =$AB17/12 -> 0 | T17: =$AB17/12 -> 0 | U17: =$AB17/12 -> 0 | V17: =$AB17/12 -> 0 | W17: =$AB17/12 -> 0 | ... AA17: =$AB17/12 -> 0 | AB17: =O17*(1+Assumptions!E73) -> 0 | AC17: =$AO17/12 -> 0 | AD17: =$AO17/12 -> 0 | AE17: =$AO17/12 -> 0 | AF17: =$AO17/12 -> 0 | AG17: =$AO17/12 -> 0 | AH17: =$AO17/12 -> 0 | AI17: =$AO17/12 -> 0 | AJ17: =$AO17/12 -> 0 | ... AN17: =$AO17/12 -> 0 | AO17: =AB17*(1+Assumptions!E73) -> 0 | AP17: =$BB17/12 -> 0 | AQ17: =$BB17/12 -> 0 | AR17: =$BB17/12 -> 0 | AS17: =$BB17/12 -> 0 | AT17: =$BB17/12 -> 0 | AU17: =$BB17/12 -> 0 | AV17: =$BB17/12 -> 0 | AW17: =$BB17/12 -> 0 | ... BA17: =$BB17/12 -> 0 | BB17: =AO17*(1+Assumptions!E73) -> 0 | BC17: =$BO17/12 -> 0 | BD17: =$BO17/12 -> 0 | BE17: =$BO17/12 -> 0 | BF17: =$BO17/12 -> 0 | BG17: =$BO17/12 -> 0 | BH17: =$BO17/12 -> 0 | BI17: =$BO17/12 -> 0 | BJ17: =$BO17/12 -> 0 | ... BN17: =$BO17/12 -> 0 | BO17: =BB17*(1+Assumptions!E73) -> 0
A18: Payroll Tax on New Positions | C18: =(C16+C17)*Assumptions!E76 -> 504 | D18: =(D16+D17)*Assumptions!E76 -> 504 | E18: =(E16+E17)*Assumptions!E76 -> 504 | F18: =(F16+F17)*Assumptions!E76 -> 504 | G18: =(G16+G17)*Assumptions!E76 -> 504 | H18: =(H16+H17)*Assumptions!E76 -> 504 | I18: =(I16+I17)*Assumptions!E76 -> 504 | J18: =(J16+J17)*Assumptions!E76 -> 504 | K18: =(K16+K17)*Assumptions!E76 -> 504 | L18: =(L16+L17)*Assumptions!E76 -> 504 | M18: =(M16+M17)*Assumptions!E76 -> 504 | N18: =(N16+N17)*Assumptions!E76 -> 504 | O18: =(O16+O17)*Assumptions!E76 -> 6048 | P18: =(P16+P17)*Assumptions!E76 -> 521.64 | Q18: =(Q16+Q17)*Assumptions!E76 -> 521.64 | R18: =(R16+R17)*Assumptions!E76 -> 521.64 | S18: =(S16+S17)*Assumptions!E76 -> 521.64 | T18: =(T16+T17)*Assumptions!E76 -> 521.64 | U18: =(U16+U17)*Assumptions!E76 -> 521.64 | V18: =(V16+V17)*Assumptions!E76 -> 521.64 | W18: =(W16+W17)*Assumptions!E76 -> 521.64 | X18: =(X16+X17)*Assumptions!E76 -> 521.64 | Y18: =(Y16+Y17)*Assumptions!E76 -> 521.64 | Z18: =(Z16+Z17)*Assumptions!E76 -> 521.64 | AA18: =(AA16+AA17)*Assumptions!E76 -> 521.64 | AB18: =(AB16+AB17)*Assumptions!E76 -> 6259.68 | AC18: =(AC16+AC17)*Assumptions!E76 -> 539.8974 | AD18: =(AD16+AD17)*Assumptions!E76 -> 539.8974 | AE18: =(AE16+AE17)*Assumptions!E76 -> 539.8974 | AF18: =(AF16+AF17)*Assumptions!E76 -> 539.8974 | AG18: =(AG16+AG17)*Assumptions!E76 -> 539.8974 | AH18: =(AH16+AH17)*Assumptions!E76 -> 539.8974 | AI18: =(AI16+AI17)*Assumptions!E76 -> 539.8974 | AJ18: =(AJ16+AJ17)*Assumptions!E76 -> 539.8974 | AK18: =(AK16+AK17)*Assumptions!E76 -> 539.8974 | AL18: =(AL16+AL17)*Assumptions!E76 -> 539.8974 | AM18: =(AM16+AM17)*Assumptions!E76 -> 539.8974 | AN18: =(AN16+AN17)*Assumptions!E76 -> 539.8974 | AO18: =(AO16+AO17)*Assumptions!E76 -> 6478.7688 | AP18: =(AP16+AP17)*Assumptions!E76 -> 558.79381 | AQ18: =(AQ16+AQ17)*Assumptions!E76 -> 558.79381 | AR18: =(AR16+AR17)*Assumptions!E76 -> 558.79381 | AS18: =(AS16+AS17)*Assumptions!E76 -> 558.79381 | AT18: =(AT16+AT17)*Assumptions!E76 -> 558.79381 | AU18: =(AU16+AU17)*Assumptions!E76 -> 558.79381 | AV18: =(AV16+AV17)*Assumptions!E76 -> 558.79381 | AW18: =(AW16+AW17)*Assumptions!E76 -> 558.79381 | AX18: =(AX16+AX17)*Assumptions!E76 -> 558.79381 | AY18: =(AY16+AY17)*Assumptions!E76 -> 558.79381 | AZ18: =(AZ16+AZ17)*Assumptions!E76 -> 558.79381 | BA18: =(BA16+BA17)*Assumptions!E76 -> 558.79381 | BB18: =(BB16+BB17)*Assumptions!E76 -> 6705.5257 | BC18: =(BC16+BC17)*Assumptions!E76 -> 578.35159 | BD18: =(BD16+BD17)*Assumptions!E76 -> 578.35159 | BE18: =(BE16+BE17)*Assumptions!E76 -> 578.35159 | BF18: =(BF16+BF17)*Assumptions!E76 -> 578.35159 | BG18: =(BG16+BG17)*Assumptions!E76 -> 578.35159 | BH18: =(BH16+BH17)*Assumptions!E76 -> 578.35159 | BI18: =(BI16+BI17)*Assumptions!E76 -> 578.35159 | BJ18: =(BJ16+BJ17)*Assumptions!E76 -> 578.35159 | BK18: =(BK16+BK17)*Assumptions!E76 -> 578.35159 | BL18: =(BL16+BL17)*Assumptions!E76 -> 578.35159 | BM18: =(BM16+BM17)*Assumptions!E76 -> 578.35159 | BN18: =(BN16+BN17)*Assumptions!E76 -> 578.35159 | BO18: =(BO16+BO17)*Assumptions!E76 -> 6940.2191
A19: Total Indirect Labor | C19: =C15+C16+C17+C18 -> 27246.899 | D19: =D15+D16+D17+D18 -> 27246.899 | E19: =E15+E16+E17+E18 -> 27246.899 | F19: =F15+F16+F17+F18 -> 27246.899 | G19: =G15+G16+G17+G18 -> 27246.899 | H19: =H15+H16+H17+H18 -> 27246.899 | I19: =I15+I16+I17+I18 -> 27246.899 | J19: =J15+J16+J17+J18 -> 27246.899 | ... BO19: =BO15+BO16+BO17+BO18 -> 375197.32
A20: Software & Systems | C20: =$O20/12 -> 3720.0301 | D20: =$O20/12 -> 3720.0301 | E20: =$O20/12 -> 3720.0301 | F20: =$O20/12 -> 3720.0301 | G20: =$O20/12 -> 3720.0301 | H20: =$O20/12 -> 3720.0301 | I20: =$O20/12 -> 3720.0301 | J20: =$O20/12 -> 3720.0301 | ... N20: =$O20/12 -> 3720.0301 | O20: =Assumptions!E80*(1+Assumptions!E82) -> 44640.362 | P20: =$AB20/12 -> 3906.0316 | Q20: =$AB20/12 -> 3906.0316 | R20: =$AB20/12 -> 3906.0316 | S20: =$AB20/12 -> 3906.0316 | T20: =$AB20/12 -> 3906.0316 | U20: =$AB20/12 -> 3906.0316 | V20: =$AB20/12 -> 3906.0316 | W20: =$AB20/12 -> 3906.0316 | ... AA20: =$AB20/12 -> 3906.0316 | AB20: =O20*(1+Assumptions!E82) -> 46872.38 | AC20: =$AO20/12 -> 4101.3332 | AD20: =$AO20/12 -> 4101.3332 | AE20: =$AO20/12 -> 4101.3332 | AF20: =$AO20/12 -> 4101.3332 | AG20: =$AO20/12 -> 4101.3332 | AH20: =$AO20/12 -> 4101.3332 | AI20: =$AO20/12 -> 4101.3332 | AJ20: =$AO20/12 -> 4101.3332 | ... AN20: =$AO20/12 -> 4101.3332 | AO20: =AB20*(1+Assumptions!E82) -> 49215.999 | AP20: =$BB20/12 -> 4306.3999 | AQ20: =$BB20/12 -> 4306.3999 | AR20: =$BB20/12 -> 4306.3999 | AS20: =$BB20/12 -> 4306.3999 | AT20: =$BB20/12 -> 4306.3999 | AU20: =$BB20/12 -> 4306.3999 | AV20: =$BB20/12 -> 4306.3999 | AW20: =$BB20/12 -> 4306.3999 | ... BA20: =$BB20/12 -> 4306.3999 | BB20: =AO20*(1+Assumptions!E82) -> 51676.798 | BC20: =$BO20/12 -> 4521.7199 | BD20: =$BO20/12 -> 4521.7199 | BE20: =$BO20/12 -> 4521.7199 | BF20: =$BO20/12 -> 4521.7199 | BG20: =$BO20/12 -> 4521.7199 | BH20: =$BO20/12 -> 4521.7199 | BI20: =$BO20/12 -> 4521.7199 | BJ20: =$BO20/12 -> 4521.7199 | ... BN20: =$BO20/12 -> 4521.7199 | BO20: =BB20*(1+Assumptions!E82) -> 54260.638
A21: General & Administrative (Ex-Software) | C21: =$O21/12 -> 3442.6514 | D21: =$O21/12 -> 3442.6514 | E21: =$O21/12 -> 3442.6514 | F21: =$O21/12 -> 3442.6514 | G21: =$O21/12 -> 3442.6514 | H21: =$O21/12 -> 3442.6514 | I21: =$O21/12 -> 3442.6514 | J21: =$O21/12 -> 3442.6514 | ... N21: =$O21/12 -> 3442.6514 | O21: =Assumptions!E87*(1+Assumptions!E90) -> 41311.817 | P21: =$AB21/12 -> 3545.9309 | Q21: =$AB21/12 -> 3545.9309 | R21: =$AB21/12 -> 3545.9309 | S21: =$AB21/12 -> 3545.9309 | T21: =$AB21/12 -> 3545.9309 | U21: =$AB21/12 -> 3545.9309 | V21: =$AB21/12 -> 3545.9309 | W21: =$AB21/12 -> 3545.9309 | ... AA21: =$AB21/12 -> 3545.9309 | AB21: =O21*(1+Assumptions!E90) -> 42551.171 | AC21: =$AO21/12 -> 3652.3089 | AD21: =$AO21/12 -> 3652.3089 | AE21: =$AO21/12 -> 3652.3089 | AF21: =$AO21/12 -> 3652.3089 | AG21: =$AO21/12 -> 3652.3089 | AH21: =$AO21/12 -> 3652.3089 | AI21: =$AO21/12 -> 3652.3089 | AJ21: =$AO21/12 -> 3652.3089 | ... AN21: =$AO21/12 -> 3652.3089 | AO21: =AB21*(1+Assumptions!E90) -> 43827.706 | AP21: =$BB21/12 -> 3761.8781 | AQ21: =$BB21/12 -> 3761.8781 | AR21: =$BB21/12 -> 3761.8781 | AS21: =$BB21/12 -> 3761.8781 | AT21: =$BB21/12 -> 3761.8781 | AU21: =$BB21/12 -> 3761.8781 | AV21: =$BB21/12 -> 3761.8781 | AW21: =$BB21/12 -> 3761.8781 | ... BA21: =$BB21/12 -> 3761.8781 | BB21: =AO21*(1+Assumptions!E90) -> 45142.538 | BC21: =$BO21/12 -> 3874.7345 | BD21: =$BO21/12 -> 3874.7345 | BE21: =$BO21/12 -> 3874.7345 | BF21: =$BO21/12 -> 3874.7345 | BG21: =$BO21/12 -> 3874.7345 | BH21: =$BO21/12 -> 3874.7345 | BI21: =$BO21/12 -> 3874.7345 | BJ21: =$BO21/12 -> 3874.7345 | ... BN21: =$BO21/12 -> 3874.7345 | BO21: =BB21*(1+Assumptions!E90) -> 46496.814
A22: Fees & Charges (Bank / Credit Card) | C22: =C7*Assumptions!E89 -> 2634.7376 | D22: =D7*Assumptions!E89 -> 2634.7376 | E22: =E7*Assumptions!E89 -> 2634.7376 | F22: =F7*Assumptions!E89 -> 2634.7376 | G22: =G7*Assumptions!E89 -> 2634.7376 | H22: =H7*Assumptions!E89 -> 2634.7376 | I22: =I7*Assumptions!E89 -> 2634.7376 | J22: =J7*Assumptions!E89 -> 2634.7376 | K22: =K7*Assumptions!E89 -> 2634.7376 | L22: =L7*Assumptions!E89 -> 2634.7376 | M22: =M7*Assumptions!E89 -> 2634.7376 | N22: =N7*Assumptions!E89 -> 2634.7376 | O22: =O7*Assumptions!E89 -> 31616.851 | P22: =P7*Assumptions!E89 -> 2753.3008 | Q22: =Q7*Assumptions!E89 -> 2753.3008 | R22: =R7*Assumptions!E89 -> 2753.3008 | S22: =S7*Assumptions!E89 -> 2753.3008 | T22: =T7*Assumptions!E89 -> 2753.3008 | U22: =U7*Assumptions!E89 -> 2753.3008 | V22: =V7*Assumptions!E89 -> 2753.3008 | W22: =W7*Assumptions!E89 -> 2753.3008 | X22: =X7*Assumptions!E89 -> 2753.3008 | Y22: =Y7*Assumptions!E89 -> 2753.3008 | Z22: =Z7*Assumptions!E89 -> 2753.3008 | AA22: =AA7*Assumptions!E89 -> 2753.3008 | AB22: =AB7*Assumptions!E89 -> 33039.61 | AC22: =AC7*Assumptions!E89 -> 2877.1993 | AD22: =AD7*Assumptions!E89 -> 2877.1993 | AE22: =AE7*Assumptions!E89 -> 2877.1993 | AF22: =AF7*Assumptions!E89 -> 2877.1993 | AG22: =AG7*Assumptions!E89 -> 2877.1993 | AH22: =AH7*Assumptions!E89 -> 2877.1993 | AI22: =AI7*Assumptions!E89 -> 2877.1993 | AJ22: =AJ7*Assumptions!E89 -> 2877.1993 | AK22: =AK7*Assumptions!E89 -> 2877.1993 | AL22: =AL7*Assumptions!E89 -> 2877.1993 | AM22: =AM7*Assumptions!E89 -> 2877.1993 | AN22: =AN7*Assumptions!E89 -> 2877.1993 | AO22: =AO7*Assumptions!E89 -> 34526.392 | AP22: =AP7*Assumptions!E89 -> 3006.6733 | AQ22: =AQ7*Assumptions!E89 -> 3006.6733 | AR22: =AR7*Assumptions!E89 -> 3006.6733 | AS22: =AS7*Assumptions!E89 -> 3006.6733 | AT22: =AT7*Assumptions!E89 -> 3006.6733 | AU22: =AU7*Assumptions!E89 -> 3006.6733 | AV22: =AV7*Assumptions!E89 -> 3006.6733 | AW22: =AW7*Assumptions!E89 -> 3006.6733 | AX22: =AX7*Assumptions!E89 -> 3006.6733 | AY22: =AY7*Assumptions!E89 -> 3006.6733 | AZ22: =AZ7*Assumptions!E89 -> 3006.6733 | BA22: =BA7*Assumptions!E89 -> 3006.6733 | BB22: =BB7*Assumptions!E89 -> 36080.08 | BC22: =BC7*Assumptions!E89 -> 3141.9736 | BD22: =BD7*Assumptions!E89 -> 3141.9736 | BE22: =BE7*Assumptions!E89 -> 3141.9736 | BF22: =BF7*Assumptions!E89 -> 3141.9736 | BG22: =BG7*Assumptions!E89 -> 3141.9736 | BH22: =BH7*Assumptions!E89 -> 3141.9736 | BI22: =BI7*Assumptions!E89 -> 3141.9736 | BJ22: =BJ7*Assumptions!E89 -> 3141.9736 | BK22: =BK7*Assumptions!E89 -> 3141.9736 | BL22: =BL7*Assumptions!E89 -> 3141.9736 | BM22: =BM7*Assumptions!E89 -> 3141.9736 | BN22: =BN7*Assumptions!E89 -> 3141.9736 | BO22: =BO7*Assumptions!E89 -> 37703.683
A23: Total Operating Expenses | C23: =C14+C19+C20+C21+C22 -> 41711.846 | D23: =D14+D19+D20+D21+D22 -> 41711.846 | E23: =E14+E19+E20+E21+E22 -> 41711.846 | F23: =F14+F19+F20+F21+F22 -> 41711.846 | G23: =G14+G19+G20+G21+G22 -> 41711.846 | H23: =H14+H19+H20+H21+H22 -> 41711.846 | I23: =I14+I19+I20+I21+I22 -> 41711.846 | J23: =J14+J19+J20+J21+J22 -> 41711.846 | ... BO23: =BO14+BO19+BO20+BO21+BO22 -> 595663.19
A25: EBITDA | C25: =C10-C23 -> 15131.198 | D25: =D10-D23 -> 15131.198 | E25: =E10-E23 -> 15131.198 | F25: =F10-F23 -> 15131.198 | G25: =G10-G23 -> 15131.198 | H25: =H10-H23 -> 15131.198 | I25: =I10-I23 -> 15131.198 | J25: =J10-J23 -> 15131.198 | ... BO25: =BO10-BO23 -> 153162.62
A26: EBITDA Margin % | C26: =IFERROR(C25/C7,0) -> 0.18432196 | D26: =IFERROR(D25/D7,0) -> 0.18432196 | E26: =IFERROR(E25/E7,0) -> 0.18432196 | F26: =IFERROR(F25/F7,0) -> 0.18432196 | G26: =IFERROR(G25/G7,0) -> 0.18432196 | H26: =IFERROR(H25/H7,0) -> 0.18432196 | I26: =IFERROR(I25/I7,0) -> 0.18432196 | J26: =IFERROR(J25/J7,0) -> 0.18432196 | ... BO26: =IFERROR(BO25/BO7,0) -> 0.13037975
A27: Depreciation & Amortization | C27: =$O27/12 -> 3000 | D27: =$O27/12 -> 3000 | E27: =$O27/12 -> 3000 | F27: =$O27/12 -> 3000 | G27: =$O27/12 -> 3000 | H27: =$O27/12 -> 3000 | I27: =$O27/12 -> 3000 | J27: =$O27/12 -> 3000 | ... N27: =$O27/12 -> 3000 | O27: =Assumptions!E100 -> 36000 | P27: =$AB27/12 -> 3000 | Q27: =$AB27/12 -> 3000 | R27: =$AB27/12 -> 3000 | S27: =$AB27/12 -> 3000 | T27: =$AB27/12 -> 3000 | U27: =$AB27/12 -> 3000 | V27: =$AB27/12 -> 3000 | W27: =$AB27/12 -> 3000 | ... AA27: =$AB27/12 -> 3000 | AB27: =Assumptions!E100 -> 36000 | AC27: =$AO27/12 -> 3000 | AD27: =$AO27/12 -> 3000 | AE27: =$AO27/12 -> 3000 | AF27: =$AO27/12 -> 3000 | AG27: =$AO27/12 -> 3000 | AH27: =$AO27/12 -> 3000 | AI27: =$AO27/12 -> 3000 | AJ27: =$AO27/12 -> 3000 | ... AN27: =$AO27/12 -> 3000 | AO27: =Assumptions!E100 -> 36000 | AP27: =$BB27/12 -> 3000 | AQ27: =$BB27/12 -> 3000 | AR27: =$BB27/12 -> 3000 | AS27: =$BB27/12 -> 3000 | AT27: =$BB27/12 -> 3000 | AU27: =$BB27/12 -> 3000 | AV27: =$BB27/12 -> 3000 | AW27: =$BB27/12 -> 3000 | ... BA27: =$BB27/12 -> 3000 | BB27: =Assumptions!E100 -> 36000 | BC27: =$BO27/12 -> 3000 | BD27: =$BO27/12 -> 3000 | BE27: =$BO27/12 -> 3000 | BF27: =$BO27/12 -> 3000 | BG27: =$BO27/12 -> 3000 | BH27: =$BO27/12 -> 3000 | BI27: =$BO27/12 -> 3000 | BJ27: =$BO27/12 -> 3000 | ... BN27: =$BO27/12 -> 3000 | BO27: =Assumptions!E100 -> 36000
A28: EBIT (Operating Income) | C28: =C25-C27 -> 12131.198 | D28: =D25-D27 -> 12131.198 | E28: =E25-E27 -> 12131.198 | F28: =F25-F27 -> 12131.198 | G28: =G25-G27 -> 12131.198 | H28: =H25-H27 -> 12131.198 | I28: =I25-I27 -> 12131.198 | J28: =J25-J27 -> 12131.198 | ... BO28: =BO25-BO27 -> 117162.62
A29: EBIT Margin % | C29: =IFERROR(C28/C7,0) -> 0.1477772 | D29: =IFERROR(D28/D7,0) -> 0.1477772 | E29: =IFERROR(E28/E7,0) -> 0.1477772 | F29: =IFERROR(F28/F7,0) -> 0.1477772 | G29: =IFERROR(G28/G7,0) -> 0.1477772 | H29: =IFERROR(H28/H7,0) -> 0.1477772 | I29: =IFERROR(I28/I7,0) -> 0.1477772 | J29: =IFERROR(J28/J7,0) -> 0.1477772 | ... BO29: =IFERROR(BO28/BO7,0) -> 0.099734737
A31: Interest Expense — Senior SBA Loan | C31: =$O31/12 -> 4512.4976 | D31: =$O31/12 -> 4512.4976 | E31: =$O31/12 -> 4512.4976 | F31: =$O31/12 -> 4512.4976 | G31: =$O31/12 -> 4512.4976 | H31: =$O31/12 -> 4512.4976 | I31: =$O31/12 -> 4512.4976 | J31: =$O31/12 -> 4512.4976 | ... N31: =$O31/12 -> 4512.4976 | O31: =(Assumptions!E32)*Assumptions!E30 -> 54149.971 | P31: =$AB31/12 -> 4222.4968 | Q31: =$AB31/12 -> 4222.4968 | R31: =$AB31/12 -> 4222.4968 | S31: =$AB31/12 -> 4222.4968 | T31: =$AB31/12 -> 4222.4968 | U31: =$AB31/12 -> 4222.4968 | V31: =$AB31/12 -> 4222.4968 | W31: =$AB31/12 -> 4222.4968 | ... AA31: =$AB31/12 -> 4222.4968 | AB31: =(IFERROR(Assumptions!E32*(1+Assumptions!E30)^1-(PMT(Assumptions!E30,Assumptions!E31,-Assumptions!E32))*(((1+Assumptions!E30)^1-1)/Assumptions!E30),Assumptions!E32))*Assumptions!E30 -> 50669.961 | AC31: =$AO31/12 -> 3904.9458 | AD31: =$AO31/12 -> 3904.9458 | AE31: =$AO31/12 -> 3904.9458 | AF31: =$AO31/12 -> 3904.9458 | AG31: =$AO31/12 -> 3904.9458 | AH31: =$AO31/12 -> 3904.9458 | AI31: =$AO31/12 -> 3904.9458 | AJ31: =$AO31/12 -> 3904.9458 | ... AN31: =$AO31/12 -> 3904.9458 | AO31: =(IFERROR(Assumptions!E32*(1+Assumptions!E30)^2-(PMT(Assumptions!E30,Assumptions!E31,-Assumptions!E32))*(((1+Assumptions!E30)^2-1)/Assumptions!E30),Assumptions!E32))*Assumptions!E30 -> 46859.35 | AP31: =$BB31/12 -> 3557.2276 | AQ31: =$BB31/12 -> 3557.2276 | AR31: =$BB31/12 -> 3557.2276 | AS31: =$BB31/12 -> 3557.2276 | AT31: =$BB31/12 -> 3557.2276 | AU31: =$BB31/12 -> 3557.2276 | AV31: =$BB31/12 -> 3557.2276 | AW31: =$BB31/12 -> 3557.2276 | ... BA31: =$BB31/12 -> 3557.2276 | BB31: =(IFERROR(Assumptions!E32*(1+Assumptions!E30)^3-(PMT(Assumptions!E30,Assumptions!E31,-Assumptions!E32))*(((1+Assumptions!E30)^3-1)/Assumptions!E30),Assumptions!E32))*Assumptions!E30 -> 42686.731 | BC31: =$BO31/12 -> 3176.476 | BD31: =$BO31/12 -> 3176.476 | BE31: =$BO31/12 -> 3176.476 | BF31: =$BO31/12 -> 3176.476 | BG31: =$BO31/12 -> 3176.476 | BH31: =$BO31/12 -> 3176.476 | BI31: =$BO31/12 -> 3176.476 | BJ31: =$BO31/12 -> 3176.476 | ... BN31: =$BO31/12 -> 3176.476 | BO31: =(IFERROR(Assumptions!E32*(1+Assumptions!E30)^4-(PMT(Assumptions!E30,Assumptions!E31,-Assumptions!E32))*(((1+Assumptions!E30)^4-1)/Assumptions!E30),Assumptions!E32))*Assumptions!E30 -> 38117.712
A32: Interest Expense — Seller Note | C32: =$O32/12 -> 0 | D32: =$O32/12 -> 0 | E32: =$O32/12 -> 0 | F32: =$O32/12 -> 0 | G32: =$O32/12 -> 0 | H32: =$O32/12 -> 0 | I32: =$O32/12 -> 0 | J32: =$O32/12 -> 0 | ... N32: =$O32/12 -> 0 | O32: =(Assumptions!E17)*Assumptions!E18 -> 0 | P32: =$AB32/12 -> 0 | Q32: =$AB32/12 -> 0 | R32: =$AB32/12 -> 0 | S32: =$AB32/12 -> 0 | T32: =$AB32/12 -> 0 | U32: =$AB32/12 -> 0 | V32: =$AB32/12 -> 0 | W32: =$AB32/12 -> 0 | ... AA32: =$AB32/12 -> 0 | AB32: =(IFERROR(Assumptions!E17*(1+Assumptions!E18)^1-(PMT(Assumptions!E18,Assumptions!E19,-Assumptions!E17))*(((1+Assumptions!E18)^1-1)/Assumptions!E18),Assumptions!E17))*Assumptions!E18 -> 0 | AC32: =$AO32/12 -> 0 | AD32: =$AO32/12 -> 0 | AE32: =$AO32/12 -> 0 | AF32: =$AO32/12 -> 0 | AG32: =$AO32/12 -> 0 | AH32: =$AO32/12 -> 0 | AI32: =$AO32/12 -> 0 | AJ32: =$AO32/12 -> 0 | ... AN32: =$AO32/12 -> 0 | AO32: =(IFERROR(Assumptions!E17*(1+Assumptions!E18)^2-(PMT(Assumptions!E18,Assumptions!E19,-Assumptions!E17))*(((1+Assumptions!E18)^2-1)/Assumptions!E18),Assumptions!E17))*Assumptions!E18 -> 0 | AP32: =$BB32/12 -> 0 | AQ32: =$BB32/12 -> 0 | AR32: =$BB32/12 -> 0 | AS32: =$BB32/12 -> 0 | AT32: =$BB32/12 -> 0 | AU32: =$BB32/12 -> 0 | AV32: =$BB32/12 -> 0 | AW32: =$BB32/12 -> 0 | ... BA32: =$BB32/12 -> 0 | BB32: =(IFERROR(Assumptions!E17*(1+Assumptions!E18)^3-(PMT(Assumptions!E18,Assumptions!E19,-Assumptions!E17))*(((1+Assumptions!E18)^3-1)/Assumptions!E18),Assumptions!E17))*Assumptions!E18 -> 0 | BC32: =$BO32/12 -> 0 | BD32: =$BO32/12 -> 0 | BE32: =$BO32/12 -> 0 | BF32: =$BO32/12 -> 0 | BG32: =$BO32/12 -> 0 | BH32: =$BO32/12 -> 0 | BI32: =$BO32/12 -> 0 | BJ32: =$BO32/12 -> 0 | ... BN32: =$BO32/12 -> 0 | BO32: =(IFERROR(Assumptions!E17*(1+Assumptions!E18)^4-(PMT(Assumptions!E18,Assumptions!E19,-Assumptions!E17))*(((1+Assumptions!E18)^4-1)/Assumptions!E18),Assumptions!E17))*Assumptions!E18 -> 0
A33: Total Interest Expense | C33: =C31+C32 -> 4512.4976 | D33: =D31+D32 -> 4512.4976 | E33: =E31+E32 -> 4512.4976 | F33: =F31+F32 -> 4512.4976 | G33: =G31+G32 -> 4512.4976 | H33: =H31+H32 -> 4512.4976 | I33: =I31+I32 -> 4512.4976 | J33: =J31+J32 -> 4512.4976 | ... BO33: =BO31+BO32 -> 38117.712
A34: Pretax Income | C34: =C28-C33 -> 7618.7 | D34: =D28-D33 -> 7618.7 | E34: =E28-E33 -> 7618.7 | F34: =F28-F33 -> 7618.7 | G34: =G28-G33 -> 7618.7 | H34: =H28-H33 -> 7618.7 | I34: =I28-I33 -> 7618.7 | J34: =J28-J33 -> 7618.7 | ... BO34: =BO28-BO33 -> 79044.911
A35: Entity-Level Income Tax (Pass-Through LLC) | C35: =0 -> 0 | D35: =0 -> 0 | E35: =0 -> 0 | F35: =0 -> 0 | G35: =0 -> 0 | H35: =0 -> 0 | I35: =0 -> 0 | J35: =0 -> 0 | ... BO35: =0 -> 0
A36: Net Income (Pass-Through to Owner) | C36: =C34-C35 -> 7618.7 | D36: =D34-D35 -> 7618.7 | E36: =E34-E35 -> 7618.7 | F36: =F34-F35 -> 7618.7 | G36: =G34-G35 -> 7618.7 | H36: =H34-H35 -> 7618.7 | I36: =I34-I35 -> 7618.7 | J36: =J34-J35 -> 7618.7 | ... BO36: =BO34-BO35 -> 79044.911
A37: Net Margin % | C37: =IFERROR(C36/C7,0) -> 0.092807835 | D37: =IFERROR(D36/D7,0) -> 0.092807835 | E37: =IFERROR(E36/E7,0) -> 0.092807835 | F37: =IFERROR(F36/F7,0) -> 0.092807835 | G37: =IFERROR(G36/G7,0) -> 0.092807835 | H37: =IFERROR(H36/H7,0) -> 0.092807835 | I37: =IFERROR(I36/I7,0) -> 0.092807835 | J37: =IFERROR(J36/J7,0) -> 0.092807835 | ... BO37: =IFERROR(BO36/BO7,0) -> 0.067287017
A39: Memo: Owner Tax Distribution (Assumed) | C39: =$O39/12 -> 1142.805 | D39: =$O39/12 -> 1142.805 | E39: =$O39/12 -> 1142.805 | F39: =$O39/12 -> 1142.805 | G39: =$O39/12 -> 1142.805 | H39: =$O39/12 -> 1142.805 | I39: =$O39/12 -> 1142.805 | J39: =$O39/12 -> 1142.805 | ... N39: =$O39/12 -> 1142.805 | O39: =MAX(0,O36)*Assumptions!E110 -> 13713.66 | P39: =$AB39/12 -> 588.03174 | Q39: =$AB39/12 -> 588.03174 | R39: =$AB39/12 -> 588.03174 | S39: =$AB39/12 -> 588.03174 | T39: =$AB39/12 -> 588.03174 | U39: =$AB39/12 -> 588.03174 | V39: =$AB39/12 -> 588.03174 | W39: =$AB39/12 -> 588.03174 | ... AA39: =$AB39/12 -> 588.03174 | AB39: =MAX(0,AB36)*Assumptions!E110 -> 7056.3809 | AC39: =$AO39/12 -> 715.86948 | AD39: =$AO39/12 -> 715.86948 | AE39: =$AO39/12 -> 715.86948 | AF39: =$AO39/12 -> 715.86948 | AG39: =$AO39/12 -> 715.86948 | AH39: =$AO39/12 -> 715.86948 | AI39: =$AO39/12 -> 715.86948 | AJ39: =$AO39/12 -> 715.86948 | ... AN39: =$AO39/12 -> 715.86948 | AO39: =MAX(0,AO36)*Assumptions!E110 -> 8590.4338 | AP39: =$BB39/12 -> 849.17917 | AQ39: =$BB39/12 -> 849.17917 | AR39: =$BB39/12 -> 849.17917 | AS39: =$BB39/12 -> 849.17917 | AT39: =$BB39/12 -> 849.17917 | AU39: =$BB39/12 -> 849.17917 | AV39: =$BB39/12 -> 849.17917 | AW39: =$BB39/12 -> 849.17917 | ... BA39: =$BB39/12 -> 849.17917 | BB39: =MAX(0,BB36)*Assumptions!E110 -> 10190.15 | BC39: =$BO39/12 -> 988.06139 | BD39: =$BO39/12 -> 988.06139 | BE39: =$BO39/12 -> 988.06139 | BF39: =$BO39/12 -> 988.06139 | BG39: =$BO39/12 -> 988.06139 | BH39: =$BO39/12 -> 988.06139 | BI39: =$BO39/12 -> 988.06139 | BJ39: =$BO39/12 -> 988.06139 | ... BN39: =$BO39/12 -> 988.06139 | BO39: =MAX(0,BO36)*Assumptions!E110 -> 11856.737
A40: Memo: Net Income Retained in Business | C40: =C36-C39 -> 6475.895 | D40: =D36-D39 -> 6475.895 | E40: =E36-E39 -> 6475.895 | F40: =F36-F39 -> 6475.895 | G40: =G36-G39 -> 6475.895 | H40: =H36-H39 -> 6475.895 | I40: =I36-I39 -> 6475.895 | J40: =J36-J39 -> 6475.895 | ... BO40: =BO36-BO39 -> 67188.175
A43: BALANCE SHEET
B44: At Close | C44: M1 | D44: M2 | E44: M3 | F44: M4 | G44: M5 | H44: M6 | I44: M7 | J44: M8 | K44: M9 | L44: M10 | M44: M11 | N44: M12 | O44: Year 1 | P44: M1 | Q44: M2 | R44: M3 | S44: M4 | T44: M5 | U44: M6 | V44: M7 | W44: M8 | X44: M9 | Y44: M10 | Z44: M11 | AA44: M12 | AB44: Year 2 | AC44: M1 | AD44: M2 | AE44: M3 | AF44: M4 | AG44: M5 | AH44: M6 | AI44: M7 | AJ44: M8 | AK44: M9 | AL44: M10 | AM44: M11 | AN44: M12 | AO44: Year 3 | AP44: M1 | AQ44: M2 | AR44: M3 | AS44: M4 | AT44: M5 | AU44: M6 | AV44: M7 | AW44: M8 | AX44: M9 | AY44: M10 | AZ44: M11 | BA44: M12 | BB44: Year 4 | BC44: M1 | BD44: M2 | BE44: M3 | BF44: M4 | BG44: M5 | BH44: M6 | BI44: M7 | BJ44: M8 | BK44: M9 | BL44: M10 | BM44: M11 | BN44: M12 | BO44: Year 5
A45: Assets
A46: Cash | B46: =Assumptions!E12 -> 29999.7 | C46: =$B46+($O46-$B46)*1/12 -> 36833.41 | D46: =$B46+($O46-$B46)*2/12 -> 43667.12 | E46: =$B46+($O46-$B46)*3/12 -> 50500.83 | F46: =$B46+($O46-$B46)*4/12 -> 57334.54 | G46: =$B46+($O46-$B46)*5/12 -> 64168.25 | H46: =$B46+($O46-$B46)*6/12 -> 71001.96 | I46: =$B46+($O46-$B46)*7/12 -> 77835.67 | J46: =$B46+($O46-$B46)*8/12 -> 84669.38 | K46: =$B46+($O46-$B46)*9/12 -> 91503.09 | L46: =$B46+($O46-$B46)*10/12 -> 98336.801 | M46: =$B46+($O46-$B46)*11/12 -> 105170.51 | N46: =$B46+($O46-$B46)*12/12 -> 112004.22 | O46: =B46+O36+O27-((O7*Assumptions!E104)-(0))-((Assumptions!E32)-(IFERROR(Assumptions!E32*(1+Assumptions!E30)^1-(PMT(Assumptions!E30,Assumptions!E31,-Assumptions!E32))*(((1+Assumptions!E30)^1-1)/Assumptions!E30),Assumptions!E32)))-((Assumptions!E17)-(IFERROR(Assumptions!E17*(1+Assumptions!E18)^1-(PMT(Assumptions!E18,Assumptions!E19,-Assumptions!E17))*(((1+Assumptions!E18)^1-1)/Assumptions!E18),Assumptions!E17)))-O39 -> 112004.22 | P46: =$O46+($AB46-$O46)*1/12 -> 115012.23 | Q46: =$O46+($AB46-$O46)*2/12 -> 118020.24 | R46: =$O46+($AB46-$O46)*3/12 -> 121028.25 | S46: =$O46+($AB46-$O46)*4/12 -> 124036.26 | T46: =$O46+($AB46-$O46)*5/12 -> 127044.27 | U46: =$O46+($AB46-$O46)*6/12 -> 130052.27 | V46: =$O46+($AB46-$O46)*7/12 -> 133060.28 | W46: =$O46+($AB46-$O46)*8/12 -> 136068.29 | X46: =$O46+($AB46-$O46)*9/12 -> 139076.3 | Y46: =$O46+($AB46-$O46)*10/12 -> 142084.31 | Z46: =$O46+($AB46-$O46)*11/12 -> 145092.32 | AA46: =$O46+($AB46-$O46)*12/12 -> 148100.33 | AB46: =O46+AB36+AB27-((AB7*Assumptions!E104)-(O7*Assumptions!E104))-((IFERROR(Assumptions!E32*(1+Assumptions!E30)^1-(PMT(Assumptions!E30,Assumptions!E31,-Assumptions!E32))*(((1+Assumptions!E30)^1-1)/Assumptions!E30),Assumptions!E32))-(IFERROR(Assumptions!E32*(1+Assumptions!E30)^2-(PMT(Assumptions!E30,Assumptions!E31,-Assumptions!E32))*(((1+Assumptions!E30)^2-1)/Assumptions!E30),Assumptions!E32)))-((IFERROR(Assumptions!E17*(1+Assumptions!E18)^1-(PMT(Assumptions!E18,Assumptions!E19,-Assumptions!E17))*(((1+Assumptions!E18)^1-1)/Assumptions!E18),Assumptions!E17))-(IFERROR(Assumptions!E17*(1+Assumptions!E18)^2-(PMT(Assumptions!E18,Assumptions!E19,-Assumptions!E17))*(((1+Assumptions!E18)^2-1)/Assumptions!E18),Assumptions!E17)))-AB39 -> 148100.33 | AC46: =$AB46+($AO46-$AB46)*1/12 -> 151516.03 | AD46: =$AB46+($AO46-$AB46)*2/12 -> 154931.73 | AE46: =$AB46+($AO46-$AB46)*3/12 -> 158347.44 | AF46: =$AB46+($AO46-$AB46)*4/12 -> 161763.14 | AG46: =$AB46+($AO46-$AB46)*5/12 -> 165178.84 | AH46: =$AB46+($AO46-$AB46)*6/12 -> 168594.55 | AI46: =$AB46+($AO46-$AB46)*7/12 -> 172010.25 | AJ46: =$AB46+($AO46-$AB46)*8/12 -> 175425.95 | AK46: =$AB46+($AO46-$AB46)*9/12 -> 178841.65 | AL46: =$AB46+($AO46-$AB46)*10/12 -> 182257.36 | AM46: =$AB46+($AO46-$AB46)*11/12 -> 185673.06 | AN46: =$AB46+($AO46-$AB46)*12/12 -> 189088.76 | AO46: =AB46+AO36+AO27-((AO7*Assumptions!E104)-(AB7*Assumptions!E104))-((IFERROR(Assumptions!E32*(1+Assumptions!E30)^2-(PMT(Assumptions!E30,Assumptions!E31,-Assumptions!E32))*(((1+Assumptions!E30)^2-1)/Assumptions!E30),Assumptions!E32))-(IFERROR(Assumptions!E32*(1+Assumptions!E30)^3-(PMT(Assumptions!E30,Assumptions!E31,-Assumptions!E32))*(((1+Assumptions!E30)^3-1)/Assumptions!E30),Assumptions!E32)))-((IFERROR(Assumptions!E17*(1+Assumptions!E18)^2-(PMT(Assumptions!E18,Assumptions!E19,-Assumptions!E17))*(((1+Assumptions!E18)^2-1)/Assumptions!E18),Assumptions!E17))-(IFERROR(Assumptions!E17*(1+Assumptions!E18)^3-(PMT(Assumptions!E18,Assumptions!E19,-Assumptions!E17))*(((1+Assumptions!E18)^3-1)/Assumptions!E18),Assumptions!E17)))-AO39 -> 189088.76 | AP46: =$AO46+($BB46-$AO46)*1/12 -> 192913.04 | AQ46: =$AO46+($BB46-$AO46)*2/12 -> 196737.31 | AR46: =$AO46+($BB46-$AO46)*3/12 -> 200561.59 | AS46: =$AO46+($BB46-$AO46)*4/12 -> 204385.86 | AT46: =$AO46+($BB46-$AO46)*5/12 -> 208210.14 | AU46: =$AO46+($BB46-$AO46)*6/12 -> 212034.41 | AV46: =$AO46+($BB46-$AO46)*7/12 -> 215858.69 | AW46: =$AO46+($BB46-$AO46)*8/12 -> 219682.96 | AX46: =$AO46+($BB46-$AO46)*9/12 -> 223507.24 | AY46: =$AO46+($BB46-$AO46)*10/12 -> 227331.51 | AZ46: =$AO46+($BB46-$AO46)*11/12 -> 231155.79 | BA46: =$AO46+($BB46-$AO46)*12/12 -> 234980.06 | BB46: =AO46+BB36+BB27-((BB7*Assumptions!E104)-(AO7*Assumptions!E104))-((IFERROR(Assumptions!E32*(1+Assumptions!E30)^3-(PMT(Assumptions!E30,Assumptions!E31,-Assumptions!E32))*(((1+Assumptions!E30)^3-1)/Assumptions!E30),Assumptions!E32))-(IFERROR(Assumptions!E32*(1+Assumptions!E30)^4-(PMT(Assumptions!E30,Assumptions!E31,-Assumptions!E32))*(((1+Assumptions!E30)^4-1)/Assumptions!E30),Assumptions!E32)))-((IFERROR(Assumptions!E17*(1+Assumptions!E18)^3-(PMT(Assumptions!E18,Assumptions!E19,-Assumptions!E17))*(((1+Assumptions!E18)^3-1)/Assumptions!E18),Assumptions!E17))-(IFERROR(Assumptions!E17*(1+Assumptions!E18)^4-(PMT(Assumptions!E18,Assumptions!E19,-Assumptions!E17))*(((1+Assumptions!E18)^4-1)/Assumptions!E18),Assumptions!E17)))-BB39 -> 234980.06 | BC46: =$BB46+($BO46-$BB46)*1/12 -> 239211.49 | BD46: =$BB46+($BO46-$BB46)*2/12 -> 243442.92 | BE46: =$BB46+($BO46-$BB46)*3/12 -> 247674.35 | BF46: =$BB46+($BO46-$BB46)*4/12 -> 251905.78 | BG46: =$BB46+($BO46-$BB46)*5/12 -> 256137.21 | BH46: =$BB46+($BO46-$BB46)*6/12 -> 260368.64 | BI46: =$BB46+($BO46-$BB46)*7/12 -> 264600.07 | BJ46: =$BB46+($BO46-$BB46)*8/12 -> 268831.5 | BK46: =$BB46+($BO46-$BB46)*9/12 -> 273062.93 | BL46: =$BB46+($BO46-$BB46)*10/12 -> 277294.36 | BM46: =$BB46+($BO46-$BB46)*11/12 -> 281525.8 | BN46: =$BB46+($BO46-$BB46)*12/12 -> 285757.23 | BO46: =BB46+BO36+BO27-((BO7*Assumptions!E104)-(BB7*Assumptions!E104))-((IFERROR(Assumptions!E32*(1+Assumptions!E30)^4-(PMT(Assumptions!E30,Assumptions!E31,-Assumptions!E32))*(((1+Assumptions!E30)^4-1)/Assumptions!E30),Assumptions!E32))-(IFERROR(Assumptions!E32*(1+Assumptions!E30)^5-(PMT(Assumptions!E30,Assumptions!E31,-Assumptions!E32))*(((1+Assumptions!E30)^5-1)/Assumptions!E30),Assumptions!E32)))-((IFERROR(Assumptions!E17*(1+Assumptions!E18)^4-(PMT(Assumptions!E18,Assumptions!E19,-Assumptions!E17))*(((1+Assumptions!E18)^4-1)/Assumptions!E18),Assumptions!E17))-(IFERROR(Assumptions!E17*(1+Assumptions!E18)^5-(PMT(Assumptions!E18,Assumptions!E19,-Assumptions!E17))*(((1+Assumptions!E18)^5-1)/Assumptions!E18),Assumptions!E17)))-BO39 -> 285757.23
A47: Net Working Capital (Ex-Cash) | B47: =0 -> 0 | C47: =$B47+($O47-$B47)*1/12 -> -410.45565 | D47: =$B47+($O47-$B47)*2/12 -> -820.9113 | E47: =$B47+($O47-$B47)*3/12 -> -1231.3669 | F47: =$B47+($O47-$B47)*4/12 -> -1641.8226 | G47: =$B47+($O47-$B47)*5/12 -> -2052.2782 | H47: =$B47+($O47-$B47)*6/12 -> -2462.7339 | I47: =$B47+($O47-$B47)*7/12 -> -2873.1895 | J47: =$B47+($O47-$B47)*8/12 -> -3283.6452 | K47: =$B47+($O47-$B47)*9/12 -> -3694.1008 | L47: =$B47+($O47-$B47)*10/12 -> -4104.5565 | M47: =$B47+($O47-$B47)*11/12 -> -4515.0121 | N47: =$B47+($O47-$B47)*12/12 -> -4925.4678 | O47: =O7*Assumptions!E104 -> -4925.4678 | P47: =$O47+($AB47-$O47)*1/12 -> -4943.9383 | Q47: =$O47+($AB47-$O47)*2/12 -> -4962.4088 | R47: =$O47+($AB47-$O47)*3/12 -> -4980.8793 | S47: =$O47+($AB47-$O47)*4/12 -> -4999.3498 | T47: =$O47+($AB47-$O47)*5/12 -> -5017.8203 | U47: =$O47+($AB47-$O47)*6/12 -> -5036.2908 | V47: =$O47+($AB47-$O47)*7/12 -> -5054.7613 | W47: =$O47+($AB47-$O47)*8/12 -> -5073.2318 | X47: =$O47+($AB47-$O47)*9/12 -> -5091.7023 | Y47: =$O47+($AB47-$O47)*10/12 -> -5110.1728 | Z47: =$O47+($AB47-$O47)*11/12 -> -5128.6433 | AA47: =$O47+($AB47-$O47)*12/12 -> -5147.1138 | AB47: =AB7*Assumptions!E104 -> -5147.1138 | AC47: =$AB47+($AO47-$AB47)*1/12 -> -5166.4155 | AD47: =$AB47+($AO47-$AB47)*2/12 -> -5185.7172 | AE47: =$AB47+($AO47-$AB47)*3/12 -> -5205.0189 | AF47: =$AB47+($AO47-$AB47)*4/12 -> -5224.3205 | AG47: =$AB47+($AO47-$AB47)*5/12 -> -5243.6222 | AH47: =$AB47+($AO47-$AB47)*6/12 -> -5262.9239 | AI47: =$AB47+($AO47-$AB47)*7/12 -> -5282.2256 | AJ47: =$AB47+($AO47-$AB47)*8/12 -> -5301.5272 | AK47: =$AB47+($AO47-$AB47)*9/12 -> -5320.8289 | AL47: =$AB47+($AO47-$AB47)*10/12 -> -5340.1306 | AM47: =$AB47+($AO47-$AB47)*11/12 -> -5359.4323 | AN47: =$AB47+($AO47-$AB47)*12/12 -> -5378.734 | AO47: =AO7*Assumptions!E104 -> -5378.734 | AP47: =$AO47+($BB47-$AO47)*1/12 -> -5398.9042 | AQ47: =$AO47+($BB47-$AO47)*2/12 -> -5419.0745 | AR47: =$AO47+($BB47-$AO47)*3/12 -> -5439.2447 | AS47: =$AO47+($BB47-$AO47)*4/12 -> -5459.415 | AT47: =$AO47+($BB47-$AO47)*5/12 -> -5479.5852 | AU47: =$AO47+($BB47-$AO47)*6/12 -> -5499.7555 | AV47: =$AO47+($BB47-$AO47)*7/12 -> -5519.9257 | AW47: =$AO47+($BB47-$AO47)*8/12 -> -5540.096 | AX47: =$AO47+($BB47-$AO47)*9/12 -> -5560.2662 | AY47: =$AO47+($BB47-$AO47)*10/12 -> -5580.4365 | AZ47: =$AO47+($BB47-$AO47)*11/12 -> -5600.6067 | BA47: =$AO47+($BB47-$AO47)*12/12 -> -5620.777 | BB47: =BB7*Assumptions!E104 -> -5620.777 | BC47: =$BB47+($BO47-$BB47)*1/12 -> -5641.8549 | BD47: =$BB47+($BO47-$BB47)*2/12 -> -5662.9328 | BE47: =$BB47+($BO47-$BB47)*3/12 -> -5684.0107 | BF47: =$BB47+($BO47-$BB47)*4/12 -> -5705.0886 | BG47: =$BB47+($BO47-$BB47)*5/12 -> -5726.1666 | BH47: =$BB47+($BO47-$BB47)*6/12 -> -5747.2445 | BI47: =$BB47+($BO47-$BB47)*7/12 -> -5768.3224 | BJ47: =$BB47+($BO47-$BB47)*8/12 -> -5789.4003 | BK47: =$BB47+($BO47-$BB47)*9/12 -> -5810.4782 | BL47: =$BB47+($BO47-$BB47)*10/12 -> -5831.5561 | BM47: =$BB47+($BO47-$BB47)*11/12 -> -5852.634 | BN47: =$BB47+($BO47-$BB47)*12/12 -> -5873.7119 | BO47: =BO7*Assumptions!E104 -> -5873.7119
A48: Total Current Assets | B48: =B46+B47 -> 29999.7 | C48: =C46+C47 -> 36422.954 | D48: =D46+D47 -> 42846.209 | E48: =E46+E47 -> 49269.463 | F48: =F46+F47 -> 55692.718 | G48: =G46+G47 -> 62115.972 | H48: =H46+H47 -> 68539.226 | I48: =I46+I47 -> 74962.481 | ... BO48: =BO46+BO47 -> 279883.51
A49: Fixed Assets, Net | B49: =Assumptions!E94 -> 0 | C49: =$B49+($O49-$B49)*1/12 -> 0 | D49: =$B49+($O49-$B49)*2/12 -> 0 | E49: =$B49+($O49-$B49)*3/12 -> 0 | F49: =$B49+($O49-$B49)*4/12 -> 0 | G49: =$B49+($O49-$B49)*5/12 -> 0 | H49: =$B49+($O49-$B49)*6/12 -> 0 | I49: =$B49+($O49-$B49)*7/12 -> 0 | J49: =$B49+($O49-$B49)*8/12 -> 0 | K49: =$B49+($O49-$B49)*9/12 -> 0 | L49: =$B49+($O49-$B49)*10/12 -> 0 | M49: =$B49+($O49-$B49)*11/12 -> 0 | N49: =$B49+($O49-$B49)*12/12 -> 0 | O49: =MAX(0,Assumptions!E94-Assumptions!E99*1) -> 0 | P49: =$O49+($AB49-$O49)*1/12 -> 0 | Q49: =$O49+($AB49-$O49)*2/12 -> 0 | R49: =$O49+($AB49-$O49)*3/12 -> 0 | S49: =$O49+($AB49-$O49)*4/12 -> 0 | T49: =$O49+($AB49-$O49)*5/12 -> 0 | U49: =$O49+($AB49-$O49)*6/12 -> 0 | V49: =$O49+($AB49-$O49)*7/12 -> 0 | W49: =$O49+($AB49-$O49)*8/12 -> 0 | X49: =$O49+($AB49-$O49)*9/12 -> 0 | Y49: =$O49+($AB49-$O49)*10/12 -> 0 | Z49: =$O49+($AB49-$O49)*11/12 -> 0 | AA49: =$O49+($AB49-$O49)*12/12 -> 0 | AB49: =MAX(0,Assumptions!E94-Assumptions!E99*2) -> 0 | AC49: =$AB49+($AO49-$AB49)*1/12 -> 0 | AD49: =$AB49+($AO49-$AB49)*2/12 -> 0 | AE49: =$AB49+($AO49-$AB49)*3/12 -> 0 | AF49: =$AB49+($AO49-$AB49)*4/12 -> 0 | AG49: =$AB49+($AO49-$AB49)*5/12 -> 0 | AH49: =$AB49+($AO49-$AB49)*6/12 -> 0 | AI49: =$AB49+($AO49-$AB49)*7/12 -> 0 | AJ49: =$AB49+($AO49-$AB49)*8/12 -> 0 | AK49: =$AB49+($AO49-$AB49)*9/12 -> 0 | AL49: =$AB49+($AO49-$AB49)*10/12 -> 0 | AM49: =$AB49+($AO49-$AB49)*11/12 -> 0 | AN49: =$AB49+($AO49-$AB49)*12/12 -> 0 | AO49: =MAX(0,Assumptions!E94-Assumptions!E99*3) -> 0 | AP49: =$AO49+($BB49-$AO49)*1/12 -> 0 | AQ49: =$AO49+($BB49-$AO49)*2/12 -> 0 | AR49: =$AO49+($BB49-$AO49)*3/12 -> 0 | AS49: =$AO49+($BB49-$AO49)*4/12 -> 0 | AT49: =$AO49+($BB49-$AO49)*5/12 -> 0 | AU49: =$AO49+($BB49-$AO49)*6/12 -> 0 | AV49: =$AO49+($BB49-$AO49)*7/12 -> 0 | AW49: =$AO49+($BB49-$AO49)*8/12 -> 0 | AX49: =$AO49+($BB49-$AO49)*9/12 -> 0 | AY49: =$AO49+($BB49-$AO49)*10/12 -> 0 | AZ49: =$AO49+($BB49-$AO49)*11/12 -> 0 | BA49: =$AO49+($BB49-$AO49)*12/12 -> 0 | BB49: =MAX(0,Assumptions!E94-Assumptions!E99*4) -> 0 | BC49: =$BB49+($BO49-$BB49)*1/12 -> 0 | BD49: =$BB49+($BO49-$BB49)*2/12 -> 0 | BE49: =$BB49+($BO49-$BB49)*3/12 -> 0 | BF49: =$BB49+($BO49-$BB49)*4/12 -> 0 | BG49: =$BB49+($BO49-$BB49)*5/12 -> 0 | BH49: =$BB49+($BO49-$BB49)*6/12 -> 0 | BI49: =$BB49+($BO49-$BB49)*7/12 -> 0 | BJ49: =$BB49+($BO49-$BB49)*8/12 -> 0 | BK49: =$BB49+($BO49-$BB49)*9/12 -> 0 | BL49: =$BB49+($BO49-$BB49)*10/12 -> 0 | BM49: =$BB49+($BO49-$BB49)*11/12 -> 0 | BN49: =$BB49+($BO49-$BB49)*12/12 -> 0 | BO49: =MAX(0,Assumptions!E94-Assumptions!E99*5) -> 0
A50: Goodwill / Intangibles, Net | B50: =Assumptions!E95 -> 540000 | C50: =$B50+($O50-$B50)*1/12 -> 537000 | D50: =$B50+($O50-$B50)*2/12 -> 534000 | E50: =$B50+($O50-$B50)*3/12 -> 531000 | F50: =$B50+($O50-$B50)*4/12 -> 528000 | G50: =$B50+($O50-$B50)*5/12 -> 525000 | H50: =$B50+($O50-$B50)*6/12 -> 522000 | I50: =$B50+($O50-$B50)*7/12 -> 519000 | J50: =$B50+($O50-$B50)*8/12 -> 516000 | K50: =$B50+($O50-$B50)*9/12 -> 513000 | L50: =$B50+($O50-$B50)*10/12 -> 510000 | M50: =$B50+($O50-$B50)*11/12 -> 507000 | N50: =$B50+($O50-$B50)*12/12 -> 504000 | O50: =MAX(0,Assumptions!E95-Assumptions!E97*1) -> 504000 | P50: =$O50+($AB50-$O50)*1/12 -> 501000 | Q50: =$O50+($AB50-$O50)*2/12 -> 498000 | R50: =$O50+($AB50-$O50)*3/12 -> 495000 | S50: =$O50+($AB50-$O50)*4/12 -> 492000 | T50: =$O50+($AB50-$O50)*5/12 -> 489000 | U50: =$O50+($AB50-$O50)*6/12 -> 486000 | V50: =$O50+($AB50-$O50)*7/12 -> 483000 | W50: =$O50+($AB50-$O50)*8/12 -> 480000 | X50: =$O50+($AB50-$O50)*9/12 -> 477000 | Y50: =$O50+($AB50-$O50)*10/12 -> 474000 | Z50: =$O50+($AB50-$O50)*11/12 -> 471000 | AA50: =$O50+($AB50-$O50)*12/12 -> 468000 | AB50: =MAX(0,Assumptions!E95-Assumptions!E97*2) -> 468000 | AC50: =$AB50+($AO50-$AB50)*1/12 -> 465000 | AD50: =$AB50+($AO50-$AB50)*2/12 -> 462000 | AE50: =$AB50+($AO50-$AB50)*3/12 -> 459000 | AF50: =$AB50+($AO50-$AB50)*4/12 -> 456000 | AG50: =$AB50+($AO50-$AB50)*5/12 -> 453000 | AH50: =$AB50+($AO50-$AB50)*6/12 -> 450000 | AI50: =$AB50+($AO50-$AB50)*7/12 -> 447000 | AJ50: =$AB50+($AO50-$AB50)*8/12 -> 444000 | AK50: =$AB50+($AO50-$AB50)*9/12 -> 441000 | AL50: =$AB50+($AO50-$AB50)*10/12 -> 438000 | AM50: =$AB50+($AO50-$AB50)*11/12 -> 435000 | AN50: =$AB50+($AO50-$AB50)*12/12 -> 432000 | AO50: =MAX(0,Assumptions!E95-Assumptions!E97*3) -> 432000 | AP50: =$AO50+($BB50-$AO50)*1/12 -> 429000 | AQ50: =$AO50+($BB50-$AO50)*2/12 -> 426000 | AR50: =$AO50+($BB50-$AO50)*3/12 -> 423000 | AS50: =$AO50+($BB50-$AO50)*4/12 -> 420000 | AT50: =$AO50+($BB50-$AO50)*5/12 -> 417000 | AU50: =$AO50+($BB50-$AO50)*6/12 -> 414000 | AV50: =$AO50+($BB50-$AO50)*7/12 -> 411000 | AW50: =$AO50+($BB50-$AO50)*8/12 -> 408000 | AX50: =$AO50+($BB50-$AO50)*9/12 -> 405000 | AY50: =$AO50+($BB50-$AO50)*10/12 -> 402000 | AZ50: =$AO50+($BB50-$AO50)*11/12 -> 399000 | BA50: =$AO50+($BB50-$AO50)*12/12 -> 396000 | BB50: =MAX(0,Assumptions!E95-Assumptions!E97*4) -> 396000 | BC50: =$BB50+($BO50-$BB50)*1/12 -> 393000 | BD50: =$BB50+($BO50-$BB50)*2/12 -> 390000 | BE50: =$BB50+($BO50-$BB50)*3/12 -> 387000 | BF50: =$BB50+($BO50-$BB50)*4/12 -> 384000 | BG50: =$BB50+($BO50-$BB50)*5/12 -> 381000 | BH50: =$BB50+($BO50-$BB50)*6/12 -> 378000 | BI50: =$BB50+($BO50-$BB50)*7/12 -> 375000 | BJ50: =$BB50+($BO50-$BB50)*8/12 -> 372000 | BK50: =$BB50+($BO50-$BB50)*9/12 -> 369000 | BL50: =$BB50+($BO50-$BB50)*10/12 -> 366000 | BM50: =$BB50+($BO50-$BB50)*11/12 -> 363000 | BN50: =$BB50+($BO50-$BB50)*12/12 -> 360000 | BO50: =MAX(0,Assumptions!E95-Assumptions!E97*5) -> 360000
A51: TOTAL ASSETS | B51: =B48+B49+B50 -> 569999.7 | C51: =C48+C49+C50 -> 573422.95 | D51: =D48+D49+D50 -> 576846.21 | E51: =E48+E49+E50 -> 580269.46 | F51: =F48+F49+F50 -> 583692.72 | G51: =G48+G49+G50 -> 587115.97 | H51: =H48+H49+H50 -> 590539.23 | I51: =I48+I49+I50 -> 593962.48 | ... BO51: =BO48+BO49+BO50 -> 639883.51
A53: Liabilities
A54: Senior SBA Term Loan Payable | B54: =Assumptions!E32 -> 569999.7 | C54: =$B54+($O54-$B54)*1/12 -> 566947.06 | D54: =$B54+($O54-$B54)*2/12 -> 563894.42 | E54: =$B54+($O54-$B54)*3/12 -> 560841.78 | F54: =$B54+($O54-$B54)*4/12 -> 557789.14 | G54: =$B54+($O54-$B54)*5/12 -> 554736.5 | H54: =$B54+($O54-$B54)*6/12 -> 551683.86 | I54: =$B54+($O54-$B54)*7/12 -> 548631.22 | J54: =$B54+($O54-$B54)*8/12 -> 545578.58 | K54: =$B54+($O54-$B54)*9/12 -> 542525.93 | L54: =$B54+($O54-$B54)*10/12 -> 539473.29 | M54: =$B54+($O54-$B54)*11/12 -> 536420.65 | N54: =$B54+($O54-$B54)*12/12 -> 533368.01 | O54: =IFERROR(Assumptions!E32*(1+Assumptions!E30)^1-(PMT(Assumptions!E30,Assumptions!E31,-Assumptions!E32))*(((1+Assumptions!E30)^1-1)/Assumptions!E30),Assumptions!E32) -> 533368.01 | P54: =$O54+($AB54-$O54)*1/12 -> 530025.37 | Q54: =$O54+($AB54-$O54)*2/12 -> 526682.73 | R54: =$O54+($AB54-$O54)*3/12 -> 523340.09 | S54: =$O54+($AB54-$O54)*4/12 -> 519997.45 | T54: =$O54+($AB54-$O54)*5/12 -> 516654.81 | U54: =$O54+($AB54-$O54)*6/12 -> 513312.16 | V54: =$O54+($AB54-$O54)*7/12 -> 509969.52 | W54: =$O54+($AB54-$O54)*8/12 -> 506626.88 | X54: =$O54+($AB54-$O54)*9/12 -> 503284.24 | Y54: =$O54+($AB54-$O54)*10/12 -> 499941.6 | Z54: =$O54+($AB54-$O54)*11/12 -> 496598.96 | AA54: =$O54+($AB54-$O54)*12/12 -> 493256.32 | AB54: =IFERROR(Assumptions!E32*(1+Assumptions!E30)^2-(PMT(Assumptions!E30,Assumptions!E31,-Assumptions!E32))*(((1+Assumptions!E30)^2-1)/Assumptions!E30),Assumptions!E32) -> 493256.32 | AC54: =$AB54+($AO54-$AB54)*1/12 -> 489596.12 | AD54: =$AB54+($AO54-$AB54)*2/12 -> 485935.93 | AE54: =$AB54+($AO54-$AB54)*3/12 -> 482275.74 | AF54: =$AB54+($AO54-$AB54)*4/12 -> 478615.55 | AG54: =$AB54+($AO54-$AB54)*5/12 -> 474955.35 | AH54: =$AB54+($AO54-$AB54)*6/12 -> 471295.16 | AI54: =$AB54+($AO54-$AB54)*7/12 -> 467634.97 | AJ54: =$AB54+($AO54-$AB54)*8/12 -> 463974.78 | AK54: =$AB54+($AO54-$AB54)*9/12 -> 460314.58 | AL54: =$AB54+($AO54-$AB54)*10/12 -> 456654.39 | AM54: =$AB54+($AO54-$AB54)*11/12 -> 452994.2 | AN54: =$AB54+($AO54-$AB54)*12/12 -> 449334.01 | AO54: =IFERROR(Assumptions!E32*(1+Assumptions!E30)^3-(PMT(Assumptions!E30,Assumptions!E31,-Assumptions!E32))*(((1+Assumptions!E30)^3-1)/Assumptions!E30),Assumptions!E32) -> 449334.01 | AP54: =$AO54+($BB54-$AO54)*1/12 -> 445326.1 | AQ54: =$AO54+($BB54-$AO54)*2/12 -> 441318.19 | AR54: =$AO54+($BB54-$AO54)*3/12 -> 437310.27 | AS54: =$AO54+($BB54-$AO54)*4/12 -> 433302.36 | AT54: =$AO54+($BB54-$AO54)*5/12 -> 429294.45 | AU54: =$AO54+($BB54-$AO54)*6/12 -> 425286.54 | AV54: =$AO54+($BB54-$AO54)*7/12 -> 421278.63 | AW54: =$AO54+($BB54-$AO54)*8/12 -> 417270.72 | AX54: =$AO54+($BB54-$AO54)*9/12 -> 413262.81 | AY54: =$AO54+($BB54-$AO54)*10/12 -> 409254.9 | AZ54: =$AO54+($BB54-$AO54)*11/12 -> 405246.99 | BA54: =$AO54+($BB54-$AO54)*12/12 -> 401239.08 | BB54: =IFERROR(Assumptions!E32*(1+Assumptions!E30)^4-(PMT(Assumptions!E30,Assumptions!E31,-Assumptions!E32))*(((1+Assumptions!E30)^4-1)/Assumptions!E30),Assumptions!E32) -> 401239.08 | BC54: =$BB54+($BO54-$BB54)*1/12 -> 396850.42 | BD54: =$BB54+($BO54-$BB54)*2/12 -> 392461.75 | BE54: =$BB54+($BO54-$BB54)*3/12 -> 388073.09 | BF54: =$BB54+($BO54-$BB54)*4/12 -> 383684.43 | BG54: =$BB54+($BO54-$BB54)*5/12 -> 379295.77 | BH54: =$BB54+($BO54-$BB54)*6/12 -> 374907.11 | BI54: =$BB54+($BO54-$BB54)*7/12 -> 370518.44 | BJ54: =$BB54+($BO54-$BB54)*8/12 -> 366129.78 | BK54: =$BB54+($BO54-$BB54)*9/12 -> 361741.12 | BL54: =$BB54+($BO54-$BB54)*10/12 -> 357352.46 | BM54: =$BB54+($BO54-$BB54)*11/12 -> 352963.79 | BN54: =$BB54+($BO54-$BB54)*12/12 -> 348575.13 | BO54: =IFERROR(Assumptions!E32*(1+Assumptions!E30)^5-(PMT(Assumptions!E30,Assumptions!E31,-Assumptions!E32))*(((1+Assumptions!E30)^5-1)/Assumptions!E30),Assumptions!E32) -> 348575.13
A55: Seller Note Payable | B55: =Assumptions!E17 -> 0 | C55: =$B55+($O55-$B55)*1/12 -> 0 | D55: =$B55+($O55-$B55)*2/12 -> 0 | E55: =$B55+($O55-$B55)*3/12 -> 0 | F55: =$B55+($O55-$B55)*4/12 -> 0 | G55: =$B55+($O55-$B55)*5/12 -> 0 | H55: =$B55+($O55-$B55)*6/12 -> 0 | I55: =$B55+($O55-$B55)*7/12 -> 0 | J55: =$B55+($O55-$B55)*8/12 -> 0 | K55: =$B55+($O55-$B55)*9/12 -> 0 | L55: =$B55+($O55-$B55)*10/12 -> 0 | M55: =$B55+($O55-$B55)*11/12 -> 0 | N55: =$B55+($O55-$B55)*12/12 -> 0 | O55: =IFERROR(Assumptions!E17*(1+Assumptions!E18)^1-(PMT(Assumptions!E18,Assumptions!E19,-Assumptions!E17))*(((1+Assumptions!E18)^1-1)/Assumptions!E18),Assumptions!E17) -> 0 | P55: =$O55+($AB55-$O55)*1/12 -> 0 | Q55: =$O55+($AB55-$O55)*2/12 -> 0 | R55: =$O55+($AB55-$O55)*3/12 -> 0 | S55: =$O55+($AB55-$O55)*4/12 -> 0 | T55: =$O55+($AB55-$O55)*5/12 -> 0 | U55: =$O55+($AB55-$O55)*6/12 -> 0 | V55: =$O55+($AB55-$O55)*7/12 -> 0 | W55: =$O55+($AB55-$O55)*8/12 -> 0 | X55: =$O55+($AB55-$O55)*9/12 -> 0 | Y55: =$O55+($AB55-$O55)*10/12 -> 0 | Z55: =$O55+($AB55-$O55)*11/12 -> 0 | AA55: =$O55+($AB55-$O55)*12/12 -> 0 | AB55: =IFERROR(Assumptions!E17*(1+Assumptions!E18)^2-(PMT(Assumptions!E18,Assumptions!E19,-Assumptions!E17))*(((1+Assumptions!E18)^2-1)/Assumptions!E18),Assumptions!E17) -> 0 | AC55: =$AB55+($AO55-$AB55)*1/12 -> 0 | AD55: =$AB55+($AO55-$AB55)*2/12 -> 0 | AE55: =$AB55+($AO55-$AB55)*3/12 -> 0 | AF55: =$AB55+($AO55-$AB55)*4/12 -> 0 | AG55: =$AB55+($AO55-$AB55)*5/12 -> 0 | AH55: =$AB55+($AO55-$AB55)*6/12 -> 0 | AI55: =$AB55+($AO55-$AB55)*7/12 -> 0 | AJ55: =$AB55+($AO55-$AB55)*8/12 -> 0 | AK55: =$AB55+($AO55-$AB55)*9/12 -> 0 | AL55: =$AB55+($AO55-$AB55)*10/12 -> 0 | AM55: =$AB55+($AO55-$AB55)*11/12 -> 0 | AN55: =$AB55+($AO55-$AB55)*12/12 -> 0 | AO55: =IFERROR(Assumptions!E17*(1+Assumptions!E18)^3-(PMT(Assumptions!E18,Assumptions!E19,-Assumptions!E17))*(((1+Assumptions!E18)^3-1)/Assumptions!E18),Assumptions!E17) -> 0 | AP55: =$AO55+($BB55-$AO55)*1/12 -> 0 | AQ55: =$AO55+($BB55-$AO55)*2/12 -> 0 | AR55: =$AO55+($BB55-$AO55)*3/12 -> 0 | AS55: =$AO55+($BB55-$AO55)*4/12 -> 0 | AT55: =$AO55+($BB55-$AO55)*5/12 -> 0 | AU55: =$AO55+($BB55-$AO55)*6/12 -> 0 | AV55: =$AO55+($BB55-$AO55)*7/12 -> 0 | AW55: =$AO55+($BB55-$AO55)*8/12 -> 0 | AX55: =$AO55+($BB55-$AO55)*9/12 -> 0 | AY55: =$AO55+($BB55-$AO55)*10/12 -> 0 | AZ55: =$AO55+($BB55-$AO55)*11/12 -> 0 | BA55: =$AO55+($BB55-$AO55)*12/12 -> 0 | BB55: =IFERROR(Assumptions!E17*(1+Assumptions!E18)^4-(PMT(Assumptions!E18,Assumptions!E19,-Assumptions!E17))*(((1+Assumptions!E18)^4-1)/Assumptions!E18),Assumptions!E17) -> 0 | BC55: =$BB55+($BO55-$BB55)*1/12 -> 0 | BD55: =$BB55+($BO55-$BB55)*2/12 -> 0 | BE55: =$BB55+($BO55-$BB55)*3/12 -> 0 | BF55: =$BB55+($BO55-$BB55)*4/12 -> 0 | BG55: =$BB55+($BO55-$BB55)*5/12 -> 0 | BH55: =$BB55+($BO55-$BB55)*6/12 -> 0 | BI55: =$BB55+($BO55-$BB55)*7/12 -> 0 | BJ55: =$BB55+($BO55-$BB55)*8/12 -> 0 | BK55: =$BB55+($BO55-$BB55)*9/12 -> 0 | BL55: =$BB55+($BO55-$BB55)*10/12 -> 0 | BM55: =$BB55+($BO55-$BB55)*11/12 -> 0 | BN55: =$BB55+($BO55-$BB55)*12/12 -> 0 | BO55: =IFERROR(Assumptions!E17*(1+Assumptions!E18)^5-(PMT(Assumptions!E18,Assumptions!E19,-Assumptions!E17))*(((1+Assumptions!E18)^5-1)/Assumptions!E18),Assumptions!E17) -> 0
A56: TOTAL LIABILITIES | B56: =B54+B55 -> 569999.7 | C56: =C54+C55 -> 566947.06 | D56: =D54+D55 -> 563894.42 | E56: =E54+E55 -> 560841.78 | F56: =F54+F55 -> 557789.14 | G56: =G54+G55 -> 554736.5 | H56: =H54+H55 -> 551683.86 | I56: =I54+I55 -> 548631.22 | ... BO56: =BO54+BO55 -> 348575.13
A58: Equity
A59: Buyer Paid-in Equity | B59: 0 | C59: =$B59+($O59-$B59)*1/12 -> 0 | D59: =$B59+($O59-$B59)*2/12 -> 0 | E59: =$B59+($O59-$B59)*3/12 -> 0 | F59: =$B59+($O59-$B59)*4/12 -> 0 | G59: =$B59+($O59-$B59)*5/12 -> 0 | H59: =$B59+($O59-$B59)*6/12 -> 0 | I59: =$B59+($O59-$B59)*7/12 -> 0 | J59: =$B59+($O59-$B59)*8/12 -> 0 | K59: =$B59+($O59-$B59)*9/12 -> 0 | L59: =$B59+($O59-$B59)*10/12 -> 0 | M59: =$B59+($O59-$B59)*11/12 -> 0 | N59: =$B59+($O59-$B59)*12/12 -> 0 | O59: 0 | P59: =$O59+($AB59-$O59)*1/12 -> 0 | Q59: =$O59+($AB59-$O59)*2/12 -> 0 | R59: =$O59+($AB59-$O59)*3/12 -> 0 | S59: =$O59+($AB59-$O59)*4/12 -> 0 | T59: =$O59+($AB59-$O59)*5/12 -> 0 | U59: =$O59+($AB59-$O59)*6/12 -> 0 | V59: =$O59+($AB59-$O59)*7/12 -> 0 | W59: =$O59+($AB59-$O59)*8/12 -> 0 | X59: =$O59+($AB59-$O59)*9/12 -> 0 | Y59: =$O59+($AB59-$O59)*10/12 -> 0 | Z59: =$O59+($AB59-$O59)*11/12 -> 0 | AA59: =$O59+($AB59-$O59)*12/12 -> 0 | AB59: =+O59 -> 0 | AC59: =$AB59+($AO59-$AB59)*1/12 -> 0 | AD59: =$AB59+($AO59-$AB59)*2/12 -> 0 | AE59: =$AB59+($AO59-$AB59)*3/12 -> 0 | AF59: =$AB59+($AO59-$AB59)*4/12 -> 0 | AG59: =$AB59+($AO59-$AB59)*5/12 -> 0 | AH59: =$AB59+($AO59-$AB59)*6/12 -> 0 | AI59: =$AB59+($AO59-$AB59)*7/12 -> 0 | AJ59: =$AB59+($AO59-$AB59)*8/12 -> 0 | AK59: =$AB59+($AO59-$AB59)*9/12 -> 0 | AL59: =$AB59+($AO59-$AB59)*10/12 -> 0 | AM59: =$AB59+($AO59-$AB59)*11/12 -> 0 | AN59: =$AB59+($AO59-$AB59)*12/12 -> 0 | AO59: =+AB59 -> 0 | AP59: =$AO59+($BB59-$AO59)*1/12 -> 0 | AQ59: =$AO59+($BB59-$AO59)*2/12 -> 0 | AR59: =$AO59+($BB59-$AO59)*3/12 -> 0 | AS59: =$AO59+($BB59-$AO59)*4/12 -> 0 | AT59: =$AO59+($BB59-$AO59)*5/12 -> 0 | AU59: =$AO59+($BB59-$AO59)*6/12 -> 0 | AV59: =$AO59+($BB59-$AO59)*7/12 -> 0 | AW59: =$AO59+($BB59-$AO59)*8/12 -> 0 | AX59: =$AO59+($BB59-$AO59)*9/12 -> 0 | AY59: =$AO59+($BB59-$AO59)*10/12 -> 0 | AZ59: =$AO59+($BB59-$AO59)*11/12 -> 0 | BA59: =$AO59+($BB59-$AO59)*12/12 -> 0 | BB59: =+AO59 -> 0 | BC59: =$BB59+($BO59-$BB59)*1/12 -> 0 | BD59: =$BB59+($BO59-$BB59)*2/12 -> 0 | BE59: =$BB59+($BO59-$BB59)*3/12 -> 0 | BF59: =$BB59+($BO59-$BB59)*4/12 -> 0 | BG59: =$BB59+($BO59-$BB59)*5/12 -> 0 | BH59: =$BB59+($BO59-$BB59)*6/12 -> 0 | BI59: =$BB59+($BO59-$BB59)*7/12 -> 0 | BJ59: =$BB59+($BO59-$BB59)*8/12 -> 0 | BK59: =$BB59+($BO59-$BB59)*9/12 -> 0 | BL59: =$BB59+($BO59-$BB59)*10/12 -> 0 | BM59: =$BB59+($BO59-$BB59)*11/12 -> 0 | BN59: =$BB59+($BO59-$BB59)*12/12 -> 0 | BO59: =+BB59 -> 0
A60: Retained Earnings | B60: =0 -> 0 | C60: =$B60+($O60-$B60)*1/12 -> 6475.895 | D60: =$B60+($O60-$B60)*2/12 -> 12951.79 | E60: =$B60+($O60-$B60)*3/12 -> 19427.685 | F60: =$B60+($O60-$B60)*4/12 -> 25903.58 | G60: =$B60+($O60-$B60)*5/12 -> 32379.475 | H60: =$B60+($O60-$B60)*6/12 -> 38855.37 | I60: =$B60+($O60-$B60)*7/12 -> 45331.265 | J60: =$B60+($O60-$B60)*8/12 -> 51807.16 | K60: =$B60+($O60-$B60)*9/12 -> 58283.055 | L60: =$B60+($O60-$B60)*10/12 -> 64758.95 | M60: =$B60+($O60-$B60)*11/12 -> 71234.845 | N60: =$B60+($O60-$B60)*12/12 -> 77710.74 | O60: =B60+O36-O39 -> 77710.74 | P60: =$O60+($AB60-$O60)*1/12 -> 81042.92 | Q60: =$O60+($AB60-$O60)*2/12 -> 84375.1 | R60: =$O60+($AB60-$O60)*3/12 -> 87707.28 | S60: =$O60+($AB60-$O60)*4/12 -> 91039.46 | T60: =$O60+($AB60-$O60)*5/12 -> 94371.639 | U60: =$O60+($AB60-$O60)*6/12 -> 97703.819 | V60: =$O60+($AB60-$O60)*7/12 -> 101036 | W60: =$O60+($AB60-$O60)*8/12 -> 104368.18 | X60: =$O60+($AB60-$O60)*9/12 -> 107700.36 | Y60: =$O60+($AB60-$O60)*10/12 -> 111032.54 | Z60: =$O60+($AB60-$O60)*11/12 -> 114364.72 | AA60: =$O60+($AB60-$O60)*12/12 -> 117696.9 | AB60: =O60+AB36-AB39 -> 117696.9 | AC60: =$AB60+($AO60-$AB60)*1/12 -> 121753.49 | AD60: =$AB60+($AO60-$AB60)*2/12 -> 125810.09 | AE60: =$AB60+($AO60-$AB60)*3/12 -> 129866.68 | AF60: =$AB60+($AO60-$AB60)*4/12 -> 133923.27 | AG60: =$AB60+($AO60-$AB60)*5/12 -> 137979.87 | AH60: =$AB60+($AO60-$AB60)*6/12 -> 142036.46 | AI60: =$AB60+($AO60-$AB60)*7/12 -> 146093.05 | AJ60: =$AB60+($AO60-$AB60)*8/12 -> 150149.65 | AK60: =$AB60+($AO60-$AB60)*9/12 -> 154206.24 | AL60: =$AB60+($AO60-$AB60)*10/12 -> 158262.84 | AM60: =$AB60+($AO60-$AB60)*11/12 -> 162319.43 | AN60: =$AB60+($AO60-$AB60)*12/12 -> 166376.02 | AO60: =AB60+AO36-AO39 -> 166376.02 | AP60: =$AO60+($BB60-$AO60)*1/12 -> 171188.04 | AQ60: =$AO60+($BB60-$AO60)*2/12 -> 176000.05 | AR60: =$AO60+($BB60-$AO60)*3/12 -> 180812.07 | AS60: =$AO60+($BB60-$AO60)*4/12 -> 185624.08 | AT60: =$AO60+($BB60-$AO60)*5/12 -> 190436.1 | AU60: =$AO60+($BB60-$AO60)*6/12 -> 195248.11 | AV60: =$AO60+($BB60-$AO60)*7/12 -> 200060.13 | AW60: =$AO60+($BB60-$AO60)*8/12 -> 204872.15 | AX60: =$AO60+($BB60-$AO60)*9/12 -> 209684.16 | AY60: =$AO60+($BB60-$AO60)*10/12 -> 214496.18 | AZ60: =$AO60+($BB60-$AO60)*11/12 -> 219308.19 | BA60: =$AO60+($BB60-$AO60)*12/12 -> 224120.21 | BB60: =AO60+BB36-BB39 -> 224120.21 | BC60: =$BB60+($BO60-$BB60)*1/12 -> 229719.22 | BD60: =$BB60+($BO60-$BB60)*2/12 -> 235318.24 | BE60: =$BB60+($BO60-$BB60)*3/12 -> 240917.25 | BF60: =$BB60+($BO60-$BB60)*4/12 -> 246516.26 | BG60: =$BB60+($BO60-$BB60)*5/12 -> 252115.28 | BH60: =$BB60+($BO60-$BB60)*6/12 -> 257714.29 | BI60: =$BB60+($BO60-$BB60)*7/12 -> 263313.31 | BJ60: =$BB60+($BO60-$BB60)*8/12 -> 268912.32 | BK60: =$BB60+($BO60-$BB60)*9/12 -> 274511.34 | BL60: =$BB60+($BO60-$BB60)*10/12 -> 280110.35 | BM60: =$BB60+($BO60-$BB60)*11/12 -> 285709.37 | BN60: =$BB60+($BO60-$BB60)*12/12 -> 291308.38 | BO60: =BB60+BO36-BO39 -> 291308.38
A61: TOTAL EQUITY | B61: =B59+B60 -> 0 | C61: =C59+C60 -> 6475.895 | D61: =D59+D60 -> 12951.79 | E61: =E59+E60 -> 19427.685 | F61: =F59+F60 -> 25903.58 | G61: =G59+G60 -> 32379.475 | H61: =H59+H60 -> 38855.37 | I61: =I59+I60 -> 45331.265 | ... BO61: =BO59+BO60 -> 291308.38
A62: TOTAL LIABILITIES & EQUITY | B62: =B56+B61 -> 569999.7 | C62: =C56+C61 -> 573422.95 | D62: =D56+D61 -> 576846.21 | E62: =E56+E61 -> 580269.46 | F62: =F56+F61 -> 583692.72 | G62: =G56+G61 -> 587115.97 | H62: =H56+H61 -> 590539.23 | I62: =I56+I61 -> 593962.48 | ... BO62: =BO56+BO61 -> 639883.51
